Workbook

Sheet Início
A1: PLANILHA DE CONTROLE E PRESCRIÇÃO DE TREINAMENTO • VOLEIBOL
A2: Periodização Macrociclo → Mesociclo → Microciclo → Sessão | Controle de carga por PSE da sessão, ACWR, Monotonia/Strain e Wellness
B4: COMO USAR — PASSO A PASSO
B5: 1. Listas | C5: Opções de todos os menus suspensos (posições, escolaridade, renda, tipos de sessão, superfícies…).
B6: 2. Cadastro | C6: Ficha completa do atleta: identificação, contato, SOCIOECONÔMICO, histórico esportivo e saúde.
B7: 3. Antropometria | C7: Avaliações longitudinais no perfil ISAK: dobras, perímetros, diâmetros, % de gordura e somatotipo.
B8: 4. Testes | C8: Bateria física: alcances e impulsões, SJ, CMJ, drop jump com RSI, sprint, agilidade e IMTP.
B9: 5. Perfil F-V-P | C9: Perfil força-velocidade-potência pelo salto com carga: F0, V0, Pmax e desequilíbrio F-V.
B10: 6. Exercícios | C10: Biblioteca com 89 exercícios, incluindo todos os do seu documento de Preparação Física.
B11: 7. Programa PF | C11: As 8 séries do seu documento 'Preparação Física 2026/2027', na íntegra.
B12: 8. Macrociclo | C12: A temporada dividida em mesociclos, com dinâmica de volume e intensidade.
B13: 9. Mesociclo | C13: Microciclos do mesociclo escolhido, com carga prevista × realizada.
B14: 10. Bloco Base | C14: PERIODIZAÇÃO EM BLOCOS: as 8 semanas de base (força máxima, LPO, agachamento e pliometria).
B15: 11. Microciclo | C15: A semana de quadra: sessões por dia e distribuição de conteúdos.
B16: 12. Prescrição | C16: Prescrição do treino técnico-tático, por equipe ou por atleta.
... B26: 22. Evidências | C26: 60 referências científicas que sustentam cada escolha metodológica da planilha.
B28: LEGENDA DE CORES
B29: Célula de PREENCHIMENTO (azul sobre amarelo)
B30: Célula CALCULADA — não digite por cima
B31: Cabeçalho de tabela
B32: Alerta / risco elevado
B33: Atenção / monitorar
B34: Adequado / dentro da meta
B36: MÉTRICAS DE CONTROLE UTILIZADAS — DEFINIÇÕES E REFERÊNCIAS
B37: Carga Interna (UA) | C37: Duração da sessão (min) × PSE da sessão (escala 0–10, coletada ~30 min após o treino). Método da PSE da sessão de Foster et al. (2001), J Strength Cond Res.
B38: Carga Aguda (7 d) | C38: Soma da carga em UA dos últimos 7 dias do atleta (inclui o dia atual).
B39: Carga Crônica (28 d) | C39: Soma da carga dos últimos 28 dias ÷ 4 (média semanal), para ficar na mesma escala da aguda.
B40: ACWR | C40: Carga Aguda ÷ Carga Crônica. Faixas usadas na planilha: <0,80 subcarga | 0,80–1,30 zona ideal | 1,31–1,50 atenção | >1,50 risco elevado. Referência: Gabbett (2016), Br J Sports Med. Interpretar sempre junto do contexto e da clínica do atleta.
B41: Monotonia | C41: Média das cargas diárias da semana ÷ desvio-padrão dessas mesmas cargas (7 dias, dias de folga contam como zero). >2,0 indica semana monótona.
B42: Strain | C42: Carga semanal total × Monotonia. Picos de strain associam-se a maior risco de lesão/doença (Foster, 1998).
B43: Índice de Hooper | C43: Soma de 4 itens (qualidade do sono, estresse, fadiga e dor muscular), cada um de 1 = muito bom/ausente a 7 = muito ruim/máxima. Varia de 4 a 28; QUANTO MAIOR, PIOR. Referência: Hooper & Mackinnon (1995), Sports Med.
B44: Volume × Intensidade | C44: No Macrociclo, valores em % representam a proporção relativa planejada para cada mesociclo (ex.: 85% = volume alto).
B45: Tonelagem | C45: Séries × repetições × carga usada, em kg. É o volume-carga do treino de força; some por sessão, semana e bloco.
B46: Intensidade média relativa | C46: Média dos %1RM prescritos, ponderada pelo número de repetições de cada exercício. Mostra o quanto a semana foi 'pesada' de verdade.
B47: Perda de velocidade | C47: Queda percentual da velocidade da barra dentro da série. Limiares ≤ 25% favorecem força; acima de 20–25% favorecem hipertrofia (Hickmott et al., 2022).
B48: F0, V0 e Pmax | C48: Força teórica máxima, velocidade teórica máxima e potência máxima estimadas por regressão linear a partir de saltos com cargas progressivas (Morin & Samozino, 2016).
... B52: Somatotipo | C52: Endomorfia, mesomorfia e ectomorfia pelo método Heath-Carter, a partir de dobras, perímetros, diâmetros, estatura e massa.
B54: ATENÇÃO — DADOS DE EXEMPLO: a planilha vem preenchida com 12 atletas fictícios, um macrociclo modelo e registros de carga/wellness/presença apenas para demonstrar os cálculos e os gráficos. Apague esses dados (linhas marcadas como EXEMPLO) antes de usar com a sua equipe. As fórmulas permanecem intactas. AVISO: esta planilha é uma ferramenta de organização do treino. Não substitui avaliação médica nem fisioterápica; os indicadores de risco são apoio à decisão do técnico/preparador físico.

Sheet Cadastro
A1: CADASTRO DE ATLETAS — FICHA COMPLETA
A2: Uma linha por atleta. Blocos: Identificação · Antropometria (puxada da aba Antropometria) · Contato · Socioeconômico · Histórico Esportivo · Saúde · Situação.
B4: LGPD — esta aba armazena dados pessoais e de saúde (dados sensíveis). Colete somente o necessário, com consentimento por escrito do atleta (ou do responsável, se menor), e restrinja o acesso ao arquivo. Por decisão do usuário, NENHUM dado financeiro do atleta é registrado aqui.
A6: IDENTIFICAÇÃO | M6: ANTROPOMETRIA (puxada da aba Antropometria) | R6: CONTATO | Z6: SOCIOECONÔMICO | AS6: HISTÓRICO ESPORTIVO | AY6: SAÚDE | BK6: SITUAÇÃO
A7: ID | B7: Nome Completo | C7: Nome na Equipe | D7: Data de Nasc. | E7: Idade | F7: Sexo | G7: Nacionalidade | H7: Naturalidade (Cidade/UF) | I7: Documento (RG/CPF) | J7: Nº Camisa | K7: Categoria | L7: Posição | M7: Dominância de Mão | N7: Perna de Impulsão | O7: Estatura (cm) | P7: Massa (kg) | Q7: IMC | R7: Telefone | S7: E-mail | T7: Endereço | U7: Cidade / UF | V7: CEP | W7: Contato de Emergência | X7: Telefone de Emergência | Y7: Parentesco | Z7: Escolaridade | AA7: Situação de Estudo | AB7: Turno de Estudo | AC7: Instituição de Ensino | AD7: Trabalha? | AE7: Horas de Trabalho / Semana | AF7: Ocupação | AG7: Nº de Pessoas no Domicílio | AH7: Classe Econômica (Critério Brasil) | AI7: Tipo de Moradia | AJ7: Reside com | AK7: Transporte para o Treino | AL7: Tempo de Deslocamento (min) | AM7: Recebe Bolsa / Auxílio? | AN7: Benefício Social | AO7: Plano de Saúde | AP7: Acesso à Internet em Casa | AQ7: Refeições por Dia | AR7: Acompanhamento Nutricional | AS7: Idade de Início no Vôlei | AT7: Anos de Prática | AU7: Anos de Treino de Força | AV7: Nível Competitivo Máximo | AW7: Clubes Anteriores | AX7: Seleções / Convocações | AY7: Tipo Sanguíneo | AZ7: Alergias | BA7: Medicamentos em Uso | BB7: Cirurgias Prévias | BC7: Lesões Prévias (região) | BD7: Nº de Lesões (12 meses) | BE7: Queixa / Dor Atual | BF7: Data do Atestado Médico | BG7: Validade do Atestado | BH7: Situação do Atestado | BI7: PAR-Q Respondido? | BJ7: Usa Óculos / Lentes? | BK7: Data de Entrada na Equipe | BL7: Status | BM7: Observações | BN7: últ. aval.
A8: =IF($B8="","","ATL-"&TEXT(ROW()-7,"000")) -> ATL-001 | B8: Rafael Monteiro Alves | C8: Rafa | D8: 35868 | E8: =IFERROR(DATEDIF($D8,TODAY(),"Y"),"") -> 28 | F8: Masculino | G8: Brasileira | H8: — | I8: — | J8: 5 | K8: Adulto | L8: Levantador | M8: Destro | N8: Esquerda | O8: =IF(OR($B8="",$BN8=0),"",IFERROR(AVERAGEIFS(Antropometria!$F$8:$F$407,Antropometria!$B$8:$B$407,$B8,Antropometria!$A$8:$A$407,$BN8),"")) -> 196 | P8: =IF(OR($B8="",$BN8=0),"",IFERROR(AVERAGEIFS(Antropometria!$E$8:$E$407,Antropometria!$B$8:$B$407,$B8,Antropometria!$A$8:$A$407,$BN8),"")) -> 87.8 | Q8: =IFERROR(ROUND($P8/($O8/100)^2,1),"") -> 22.9 | R8: (00) 90000-0001 | S8: atleta1@elase.com.br | T8: — | U8: — | V8: — | W8: Responsável / familiar | X8: (00) 90000-1001 | Y8: — | Z8: Superior em andamento | AA8: Cursando | AB8: Noturno | AC8: — | AD8: Não | AE8: 0 | AF8: Atleta profissional | AG8: 3 | AH8: B1 | AI8: Própria | AJ8: Família | AK8: Carro próprio | AL8: 25 | AM8: Sim | AN8: Não | AO8: Sim | AP8: Sim | AQ8: 6 | AR8: Sim | AS8: 11 | AT8: =IFERROR($E8-$AS8,"") -> 17 | AU8: 4 | AV8: Superliga A | AW8: — | AX8: Seleção estadual | AY8: O+ | AZ8: — | BA8: — | BB8: — | BC8: — | BD8: 0 | BE8: — | BF8: 46034 | BG8: 46399 | BH8: =IF($BG8="","",IF($BG8<TODAY(),"VENCIDO",IF($BG8<=TODAY()+30,"Vence em 30 dias","Válido"))) -> Válido | BI8: Sim | BJ8: Sim | BK8: 46027 | BL8: Ativo | BM8: EXEMPLO — substituir | BN8: =IF($B8="",0,IFERROR(SUMPRODUCT(MAX((Antropometria!$B$8:$B$407=$B8)*Antropometria!$A$8:$A$407)),0)) -> 46225
A9: =IF($B9="","","ATL-"&TEXT(ROW()-7,"000")) -> ATL-002 | B9: Diego Salgado Ferraz | C9: Diego | D9: 35279 | E9: =IFERROR(DATEDIF($D9,TODAY(),"Y"),"") -> 30 | F9: Masculino | G9: Brasileira | H9: — | I9: — | J9: 12 | K9: Adulto | L9: Oposto | M9: Canhoto | N9: Esquerda | O9: =IF(OR($B9="",$BN9=0),"",IFERROR(AVERAGEIFS(Antropometria!$F$8:$F$407,Antropometria!$B$8:$B$407,$B9,Antropometria!$A$8:$A$407,$BN9),"")) -> 202 | P9: =IF(OR($B9="",$BN9=0),"",IFERROR(AVERAGEIFS(Antropometria!$E$8:$E$407,Antropometria!$B$8:$B$407,$B9,Antropometria!$A$8:$A$407,$BN9),"")) -> 94.2 | Q9: =IFERROR(ROUND($P9/($O9/100)^2,1),"") -> 23.1 | R9: (00) 90000-0002 | S9: atleta2@elase.com.br | T9: — | U9: — | V9: — | W9: Responsável / familiar | X9: (00) 90000-1002 | Y9: — | Z9: Superior completo | AA9: Concluído | AB9: — | AC9: — | AD9: Não | AE9: 0 | AF9: Atleta profissional | AG9: 2 | AH9: B1 | AI9: Alugada | AJ9: Cônjuge | AK9: Carro próprio | AL9: 20 | AM9: Sim | AN9: Não | AO9: Sim | AP9: Sim | AQ9: 6 | AR9: Sim | AS9: 12 | AT9: =IFERROR($E9-$AS9,"") -> 18 | AU9: 6 | AV9: Superliga B | AW9: — | AX9: Seleção nacional Sub-21 | AY9: O+ | AZ9: — | BA9: — | BB9: — | BC9: Entorse de tornozelo D | BD9: 1 | BE9: — | BF9: 46034 | BG9: 46399 | BH9: =IF($BG9="","",IF($BG9<TODAY(),"VENCIDO",IF($BG9<=TODAY()+30,"Vence em 30 dias","Válido"))) -> Válido | BI9: Sim | BJ9: Não | BK9: 46027 | BL9: Ativo | BM9: EXEMPLO — substituir | BN9: =IF($B9="",0,IFERROR(SUMPRODUCT(MAX((Antropometria!$B$8:$B$407=$B9)*Antropometria!$A$8:$A$407)),0)) -> 46225
A10: =IF($B10="","","ATL-"&TEXT(ROW()-7,"000")) -> ATL-003 | B10: Lucas Prado Bittencourt | C10: Lucas | D10: 36552 | E10: =IFERROR(DATEDIF($D10,TODAY(),"Y"),"") -> 26 | F10: Masculino | G10: Brasileira | H10: — | I10: — | J10: 7 | K10: Adulto | L10: Ponteiro (Ponta) | M10: Destro | N10: Esquerda | O10: =IF(OR($B10="",$BN10=0),"",IFERROR(AVERAGEIFS(Antropometria!$F$8:$F$407,Antropometria!$B$8:$B$407,$B10,Antropometria!$A$8:$A$407,$BN10),"")) -> 198 | P10: =IF(OR($B10="",$BN10=0),"",IFERROR(AVERAGEIFS(Antropometria!$E$8:$E$407,Antropometria!$B$8:$B$407,$B10,Antropometria!$A$8:$A$407,$BN10),"")) -> 88.9 | Q10: =IFERROR(ROUND($P10/($O10/100)^2,1),"") -> 22.7 | R10: (00) 90000-0003 | S10: atleta3@elase.com.br | T10: — | U10: — | V10: — | W10: Responsável / familiar | X10: (00) 90000-1003 | Y10: — | Z10: Superior em andamento | AA10: Cursando | AB10: Matutino | AC10: — | AD10: Não | AE10: 0 | AF10: Atleta profissional | AG10: 4 | AH10: B2 | AI10: Própria | AJ10: Família | AK10: Transporte do clube | AL10: 35 | AM10: Sim | AN10: Não | AO10: Sim | AP10: Sim | AQ10: 5 | AR10: Sim | AS10: 13 | AT10: =IFERROR($E10-$AS10,"") -> 13 | AU10: 3 | AV10: Superliga B | AW10: — | AX10: Seleção estadual | AY10: O+ | AZ10: — | BA10: — | BB10: — | BC10: — | BD10: 0 | BE10: — | BF10: 46034 | BG10: 46399 | BH10: =IF($BG10="","",IF($BG10<TODAY(),"VENCIDO",IF($BG10<=TODAY()+30,"Vence em 30 dias","Válido"))) -> Válido | BI10: Sim | BJ10: Não | BK10: 46027 | BL10: Ativo | BM10: EXEMPLO — substituir | BN10: =IF($B10="",0,IFERROR(SUMPRODUCT(MAX((Antropometria!$B$8:$B$407=$B10)*Antropometria!$A$8:$A$407)),0)) -> 46225
A11: =IF($B11="","","ATL-"&TEXT(ROW()-7,"000")) -> ATL-004 | B11: Bruno Rezende Camargo | C11: Bruninho | D11: 36469 | E11: =IFERROR(DATEDIF($D11,TODAY(),"Y"),"") -> 26 | F11: Masculino | G11: Brasileira | H11: — | I11: — | J11: 9 | K11: Adulto | L11: Ponteiro (Ponta) | M11: Destro | N11: Esquerda | O11: =IF(OR($B11="",$BN11=0),"",IFERROR(AVERAGEIFS(Antropometria!$F$8:$F$407,Antropometria!$B$8:$B$407,$B11,Antropometria!$A$8:$A$407,$BN11),"")) -> 197 | P11: =IF(OR($B11="",$BN11=0),"",IFERROR(AVERAGEIFS(Antropometria!$E$8:$E$407,Antropometria!$B$8:$B$407,$B11,Antropometria!$A$8:$A$407,$BN11),"")) -> 87.7 | Q11: =IFERROR(ROUND($P11/($O11/100)^2,1),"") -> 22.6 | R11: (00) 90000-0004 | S11: atleta4@elase.com.br | T11: — | U11: — | V11: — | W11: Responsável / familiar | X11: (00) 90000-1004 | Y11: — | Z11: Superior em andamento | AA11: Cursando | AB11: Noturno | AC11: — | AD11: Sim | AE11: 20 | AF11: Estagiário | AG11: 4 | AH11: C1 | AI11: Alugada | AJ11: Família | AK11: Transporte público | AL11: 55 | AM11: Sim | AN11: Sim | AO11: Não | AP11: Sim | AQ11: 4 | AR11: Não | AS11: 12 | AT11: =IFERROR($E11-$AS11,"") -> 14 | AU11: 3 | AV11: Superliga A | AW11: — | AX11: — | AY11: O+ | AZ11: — | BA11: — | BB11: — | BC11: Tendinopatia patelar | BD11: 2 | BE11: Dor anterior no joelho D (leve) | BF11: 46034 | BG11: 46399 | BH11: =IF($BG11="","",IF($BG11<TODAY(),"VENCIDO",IF($BG11<=TODAY()+30,"Vence em 30 dias","Válido"))) -> Válido | BI11: Sim | BJ11: Não | BK11: 46027 | BL11: Lesionado | BM11: EXEMPLO — substituir | BN11: =IF($B11="",0,IFERROR(SUMPRODUCT(MAX((Antropometria!$B$8:$B$407=$B11)*Antropometria!$A$8:$A$407)),0)) -> 46225
A12: =IF($B12="","","ATL-"&TEXT(ROW()-7,"000")) -> ATL-005 | B12: Thiago Nogueira Vasques | C12: Thiago | D12: 34838 | E12: =IFERROR(DATEDIF($D12,TODAY(),"Y"),"") -> 31 | F12: Masculino | G12: Brasileira | H12: — | I12: — | J12: 4 | K12: Adulto | L12: Central | M12: Destro | N12: Direita | O12: =IF(OR($B12="",$BN12=0),"",IFERROR(AVERAGEIFS(Antropometria!$F$8:$F$407,Antropometria!$B$8:$B$407,$B12,Antropometria!$A$8:$A$407,$BN12),"")) -> 205 | P12: =IF(OR($B12="",$BN12=0),"",IFERROR(AVERAGEIFS(Antropometria!$E$8:$E$407,Antropometria!$B$8:$B$407,$B12,Antropometria!$A$8:$A$407,$BN12),"")) -> 99.7 | Q12: =IFERROR(ROUND($P12/($O12/100)^2,1),"") -> 23.7 | R12: (00) 90000-0005 | S12: atleta5@elase.com.br | T12: — | U12: — | V12: — | W12: Responsável / familiar | X12: (00) 90000-1005 | Y12: — | Z12: Superior completo | AA12: Concluído | AB12: — | AC12: — | AD12: Não | AE12: 0 | AF12: Atleta profissional | AG12: 3 | AH12: A | AI12: Própria | AJ12: Família | AK12: Carro próprio | AL12: 18 | AM12: Sim | AN12: Não | AO12: Sim | AP12: Sim | AQ12: 6 | AR12: Sim | AS12: 10 | AT12: =IFERROR($E12-$AS12,"") -> 21 | AU12: 8 | AV12: Superliga B | AW12: — | AX12: Seleção nacional adulta | AY12: O+ | AZ12: — | BA12: — | BB12: — | BC12: Lombalgia | BD12: 1 | BE12: — | BF12: 46034 | BG12: 46399 | BH12: =IF($BG12="","",IF($BG12<TODAY(),"VENCIDO",IF($BG12<=TODAY()+30,"Vence em 30 dias","Válido"))) -> Válido | BI12: Sim | BJ12: Sim | BK12: 46027 | BL12: Ativo | BM12: EXEMPLO — substituir | BN12: =IF($B12="",0,IFERROR(SUMPRODUCT(MAX((Antropometria!$B$8:$B$407=$B12)*Antropometria!$A$8:$A$407)),0)) -> 46225
A13: =IF($B13="","","ATL-"&TEXT(ROW()-7,"000")) -> ATL-006 | B13: Matheus Caldeira Lins | C13: Matheus | D13: 37142 | E13: =IFERROR(DATEDIF($D13,TODAY(),"Y"),"") -> 24 | F13: Masculino | G13: Brasileira | H13: — | I13: — | J13: 15 | K13: Adulto | L13: Central | M13: Destro | N13: Esquerda | O13: =IF(OR($B13="",$BN13=0),"",IFERROR(AVERAGEIFS(Antropometria!$F$8:$F$407,Antropometria!$B$8:$B$407,$B13,Antropometria!$A$8:$A$407,$BN13),"")) -> 203 | P13: =IF(OR($B13="",$BN13=0),"",IFERROR(AVERAGEIFS(Antropometria!$E$8:$E$407,Antropometria!$B$8:$B$407,$B13,Antropometria!$A$8:$A$407,$BN13),"")) -> 94.9 | Q13: =IFERROR(ROUND($P13/($O13/100)^2,1),"") -> 23 | R13: (00) 90000-0006 | S13: atleta6@elase.com.br | T13: — | U13: — | V13: — | W13: Responsável / familiar | X13: (00) 90000-1006 | Y13: — | Z13: Superior em andamento | AA13: Cursando | AB13: Noturno | AC13: — | AD13: Não | AE13: 0 | AF13: Atleta profissional | AG13: 5 | AH13: C1 | AI13: Cedida | AJ13: Alojamento do clube | AK13: A pé | AL13: 10 | AM13: Sim | AN13: Sim | AO13: Sim | AP13: Sim | AQ13: 5 | AR13: Sim | AS13: 14 | AT13: =IFERROR($E13-$AS13,"") -> 10 | AU13: 2 | AV13: Superliga B | AW13: — | AX13: — | AY13: O+ | AZ13: — | BA13: — | BB13: — | BC13: — | BD13: 0 | BE13: — | BF13: 46034 | BG13: 46399 | BH13: =IF($BG13="","",IF($BG13<TODAY(),"VENCIDO",IF($BG13<=TODAY()+30,"Vence em 30 dias","Válido"))) -> Válido | BI13: Sim | BJ13: Não | BK13: 46027 | BL13: Ativo | BM13: EXEMPLO — substituir | BN13: =IF($B13="",0,IFERROR(SUMPRODUCT(MAX((Antropometria!$B$8:$B$407=$B13)*Antropometria!$A$8:$A$407)),0)) -> 46225
A14: =IF($B14="","","ATL-"&TEXT(ROW()-7,"000")) -> ATL-007 | B14: Felipe Andrade Rocha | C14: Felipão | D14: 37663 | E14: =IFERROR(DATEDIF($D14,TODAY(),"Y"),"") -> 23 | F14: Masculino | G14: Brasileira | H14: — | I14: — | J14: 2 | K14: Adulto | L14: Líbero | M14: Destro | N14: Direita | O14: =IF(OR($B14="",$BN14=0),"",IFERROR(AVERAGEIFS(Antropometria!$F$8:$F$407,Antropometria!$B$8:$B$407,$B14,Antropometria!$A$8:$A$407,$BN14),"")) -> 184 | P14: =IF(OR($B14="",$BN14=0),"",IFERROR(AVERAGEIFS(Antropometria!$E$8:$E$407,Antropometria!$B$8:$B$407,$B14,Antropometria!$A$8:$A$407,$BN14),"")) -> 79 | Q14: =IFERROR(ROUND($P14/($O14/100)^2,1),"") -> 23.3 | R14: (00) 90000-0007 | S14: atleta7@elase.com.br | T14: — | U14: — | V14: — | W14: Responsável / familiar | X14: (00) 90000-1007 | Y14: — | Z14: Superior em andamento | AA14: Cursando | AB14: Matutino | AC14: — | AD14: Não | AE14: 0 | AF14: Atleta profissional | AG14: 4 | AH14: C2 | AI14: Alugada | AJ14: Alojamento do clube | AK14: Transporte do clube | AL14: 30 | AM14: Sim | AN14: Sim | AO14: Não | AP14: Sim | AQ14: 5 | AR14: Sim | AS14: 12 | AT14: =IFERROR($E14-$AS14,"") -> 11 | AU14: 2 | AV14: Superliga A | AW14: — | AX14: Seleção estadual Sub-19 | AY14: O+ | AZ14: — | BA14: — | BB14: — | BC14: Entorse de tornozelo E | BD14: 1 | BE14: — | BF14: 46034 | BG14: 46399 | BH14: =IF($BG14="","",IF($BG14<TODAY(),"VENCIDO",IF($BG14<=TODAY()+30,"Vence em 30 dias","Válido"))) -> Válido | BI14: Sim | BJ14: Não | BK14: 46027 | BL14: Ativo | BM14: EXEMPLO — substituir | BN14: =IF($B14="",0,IFERROR(SUMPRODUCT(MAX((Antropometria!$B$8:$B$407=$B14)*Antropometria!$A$8:$A$407)),0)) -> 46225
A15: =IF($B15="","","ATL-"&TEXT(ROW()-7,"000")) -> ATL-008 | B15: Gustavo Peixoto Maia | C15: Gu | D15: 35634 | E15: =IFERROR(DATEDIF($D15,TODAY(),"Y"),"") -> 29 | F15: Masculino | G15: Brasileira | H15: — | I15: — | J15: 11 | K15: Adulto | L15: Ponteiro (Ponta) | M15: Destro | N15: Esquerda | O15: =IF(OR($B15="",$BN15=0),"",IFERROR(AVERAGEIFS(Antropometria!$F$8:$F$407,Antropometria!$B$8:$B$407,$B15,Antropometria!$A$8:$A$407,$BN15),"")) -> 199 | P15: =IF(OR($B15="",$BN15=0),"",IFERROR(AVERAGEIFS(Antropometria!$E$8:$E$407,Antropometria!$B$8:$B$407,$B15,Antropometria!$A$8:$A$407,$BN15),"")) -> 90.4 | Q15: =IFERROR(ROUND($P15/($O15/100)^2,1),"") -> 22.8 | R15: (00) 90000-0008 | S15: atleta8@elase.com.br | T15: — | U15: — | V15: — | W15: Responsável / familiar | X15: (00) 90000-1008 | Y15: — | Z15: Superior completo | AA15: Concluído | AB15: — | AC15: — | AD15: Não | AE15: 0 | AF15: Atleta profissional | AG15: 2 | AH15: B1 | AI15: Própria | AJ15: Cônjuge | AK15: Carro próprio | AL15: 22 | AM15: Sim | AN15: Não | AO15: Sim | AP15: Sim | AQ15: 6 | AR15: Sim | AS15: 11 | AT15: =IFERROR($E15-$AS15,"") -> 18 | AU15: 7 | AV15: Superliga B | AW15: — | AX15: — | AY15: O+ | AZ15: — | BA15: — | BB15: — | BC15: Tendinopatia de ombro D | BD15: 1 | BE15: — | BF15: 46034 | BG15: 46399 | BH15: =IF($BG15="","",IF($BG15<TODAY(),"VENCIDO",IF($BG15<=TODAY()+30,"Vence em 30 dias","Válido"))) -> Válido | BI15: Sim | BJ15: Não | BK15: 46027 | BL15: Ativo | BM15: EXEMPLO — substituir | BN15: =IF($B15="",0,IFERROR(SUMPRODUCT(MAX((Antropometria!$B$8:$B$407=$B15)*Antropometria!$A$8:$A$407)),0)) -> 46225
A16: =IF($B16="","","ATL-"&TEXT(ROW()-7,"000")) -> ATL-009 | B16: Vinícius Barreto Duarte | C16: Vini | D16: 37593 | E16: =IFERROR(DATEDIF($D16,TODAY(),"Y"),"") -> 23 | F16: Masculino | G16: Brasileira | H16: — | I16: — | J16: 6 | K16: Adulto | L16: Levantador | M16: Destro | N16: Esquerda | O16: =IF(OR($B16="",$BN16=0),"",IFERROR(AVERAGEIFS(Antropometria!$F$8:$F$407,Antropometria!$B$8:$B$407,$B16,Antropometria!$A$8:$A$407,$BN16),"")) -> 192 | P16: =IF(OR($B16="",$BN16=0),"",IFERROR(AVERAGEIFS(Antropometria!$E$8:$E$407,Antropometria!$B$8:$B$407,$B16,Antropometria!$A$8:$A$407,$BN16),"")) -> 82.5 | Q16: =IFERROR(ROUND($P16/($O16/100)^2,1),"") -> 22.4 | R16: (00) 90000-0009 | S16: atleta9@elase.com.br | T16: — | U16: — | V16: — | W16: Responsável / familiar | X16: (00) 90000-1009 | Y16: — | Z16: Superior em andamento | AA16: Cursando | AB16: Noturno | AC16: — | AD16: Não | AE16: 0 | AF16: Atleta profissional | AG16: 5 | AH16: C2 | AI16: Cedida | AJ16: Alojamento do clube | AK16: A pé | AL16: 8 | AM16: Sim | AN16: Sim | AO16: Não | AP16: Sim | AQ16: 5 | AR16: Sim | AS16: 13 | AT16: =IFERROR($E16-$AS16,"") -> 10 | AU16: 2 | AV16: Superliga B | AW16: — | AX16: — | AY16: O+ | AZ16: — | BA16: — | BB16: — | BC16: — | BD16: 0 | BE16: — | BF16: 46034 | BG16: 46399 | BH16: =IF($BG16="","",IF($BG16<TODAY(),"VENCIDO",IF($BG16<=TODAY()+30,"Vence em 30 dias","Válido"))) -> Válido | BI16: Sim | BJ16: Sim | BK16: 46027 | BL16: Ativo | BM16: EXEMPLO — substituir | BN16: =IF($B16="",0,IFERROR(SUMPRODUCT(MAX((Antropometria!$B$8:$B$407=$B16)*Antropometria!$A$8:$A$407)),0)) -> 46225
A17: =IF($B17="","","ATL-"&TEXT(ROW()-7,"000")) -> ATL-010 | B17: André Luiz Sampaio | C17: Dedé | D17: 34454 | E17: =IFERROR(DATEDIF($D17,TODAY(),"Y"),"") -> 32 | F17: Masculino | G17: Brasileira | H17: — | I17: — | J17: 18 | K17: Adulto | L17: Oposto | M17: Destro | N17: Esquerda | O17: =IF(OR($B17="",$BN17=0),"",IFERROR(AVERAGEIFS(Antropometria!$F$8:$F$407,Antropometria!$B$8:$B$407,$B17,Antropometria!$A$8:$A$407,$BN17),"")) -> 201 | P17: =IF(OR($B17="",$BN17=0),"",IFERROR(AVERAGEIFS(Antropometria!$E$8:$E$407,Antropometria!$B$8:$B$407,$B17,Antropometria!$A$8:$A$407,$BN17),"")) -> 97.5 | Q17: =IFERROR(ROUND($P17/($O17/100)^2,1),"") -> 24.1 | R17: (00) 90000-0010 | S17: atleta10@elase.com.br | T17: — | U17: — | V17: — | W17: Responsável / familiar | X17: (00) 90000-1010 | Y17: — | Z17: Superior completo | AA17: Concluído | AB17: — | AC17: — | AD17: Não | AE17: 0 | AF17: Atleta profissional | AG17: 4 | AH17: A | AI17: Própria | AJ17: Família | AK17: Carro próprio | AL17: 15 | AM17: Sim | AN17: Não | AO17: Sim | AP17: Sim | AQ17: 6 | AR17: Sim | AS17: 10 | AT17: =IFERROR($E17-$AS17,"") -> 22 | AU17: 9 | AV17: Superliga A | AW17: — | AX17: Seleção nacional adulta | AY17: O+ | AZ17: — | BA17: — | BB17: Cirurgia de ombro D (2021) | BC17: Cirurgia de ombro D (2021) | BD17: 0 | BE17: — | BF17: 46034 | BG17: 46399 | BH17: =IF($BG17="","",IF($BG17<TODAY(),"VENCIDO",IF($BG17<=TODAY()+30,"Vence em 30 dias","Válido"))) -> Válido | BI17: Sim | BJ17: Não | BK17: 46027 | BL17: Ativo | BM17: EXEMPLO — substituir | BN17: =IF($B17="",0,IFERROR(SUMPRODUCT(MAX((Antropometria!$B$8:$B$407=$B17)*Antropometria!$A$8:$A$407)),0)) -> 46225
A18: =IF($B18="","","ATL-"&TEXT(ROW()-7,"000")) -> ATL-011 | B18: Pedro Henrique Coutinho | C18: PH | D18: 38155 | E18: =IFERROR(DATEDIF($D18,TODAY(),"Y"),"") -> 22 | F18: Masculino | G18: Brasileira | H18: — | I18: — | J18: 3 | K18: Adulto | L18: Central | M18: Destro | N18: Direita | O18: =IF(OR($B18="",$BN18=0),"",IFERROR(AVERAGEIFS(Antropometria!$F$8:$F$407,Antropometria!$B$8:$B$407,$B18,Antropometria!$A$8:$A$407,$BN18),"")) -> 204 | P18: =IF(OR($B18="",$BN18=0),"",IFERROR(AVERAGEIFS(Antropometria!$E$8:$E$407,Antropometria!$B$8:$B$407,$B18,Antropometria!$A$8:$A$407,$BN18),"")) -> 91.8 | Q18: =IFERROR(ROUND($P18/($O18/100)^2,1),"") -> 22.1 | R18: (00) 90000-0011 | S18: atleta11@elase.com.br | T18: — | U18: — | V18: — | W18: Responsável / familiar | X18: (00) 90000-1011 | Y18: — | Z18: Ensino Médio completo | AA18: Concluído | AB18: — | AC18: — | AD18: Não | AE18: 0 | AF18: Atleta em formação | AG18: 6 | AH18: D-E | AI18: Cedida | AJ18: Alojamento do clube | AK18: A pé | AL18: 5 | AM18: Sim | AN18: Sim | AO18: Não | AP18: Sim | AQ18: 5 | AR18: Sim | AS18: 13 | AT18: =IFERROR($E18-$AS18,"") -> 9 | AU18: 1 | AV18: Superliga B | AW18: — | AX18: Seleção estadual Sub-21 | AY18: O+ | AZ18: — | BA18: — | BB18: — | BC18: — | BD18: 0 | BE18: — | BF18: 46034 | BG18: 46399 | BH18: =IF($BG18="","",IF($BG18<TODAY(),"VENCIDO",IF($BG18<=TODAY()+30,"Vence em 30 dias","Válido"))) -> Válido | BI18: Sim | BJ18: Não | BK18: 46027 | BL18: Ativo | BM18: EXEMPLO — substituir | BN18: =IF($B18="",0,IFERROR(SUMPRODUCT(MAX((Antropometria!$B$8:$B$407=$B18)*Antropometria!$A$8:$A$407)),0)) -> 46225
A19: =IF($B19="","","ATL-"&TEXT(ROW()-7,"000")) -> ATL-012 | B19: Caio Fernandes Bastos | C19: Caio | D19: 37173 | E19: =IFERROR(DATEDIF($D19,TODAY(),"Y"),"") -> 24 | F19: Masculino | G19: Brasileira | H19: — | I19: — | J19: 1 | K19: Adulto | L19: Líbero | M19: Canhoto | N19: Direita | O19: =IF(OR($B19="",$BN19=0),"",IFERROR(AVERAGEIFS(Antropometria!$F$8:$F$407,Antropometria!$B$8:$B$407,$B19,Antropometria!$A$8:$A$407,$BN19),"")) -> 186 | P19: =IF(OR($B19="",$BN19=0),"",IFERROR(AVERAGEIFS(Antropometria!$E$8:$E$407,Antropometria!$B$8:$B$407,$B19,Antropometria!$A$8:$A$407,$BN19),"")) -> 78.2 | Q19: =IFERROR(ROUND($P19/($O19/100)^2,1),"") -> 22.6 | R19: (00) 90000-0012 | S19: atleta12@elase.com.br | T19: — | U19: — | V19: — | W19: Responsável / familiar | X19: (00) 90000-1012 | Y19: — | Z19: Superior em andamento | AA19: Cursando | AB19: Matutino | AC19: — | AD19: Sim | AE19: 12 | AF19: Auxiliar administrativo | AG19: 3 | AH19: C1 | AI19: Alugada | AJ19: Família | AK19: Transporte público | AL19: 45 | AM19: Não | AN19: Não | AO19: Sim | AP19: Sim | AQ19: 4 | AR19: Não | AS19: 12 | AT19: =IFERROR($E19-$AS19,"") -> 12 | AU19: 3 | AV19: Superliga B | AW19: — | AX19: — | AY19: O+ | AZ19: — | BA19: — | BB19: — | BC19: Entorse de dedo | BD19: 1 | BE19: — | BF19: 46034 | BG19: 46399 | BH19: =IF($BG19="","",IF($BG19<TODAY(),"VENCIDO",IF($BG19<=TODAY()+30,"Vence em 30 dias","Válido"))) -> Válido | BI19: Sim | BJ19: Não | BK19: 46027 | BL19: Ativo | BM19: EXEMPLO — substituir | BN19: =IF($B19="",0,IFERROR(SUMPRODUCT(MAX((Antropometria!$B$8:$B$407=$B19)*Antropometria!$A$8:$A$407)),0)) -> 46225
A20: =IF($B20="","","ATL-"&TEXT(ROW()-7,"000")) | E20: =IFERROR(DATEDIF($D20,TODAY(),"Y"),"") -> 126 | O20: =IF(OR($B20="",$BN20=0),"",IFERROR(AVERAGEIFS(Antropometria!$F$8:$F$407,Antropometria!$B$8:$B$407,$B20,Antropometria!$A$8:$A$407,$BN20),"")) | P20: =IF(OR($B20="",$BN20=0),"",IFERROR(AVERAGEIFS(Antropometria!$E$8:$E$407,Antropometria!$B$8:$B$407,$B20,Antropometria!$A$8:$A$407,$BN20),"")) | Q20: =IFERROR(ROUND($P20/($O20/100)^2,1),"") | AT20: =IFERROR($E20-$AS20,"") -> 126 | BH20: =IF($BG20="","",IF($BG20<TODAY(),"VENCIDO",IF($BG20<=TODAY()+30,"Vence em 30 dias","Válido"))) | BN20: =IF($B20="",0,IFERROR(SUMPRODUCT(MAX((Antropometria!$B$8:$B$407=$B20)*Antropometria!$A$8:$A$407)),0)) -> 0
A21: =IF($B21="","","ATL-"&TEXT(ROW()-7,"000")) | E21: =IFERROR(DATEDIF($D21,TODAY(),"Y"),"") -> 126 | O21: =IF(OR($B21="",$BN21=0),"",IFERROR(AVERAGEIFS(Antropometria!$F$8:$F$407,Antropometria!$B$8:$B$407,$B21,Antropometria!$A$8:$A$407,$BN21),"")) | P21: =IF(OR($B21="",$BN21=0),"",IFERROR(AVERAGEIFS(Antropometria!$E$8:$E$407,Antropometria!$B$8:$B$407,$B21,Antropometria!$A$8:$A$407,$BN21),"")) | Q21: =IFERROR(ROUND($P21/($O21/100)^2,1),"") | AT21: =IFERROR($E21-$AS21,"") -> 126 | BH21: =IF($BG21="","",IF($BG21<TODAY(),"VENCIDO",IF($BG21<=TODAY()+30,"Vence em 30 dias","Válido"))) | BN21: =IF($B21="",0,IFERROR(SUMPRODUCT(MAX((Antropometria!$B$8:$B$407=$B21)*Antropometria!$A$8:$A$407)),0)) -> 0
A22: =IF($B22="","","ATL-"&TEXT(ROW()-7,"000")) | E22: =IFERROR(DATEDIF($D22,TODAY(),"Y"),"") -> 126 | O22: =IF(OR($B22="",$BN22=0),"",IFERROR(AVERAGEIFS(Antropometria!$F$8:$F$407,Antropometria!$B$8:$B$407,$B22,Antropometria!$A$8:$A$407,$BN22),"")) | P22: =IF(OR($B22="",$BN22=0),"",IFERROR(AVERAGEIFS(Antropometria!$E$8:$E$407,Antropometria!$B$8:$B$407,$B22,Antropometria!$A$8:$A$407,$BN22),"")) | Q22: =IFERROR(ROUND($P22/($O22/100)^2,1),"") | AT22: =IFERROR($E22-$AS22,"") -> 126 | BH22: =IF($BG22="","",IF($BG22<TODAY(),"VENCIDO",IF($BG22<=TODAY()+30,"Vence em 30 dias","Válido"))) | BN22: =IF($B22="",0,IFERROR(SUMPRODUCT(MAX((Antropometria!$B$8:$B$407=$B22)*Antropometria!$A$8:$A$407)),0)) -> 0
A23: =IF($B23="","","ATL-"&TEXT(ROW()-7,"000")) | E23: =IFERROR(DATEDIF($D23,TODAY(),"Y"),"") -> 126 | O23: =IF(OR($B23="",$BN23=0),"",IFERROR(AVERAGEIFS(Antropometria!$F$8:$F$407,Antropometria!$B$8:$B$407,$B23,Antropometria!$A$8:$A$407,$BN23),"")) | P23: =IF(OR($B23="",$BN23=0),"",IFERROR(AVERAGEIFS(Antropometria!$E$8:$E$407,Antropometria!$B$8:$B$407,$B23,Antropometria!$A$8:$A$407,$BN23),"")) | Q23: =IFERROR(ROUND($P23/($O23/100)^2,1),"") | AT23: =IFERROR($E23-$AS23,"") -> 126 | BH23: =IF($BG23="","",IF($BG23<TODAY(),"VENCIDO",IF($BG23<=TODAY()+30,"Vence em 30 dias","Válido"))) | BN23: =IF($B23="",0,IFERROR(SUMPRODUCT(MAX((Antropometria!$B$8:$B$407=$B23)*Antropometria!$A$8:$A$407)),0)) -> 0
A24: =IF($B24="","","ATL-"&TEXT(ROW()-7,"000")) | E24: =IFERROR(DATEDIF($D24,TODAY(),"Y"),"") -> 126 | O24: =IF(OR($B24="",$BN24=0),"",IFERROR(AVERAGEIFS(Antropometria!$F$8:$F$407,Antropometria!$B$8:$B$407,$B24,Antropometria!$A$8:$A$407,$BN24),"")) | P24: =IF(OR($B24="",$BN24=0),"",IFERROR(AVERAGEIFS(Antropometria!$E$8:$E$407,Antropometria!$B$8:$B$407,$B24,Antropometria!$A$8:$A$407,$BN24),"")) | Q24: =IFERROR(ROUND($P24/($O24/100)^2,1),"") | AT24: =IFERROR($E24-$AS24,"") -> 126 | BH24: =IF($BG24="","",IF($BG24<TODAY(),"VENCIDO",IF($BG24<=TODAY()+30,"Vence em 30 dias","Válido"))) | BN24: =IF($B24="",0,IFERROR(SUMPRODUCT(MAX((Antropometria!$B$8:$B$407=$B24)*Antropometria!$A$8:$A$407)),0)) -> 0
A25: =IF($B25="","","ATL-"&TEXT(ROW()-7,"000")) | E25: =IFERROR(DATEDIF($D25,TODAY(),"Y"),"") -> 126 | O25: =IF(OR($B25="",$BN25=0),"",IFERROR(AVERAGEIFS(Antropometria!$F$8:$F$407,Antropometria!$B$8:$B$407,$B25,Antropometria!$A$8:$A$407,$BN25),"")) | P25: =IF(OR($B25="",$BN25=0),"",IFERROR(AVERAGEIFS(Antropometria!$E$8:$E$407,Antropometria!$B$8:$B$407,$B25,Antropometria!$A$8:$A$407,$BN25),"")) | Q25: =IFERROR(ROUND($P25/($O25/100)^2,1),"") | AT25: =IFERROR($E25-$AS25,"") -> 126 | BH25: =IF($BG25="","",IF($BG25<TODAY(),"VENCIDO",IF($BG25<=TODAY()+30,"Vence em 30 dias","Válido"))) | BN25: =IF($B25="",0,IFERROR(SUMPRODUCT(MAX((Antropometria!$B$8:$B$407=$B25)*Antropometria!$A$8:$A$407)),0)) -> 0
A26: =IF($B26="","","ATL-"&TEXT(ROW()-7,"000")) | E26: =IFERROR(DATEDIF($D26,TODAY(),"Y"),"") -> 126 | O26: =IF(OR($B26="",$BN26=0),"",IFERROR(AVERAGEIFS(Antropometria!$F$8:$F$407,Antropometria!$B$8:$B$407,$B26,Antropometria!$A$8:$A$407,$BN26),"")) | P26: =IF(OR($B26="",$BN26=0),"",IFERROR(AVERAGEIFS(Antropometria!$E$8:$E$407,Antropometria!$B$8:$B$407,$B26,Antropometria!$A$8:$A$407,$BN26),"")) | Q26: =IFERROR(ROUND($P26/($O26/100)^2,1),"") | AT26: =IFERROR($E26-$AS26,"") -> 126 | BH26: =IF($BG26="","",IF($BG26<TODAY(),"VENCIDO",IF($BG26<=TODAY()+30,"Vence em 30 dias","Válido"))) | BN26: =IF($B26="",0,IFERROR(SUMPRODUCT(MAX((Antropometria!$B$8:$B$407=$B26)*Antropometria!$A$8:$A$407)),0)) -> 0
A27: =IF($B27="","","ATL-"&TEXT(ROW()-7,"000")) | E27: =IFERROR(DATEDIF($D27,TODAY(),"Y"),"") -> 126 | O27: =IF(OR($B27="",$BN27=0),"",IFERROR(AVERAGEIFS(Antropometria!$F$8:$F$407,Antropometria!$B$8:$B$407,$B27,Antropometria!$A$8:$A$407,$BN27),"")) | P27: =IF(OR($B27="",$BN27=0),"",IFERROR(AVERAGEIFS(Antropometria!$E$8:$E$407,Antropometria!$B$8:$B$407,$B27,Antropometria!$A$8:$A$407,$BN27),"")) | Q27: =IFERROR(ROUND($P27/($O27/100)^2,1),"") | AT27: =IFERROR($E27-$AS27,"") -> 126 | BH27: =IF($BG27="","",IF($BG27<TODAY(),"VENCIDO",IF($BG27<=TODAY()+30,"Vence em 30 dias","Válido"))) | BN27: =IF($B27="",0,IFERROR(SUMPRODUCT(MAX((Antropometria!$B$8:$B$407=$B27)*Antropometria!$A$8:$A$407)),0)) -> 0
A28: =IF($B28="","","ATL-"&TEXT(ROW()-7,"000")) | E28: =IFERROR(DATEDIF($D28,TODAY(),"Y"),"") -> 126 | O28: =IF(OR($B28="",$BN28=0),"",IFERROR(AVERAGEIFS(Antropometria!$F$8:$F$407,Antropometria!$B$8:$B$407,$B28,Antropometria!$A$8:$A$407,$BN28),"")) | P28: =IF(OR($B28="",$BN28=0),"",IFERROR(AVERAGEIFS(Antropometria!$E$8:$E$407,Antropometria!$B$8:$B$407,$B28,Antropometria!$A$8:$A$407,$BN28),"")) | Q28: =IFERROR(ROUND($P28/($O28/100)^2,1),"") | AT28: =IFERROR($E28-$AS28,"") -> 126 | BH28: =IF($BG28="","",IF($BG28<TODAY(),"VENCIDO",IF($BG28<=TODAY()+30,"Vence em 30 dias","Válido"))) | BN28: =IF($B28="",0,IFERROR(SUMPRODUCT(MAX((Antropometria!$B$8:$B$407=$B28)*Antropometria!$A$8:$A$407)),0)) -> 0
A29: =IF($B29="","","ATL-"&TEXT(ROW()-7,"000")) | E29: =IFERROR(DATEDIF($D29,TODAY(),"Y"),"") -> 126 | O29: =IF(OR($B29="",$BN29=0),"",IFERROR(AVERAGEIFS(Antropometria!$F$8:$F$407,Antropometria!$B$8:$B$407,$B29,Antropometria!$A$8:$A$407,$BN29),"")) | P29: =IF(OR($B29="",$BN29=0),"",IFERROR(AVERAGEIFS(Antropometria!$E$8:$E$407,Antropometria!$B$8:$B$407,$B29,Antropometria!$A$8:$A$407,$BN29),"")) | Q29: =IFERROR(ROUND($P29/($O29/100)^2,1),"") | AT29: =IFERROR($E29-$AS29,"") -> 126 | BH29: =IF($BG29="","",IF($BG29<TODAY(),"VENCIDO",IF($BG29<=TODAY()+30,"Vence em 30 dias","Válido"))) | BN29: =IF($B29="",0,IFERROR(SUMPRODUCT(MAX((Antropometria!$B$8:$B$407=$B29)*Antropometria!$A$8:$A$407)),0)) -> 0
A30: =IF($B30="","","ATL-"&TEXT(ROW()-7,"000")) | E30: =IFERROR(DATEDIF($D30,TODAY(),"Y"),"") -> 126 | O30: =IF(OR($B30="",$BN30=0),"",IFERROR(AVERAGEIFS(Antropometria!$F$8:$F$407,Antropometria!$B$8:$B$407,$B30,Antropometria!$A$8:$A$407,$BN30),"")) | P30: =IF(OR($B30="",$BN30=0),"",IFERROR(AVERAGEIFS(Antropometria!$E$8:$E$407,Antropometria!$B$8:$B$407,$B30,Antropometria!$A$8:$A$407,$BN30),"")) | Q30: =IFERROR(ROUND($P30/($O30/100)^2,1),"") | AT30: =IFERROR($E30-$AS30,"") -> 126 | BH30: =IF($BG30="","",IF($BG30<TODAY(),"VENCIDO",IF($BG30<=TODAY()+30,"Vence em 30 dias","Válido"))) | BN30: =IF($B30="",0,IFERROR(SUMPRODUCT(MAX((Antropometria!$B$8:$B$407=$B30)*Antropometria!$A$8:$A$407)),0)) -> 0
A31: =IF($B31="","","ATL-"&TEXT(ROW()-7,"000")) | E31: =IFERROR(DATEDIF($D31,TODAY(),"Y"),"") -> 126 | O31: =IF(OR($B31="",$BN31=0),"",IFERROR(AVERAGEIFS(Antropometria!$F$8:$F$407,Antropometria!$B$8:$B$407,$B31,Antropometria!$A$8:$A$407,$BN31),"")) | P31: =IF(OR($B31="",$BN31=0),"",IFERROR(AVERAGEIFS(Antropometria!$E$8:$E$407,Antropometria!$B$8:$B$407,$B31,Antropometria!$A$8:$A$407,$BN31),"")) | Q31: =IFERROR(ROUND($P31/($O31/100)^2,1),"") | AT31: =IFERROR($E31-$AS31,"") -> 126 | BH31: =IF($BG31="","",IF($BG31<TODAY(),"VENCIDO",IF($BG31<=TODAY()+30,"Vence em 30 dias","Válido"))) | BN31: =IF($B31="",0,IFERROR(SUMPRODUCT(MAX((Antropometria!$B$8:$B$407=$B31)*Antropometria!$A$8:$A$407)),0)) -> 0
... A47: =IF($B47="","","ATL-"&TEXT(ROW()-7,"000")) | E47: =IFERROR(DATEDIF($D47,TODAY(),"Y"),"") -> 126 | O47: =IF(OR($B47="",$BN47=0),"",IFERROR(AVERAGEIFS(Antropometria!$F$8:$F$407,Antropometria!$B$8:$B$407,$B47,Antropometria!$A$8:$A$407,$BN47),"")) | P47: =IF(OR($B47="",$BN47=0),"",IFERROR(AVERAGEIFS(Antropometria!$E$8:$E$407,Antropometria!$B$8:$B$407,$B47,Antropometria!$A$8:$A$407,$BN47),"")) | Q47: =IFERROR(ROUND($P47/($O47/100)^2,1),"") | AT47: =IFERROR($E47-$AS47,"") -> 126 | BH47: =IF($BG47="","",IF($BG47<TODAY(),"VENCIDO",IF($BG47<=TODAY()+30,"Vence em 30 dias","Válido"))) | BN47: =IF($B47="",0,IFERROR(SUMPRODUCT(MAX((Antropometria!$B$8:$B$407=$B47)*Antropometria!$A$8:$A$407)),0)) -> 0

Sheet Antropometria
A1: ANTROPOMETRIA E COMPOSIÇÃO CORPORAL
A2: Avaliações longitudinais. Preencha as medidas em amarelo; densidade, % de gordura, massa magra, índices e somatotipo são calculados. Sexo e data de nascimento são lidos do Cadastro.
A4: Protocolo: perfil restrito ISAK. Dobras em mm, perímetros e diâmetros em cm. • % de gordura pela equação de 7 dobras de Jackson & Pollock (1978 masculino / 1980 feminino) com conversão de Siri (1961) — a planilha escolhe a equação pelo sexo cadastrado. • Somatotipo pelo método Heath-Carter. • Σ 7 Dobras JP = peitoral + axilar média + tríceps + subescapular + abdominal + suprailíaca + coxa medial.
A6: IDENTIFICAÇÃO E MEDIDAS BÁSICAS | I6: DOBRAS CUTÂNEAS (mm) | S6: PERÍMETROS (cm) | AC6: DIÂMETROS ÓSSEOS (cm) | AG6: CALCULADOS
A7: Data | B7: Atleta | C7: Momento | D7: Avaliador | E7: Massa (kg) | F7: Estatura (cm) | G7: Estatura Sentado (cm) | H7: Envergadura (cm) | I7: Tríceps | J7: Subescapular | K7: Bíceps | L7: Peitoral | M7: Axilar Média | N7: Suprailíaca | O7: Supraespinhal | P7: Abdominal | Q7: Coxa Medial | R7: Perna Medial | S7: Braço Relaxado | T7: Braço Contraído | U7: Antebraço | V7: Tórax | W7: Cintura | X7: Abdômen | Y7: Quadril | Z7: Coxa (1/3) | AA7: Perna | AB7: Punho | AC7: Biacromial | AD7: Biileocristal | AE7: Úmero | AF7: Fêmur | AG7: Idade na Avaliação | AH7: Σ 4 Dobras (mm) | AI7: Σ 7 Dobras JP (mm) | AJ7: Σ 8 Dobras (mm) | AK7: Densidade Corporal | AL7: % de Gordura | AM7: Massa Gorda (kg) | AN7: Massa Magra (kg) | AO7: IMC | AP7: Índice Córmico | AQ7: Cintura / Estatura | AR7: AMB (cm²) | AS7: Endomorfia | AT7: Mesomorfia | AU7: Ectomorfia | AV7: Somatotipo Dominante
A8: 46034 | B8: Rafael Monteiro Alves | C8: Pré-temporada | D8: Comissão técnica | E8: 88 | F8: 196 | G8: 102.3 | H8: 201.9 | I8: 8.1 | J8: 13 | K8: 5.4 | L8: 6.9 | M8: 7 | N8: 10 | O8: 8 | P8: 14.1 | Q8: 9.7 | R8: 6.8 | S8: 34.8 | T8: 36.3 | U8: 27.1 | V8: 98.5 | W8: 85.6 | X8: 82.2 | Y8: 101.6 | Z8: 60.2 | AA8: 38.1 | AB8: 18.5 | AC8: 44.1 | AD8: 27.7 | AE8: 7.3 | AF8: 10.2 | AG8: =IFERROR(DATEDIF(INDEX(Cadastro!$D$8:$D$47,MATCH($B8,Cadastro!$B$8:$B$47,0)),$A8,"Y"),"") -> 27 | AH8: =IF(COUNT($I8,$K8,$J8,$N8)<4,"",$I8+$K8+$J8+$N8) -> 36.5 | AI8: =IF(COUNT($L8,$M8,$I8,$J8,$P8,$N8,$Q8)<7,"",$L8+$M8+$I8+$J8+$P8+$N8+$Q8) -> 68.8 | AJ8: =IF(COUNT($I8,$J8,$K8,$O8,$P8,$Q8,$R8,$N8)<8,"",$I8+$J8+$K8+$O8+$P8+$Q8+$R8+$N8) -> 75.1 | AK8: =IF(OR($AI8="",$AG8=""),"",IF(IFERROR(INDEX(Cadastro!$F$8:$F$47,MATCH($B8,Cadastro!$B$8:$B$47,0)),"")="Feminino",1.097-0.00046971*$AI8+0.00000056*$AI8^2-0.00012828*$AG8,1.112-0.00043499*$AI8+0.00000055*$AI8^2-0.00028826*$AG8)) -> 1.0768931 | AL8: =IF(OR($AK8="",$AK8=0),"",495/$AK8-450) -> 9.6556691 | AM8: =IF(OR($AL8="",$E8=""),"",$E8*$AL8/100) -> 8.4969888 | AN8: =IF(OR($AM8="",$E8=""),"",$E8-$AM8) -> 79.503011 | AO8: =IFERROR($E8/($F8/100)^2,"") -> 22.907122 | AP8: =IFERROR($G8/$F8*100,"") -> 52.193878 | AQ8: =IFERROR($W8/$F8,"") -> 0.43673469 | AR8: =IF(OR($S8="",$I8=""),"",($S8-PI()*$I8/10)^2/(4*PI())-IF(IFERROR(INDEX(Cadastro!$F$8:$F$47,MATCH($B8,Cadastro!$B$8:$B$47,0)),"")="Feminino",6.5,10)) -> 72.792801 | AS8: =IF(OR($I8="",$J8="",$O8="",$F8=""),"",-0.7182+0.1451*(($I8+$J8+$O8)*(170.18/$F8))-0.00068*(($I8+$J8+$O8)*(170.18/$F8))^2+0.0000014*(($I8+$J8+$O8)*(170.18/$F8))^3) -> 2.5364442 | AT8: =IF(OR($AE8="",$AF8="",$T8="",$AA8="",$F8=""),"",0.858*$AE8+0.601*$AF8+0.188*($T8-$I8/10)+0.161*($AA8-$R8/10)-0.131*$F8+4.5) -> 3.91434 | AU8: =IF(OR($E8="",$F8=""),"",IF($F8/$E8^(1/3)>=40.75,0.732*($F8/$E8^(1/3))-28.58,IF($F8/$E8^(1/3)>=38.25,0.463*($F8/$E8^(1/3))-17.63,0.1))) -> 3.6756844 | AV8: =IF(OR($AS8="",$AT8="",$AU8=""),"",IF(AND($AT8>=$AS8,$AT8>=$AU8),"Mesomorfo dominante",IF(AND($AU8>=$AS8,$AU8>=$AT8),"Ectomorfo dominante","Endomorfo dominante"))) -> Mesomorfo dominante
A9: 46034 | B9: Diego Salgado Ferraz | C9: Pré-temporada | D9: Comissão técnica | E9: 95 | F9: 202 | G9: 105.4 | H9: 207 | I9: 9 | J9: 12.4 | K9: 3.1 | L9: 6.3 | M9: 7.9 | N9: 9.1 | O9: 7 | P9: 11.8 | Q9: 9.1 | R9: 6.8 | S9: 33.8 | T9: 33.7 | U9: 29.3 | V9: 99.9 | W9: 84.2 | X9: 87.8 | Y9: 98.3 | Z9: 56.3 | AA9: 39.3 | AB9: 18.5 | AC9: 42.4 | AD9: 29.8 | AE9: 7.5 | AF9: 9.6 | AG9: =IFERROR(DATEDIF(INDEX(Cadastro!$D$8:$D$47,MATCH($B9,Cadastro!$B$8:$B$47,0)),$A9,"Y"),"") -> 29 | AH9: =IF(COUNT($I9,$K9,$J9,$N9)<4,"",$I9+$K9+$J9+$N9) -> 33.6 | AI9: =IF(COUNT($L9,$M9,$I9,$J9,$P9,$N9,$Q9)<7,"",$L9+$M9+$I9+$J9+$P9+$N9+$Q9) -> 65.6 | AJ9: =IF(COUNT($I9,$J9,$K9,$O9,$P9,$Q9,$R9,$N9)<8,"",$I9+$J9+$K9+$O9+$P9+$Q9+$R9+$N9) -> 68.3 | AK9: =IF(OR($AI9="",$AG9=""),"",IF(IFERROR(INDEX(Cadastro!$F$8:$F$47,MATCH($B9,Cadastro!$B$8:$B$47,0)),"")="Feminino",1.097-0.00046971*$AI9+0.00000056*$AI9^2-0.00012828*$AG9,1.112-0.00043499*$AI9+0.00000055*$AI9^2-0.00028826*$AG9)) -> 1.077472 | AL9: =IF(OR($AK9="",$AK9=0),"",495/$AK9-450) -> 9.4087053 | AM9: =IF(OR($AL9="",$E9=""),"",$E9*$AL9/100) -> 8.9382701 | AN9: =IF(OR($AM9="",$E9=""),"",$E9-$AM9) -> 86.06173 | AO9: =IFERROR($E9/($F9/100)^2,"") -> 23.282031 | AP9: =IFERROR($G9/$F9*100,"") -> 52.178218 | AQ9: =IFERROR($W9/$F9,"") -> 0.41683168 | AR9: =IF(OR($S9="",$I9=""),"",($S9-PI()*$I9/10)^2/(4*PI())-IF(IFERROR(INDEX(Cadastro!$F$8:$F$47,MATCH($B9,Cadastro!$B$8:$B$47,0)),"")="Feminino",6.5,10)) -> 66.338659 | AS9: =IF(OR($I9="",$J9="",$O9="",$F9=""),"",-0.7182+0.1451*(($I9+$J9+$O9)*(170.18/$F9))-0.00068*(($I9+$J9+$O9)*(170.18/$F9))^2+0.0000014*(($I9+$J9+$O9)*(170.18/$F9))^3) -> 2.3834035 | AT9: =IF(OR($AE9="",$AF9="",$T9="",$AA9="",$F9=""),"",0.858*$AE9+0.601*$AF9+0.188*($T9-$I9/10)+0.161*($AA9-$R9/10)-0.131*$F9+4.5) -> 2.62682 | AU9: =IF(OR($E9="",$F9=""),"",IF($F9/$E9^(1/3)>=40.75,0.732*($F9/$E9^(1/3))-28.58,IF($F9/$E9^(1/3)>=38.25,0.463*($F9/$E9^(1/3))-17.63,0.1))) -> 3.8256882 | AV9: =IF(OR($AS9="",$AT9="",$AU9=""),"",IF(AND($AT9>=$AS9,$AT9>=$AU9),"Mesomorfo dominante",IF(AND($AU9>=$AS9,$AU9>=$AT9),"Ectomorfo dominante","Endomorfo dominante"))) -> Ectomorfo dominante
A10: 46034 | B10: Lucas Prado Bittencourt | C10: Pré-temporada | D10: Comissão técnica | E10: 89 | F10: 198 | G10: 103.4 | H10: 203 | I10: 9.3 | J10: 9.5 | K10: 5.5 | L10: 6.4 | M10: 7.3 | N10: 13.8 | O10: 8.3 | P10: 14.9 | Q10: 11.1 | R10: 8 | S10: 31.3 | T10: 35.3 | U10: 28.7 | V10: 99.1 | W10: 84.8 | X10: 81.3 | Y10: 96.5 | Z10: 59.4 | AA10: 40.7 | AB10: 18.6 | AC10: 44.5 | AD10: 28.6 | AE10: 7.3 | AF10: 9.6 | AG10: =IFERROR(DATEDIF(INDEX(Cadastro!$D$8:$D$47,MATCH($B10,Cadastro!$B$8:$B$47,0)),$A10,"Y"),"") -> 25 | AH10: =IF(COUNT($I10,$K10,$J10,$N10)<4,"",$I10+$K10+$J10+$N10) -> 38.1 | AI10: =IF(COUNT($L10,$M10,$I10,$J10,$P10,$N10,$Q10)<7,"",$L10+$M10+$I10+$J10+$P10+$N10+$Q10) -> 72.3 | AJ10: =IF(COUNT($I10,$J10,$K10,$O10,$P10,$Q10,$R10,$N10)<8,"",$I10+$J10+$K10+$O10+$P10+$Q10+$R10+$N10) -> 80.4 | AK10: =IF(OR($AI10="",$AG10=""),"",IF(IFERROR(INDEX(Cadastro!$F$8:$F$47,MATCH($B10,Cadastro!$B$8:$B$47,0)),"")="Feminino",1.097-0.00046971*$AI10+0.00000056*$AI10^2-0.00012828*$AG10,1.112-0.00043499*$AI10+0.00000055*$AI10^2-0.00028826*$AG10)) -> 1.0762187 | AL10: =IF(OR($AK10="",$AK10=0),"",495/$AK10-450) -> 9.943676 | AM10: =IF(OR($AL10="",$E10=""),"",$E10*$AL10/100) -> 8.8498716 | AN10: =IF(OR($AM10="",$E10=""),"",$E10-$AM10) -> 80.150128 | AO10: =IFERROR($E10/($F10/100)^2,"") -> 22.701765 | AP10: =IFERROR($G10/$F10*100,"") -> 52.222222 | AQ10: =IFERROR($W10/$F10,"") -> 0.42828283 | AR10: =IF(OR($S10="",$I10=""),"",($S10-PI()*$I10/10)^2/(4*PI())-IF(IFERROR(INDEX(Cadastro!$F$8:$F$47,MATCH($B10,Cadastro!$B$8:$B$47,0)),"")="Feminino",6.5,10)) -> 54.086044 | AS10: =IF(OR($I10="",$J10="",$O10="",$F10=""),"",-0.7182+0.1451*(($I10+$J10+$O10)*(170.18/$F10))-0.00068*(($I10+$J10+$O10)*(170.18/$F10))^2+0.0000014*(($I10+$J10+$O10)*(170.18/$F10))^3) -> 2.3102845 | AT10: =IF(OR($AE10="",$AF10="",$T10="",$AA10="",$F10=""),"",0.858*$AE10+0.601*$AF10+0.188*($T10-$I10/10)+0.161*($AA10-$R10/10)-0.131*$F10+4.5) -> 3.48046 | AU10: =IF(OR($E10="",$F10=""),"",IF($F10/$E10^(1/3)>=40.75,0.732*($F10/$E10^(1/3))-28.58,IF($F10/$E10^(1/3)>=38.25,0.463*($F10/$E10^(1/3))-17.63,0.1))) -> 3.8823236 | AV10: =IF(OR($AS10="",$AT10="",$AU10=""),"",IF(AND($AT10>=$AS10,$AT10>=$AU10),"Mesomorfo dominante",IF(AND($AU10>=$AS10,$AU10>=$AT10),"Ectomorfo dominante","Endomorfo dominante"))) -> Ectomorfo dominante
A11: 46034 | B11: Bruno Rezende Camargo | C11: Pré-temporada | D11: Comissão técnica | E11: 87 | F11: 197 | G11: 102.8 | H11: 202.6 | I11: 9.4 | J11: 9.7 | K11: 3 | L11: 6.4 | M11: 7.4 | N11: 13.7 | O11: 9.2 | P11: 16.6 | Q11: 13.2 | R11: 8.8 | S11: 31.6 | T11: 36.4 | U11: 29.2 | V11: 99.2 | W11: 81.4 | X11: 83.8 | Y11: 100.6 | Z11: 55.4 | AA11: 37.2 | AB11: 17.9 | AC11: 42.4 | AD11: 28.8 | AE11: 7.5 | AF11: 9.9 | AG11: =IFERROR(DATEDIF(INDEX(Cadastro!$D$8:$D$47,MATCH($B11,Cadastro!$B$8:$B$47,0)),$A11,"Y"),"") -> 26 | AH11: =IF(COUNT($I11,$K11,$J11,$N11)<4,"",$I11+$K11+$J11+$N11) -> 35.8 | AI11: =IF(COUNT($L11,$M11,$I11,$J11,$P11,$N11,$Q11)<7,"",$L11+$M11+$I11+$J11+$P11+$N11+$Q11) -> 76.4 | AJ11: =IF(COUNT($I11,$J11,$K11,$O11,$P11,$Q11,$R11,$N11)<8,"",$I11+$J11+$K11+$O11+$P11+$Q11+$R11+$N11) -> 83.6 | AK11: =IF(OR($AI11="",$AG11=""),"",IF(IFERROR(INDEX(Cadastro!$F$8:$F$47,MATCH($B11,Cadastro!$B$8:$B$47,0)),"")="Feminino",1.097-0.00046971*$AI11+0.00000056*$AI11^2-0.00012828*$AG11,1.112-0.00043499*$AI11+0.00000055*$AI11^2-0.00028826*$AG11)) -> 1.0744823 | AL11: =IF(OR($AK11="",$AK11=0),"",495/$AK11-450) -> 10.686961 | AM11: =IF(OR($AL11="",$E11=""),"",$E11*$AL11/100) -> 9.2976559 | AN11: =IF(OR($AM11="",$E11=""),"",$E11-$AM11) -> 77.702344 | AO11: =IFERROR($E11/($F11/100)^2,"") -> 22.41748 | AP11: =IFERROR($G11/$F11*100,"") -> 52.182741 | AQ11: =IFERROR($W11/$F11,"") -> 0.41319797 | AR11: =IF(OR($S11="",$I11=""),"",($S11-PI()*$I11/10)^2/(4*PI())-IF(IFERROR(INDEX(Cadastro!$F$8:$F$47,MATCH($B11,Cadastro!$B$8:$B$47,0)),"")="Feminino",6.5,10)) -> 55.304858 | AS11: =IF(OR($I11="",$J11="",$O11="",$F11=""),"",-0.7182+0.1451*(($I11+$J11+$O11)*(170.18/$F11))-0.00068*(($I11+$J11+$O11)*(170.18/$F11))^2+0.0000014*(($I11+$J11+$O11)*(170.18/$F11))^3) -> 2.4431293 | AT11: =IF(OR($AE11="",$AF11="",$T11="",$AA11="",$F11=""),"",0.858*$AE11+0.601*$AF11+0.188*($T11-$I11/10)+0.161*($AA11-$R11/10)-0.131*$F11+4.5) -> 3.5919 | AU11: =IF(OR($E11="",$F11=""),"",IF($F11/$E11^(1/3)>=40.75,0.732*($F11/$E11^(1/3))-28.58,IF($F11/$E11^(1/3)>=38.25,0.463*($F11/$E11^(1/3))-17.63,0.1))) -> 3.9639969 | AV11: =IF(OR($AS11="",$AT11="",$AU11=""),"",IF(AND($AT11>=$AS11,$AT11>=$AU11),"Mesomorfo dominante",IF(AND($AU11>=$AS11,$AU11>=$AT11),"Ectomorfo dominante","Endomorfo dominante"))) -> Ectomorfo dominante
A12: 46034 | B12: Thiago Nogueira Vasques | C12: Pré-temporada | D12: Comissão técnica | E12: 99 | F12: 205 | G12: 107 | H12: 209.6 | I12: 8.5 | J12: 11.9 | K12: 5.5 | L12: 7.7 | M12: 6.5 | N12: 12 | O12: 6.5 | P12: 16.3 | Q12: 12 | R12: 9.7 | S12: 31.1 | T12: 37.4 | U12: 29.3 | V12: 96.7 | W12: 80.9 | X12: 85 | Y12: 98.9 | Z12: 61.2 | AA12: 38.9 | AB12: 18 | AC12: 44.6 | AD12: 27.7 | AE12: 7.3 | AF12: 9.5 | AG12: =IFERROR(DATEDIF(INDEX(Cadastro!$D$8:$D$47,MATCH($B12,Cadastro!$B$8:$B$47,0)),$A12,"Y"),"") -> 30 | AH12: =IF(COUNT($I12,$K12,$J12,$N12)<4,"",$I12+$K12+$J12+$N12) -> 37.9 | AI12: =IF(COUNT($L12,$M12,$I12,$J12,$P12,$N12,$Q12)<7,"",$L12+$M12+$I12+$J12+$P12+$N12+$Q12) -> 74.9 | AJ12: =IF(COUNT($I12,$J12,$K12,$O12,$P12,$Q12,$R12,$N12)<8,"",$I12+$J12+$K12+$O12+$P12+$Q12+$R12+$N12) -> 82.4 | AK12: =IF(OR($AI12="",$AG12=""),"",IF(IFERROR(INDEX(Cadastro!$F$8:$F$47,MATCH($B12,Cadastro!$B$8:$B$47,0)),"")="Feminino",1.097-0.00046971*$AI12+0.00000056*$AI12^2-0.00012828*$AG12,1.112-0.00043499*$AI12+0.00000055*$AI12^2-0.00028826*$AG12)) -> 1.073857 | AL12: =IF(OR($AK12="",$AK12=0),"",495/$AK12-450) -> 10.955249 | AM12: =IF(OR($AL12="",$E12=""),"",$E12*$AL12/100) -> 10.845697 | AN12: =IF(OR($AM12="",$E12=""),"",$E12-$AM12) -> 88.154303 | AO12: =IFERROR($E12/($F12/100)^2,"") -> 23.557406 | AP12: =IFERROR($G12/$F12*100,"") -> 52.195122 | AQ12: =IFERROR($W12/$F12,"") -> 0.39463415 | AR12: =IF(OR($S12="",$I12=""),"",($S12-PI()*$I12/10)^2/(4*PI())-IF(IFERROR(INDEX(Cadastro!$F$8:$F$47,MATCH($B12,Cadastro!$B$8:$B$47,0)),"")="Feminino",6.5,10)) -> 54.318076 | AS12: =IF(OR($I12="",$J12="",$O12="",$F12=""),"",-0.7182+0.1451*(($I12+$J12+$O12)*(170.18/$F12))-0.00068*(($I12+$J12+$O12)*(170.18/$F12))^2+0.0000014*(($I12+$J12+$O12)*(170.18/$F12))^3) -> 2.1985129 | AT12: =IF(OR($AE12="",$AF12="",$T12="",$AA12="",$F12=""),"",0.858*$AE12+0.601*$AF12+0.188*($T12-$I12/10)+0.161*($AA12-$R12/10)-0.131*$F12+4.5) -> 2.59603 | AU12: =IF(OR($E12="",$F12=""),"",IF($F12/$E12^(1/3)>=40.75,0.732*($F12/$E12^(1/3))-28.58,IF($F12/$E12^(1/3)>=38.25,0.463*($F12/$E12^(1/3))-17.63,0.1))) -> 3.8579358 | AV12: =IF(OR($AS12="",$AT12="",$AU12=""),"",IF(AND($AT12>=$AS12,$AT12>=$AU12),"Mesomorfo dominante",IF(AND($AU12>=$AS12,$AU12>=$AT12),"Ectomorfo dominante","Endomorfo dominante"))) -> Ectomorfo dominante
A13: 46034 | B13: Matheus Caldeira Lins | C13: Pré-temporada | D13: Comissão técnica | E13: 95 | F13: 203 | G13: 106 | H13: 206.8 | I13: 10 | J13: 9.1 | K13: 3.5 | L13: 6.3 | M13: 8.6 | N13: 12.4 | O13: 8 | P13: 10 | Q13: 10.7 | R13: 8.2 | S13: 32.5 | T13: 35.1 | U13: 28.6 | V13: 104.3 | W13: 83.2 | X13: 85.3 | Y13: 100.6 | Z13: 57.4 | AA13: 37.6 | AB13: 18.8 | AC13: 44.2 | AD13: 27.6 | AE13: 7.5 | AF13: 9.9 | AG13: =IFERROR(DATEDIF(INDEX(Cadastro!$D$8:$D$47,MATCH($B13,Cadastro!$B$8:$B$47,0)),$A13,"Y"),"") -> 24 | AH13: =IF(COUNT($I13,$K13,$J13,$N13)<4,"",$I13+$K13+$J13+$N13) -> 35 | AI13: =IF(COUNT($L13,$M13,$I13,$J13,$P13,$N13,$Q13)<7,"",$L13+$M13+$I13+$J13+$P13+$N13+$Q13) -> 67.1 | AJ13: =IF(COUNT($I13,$J13,$K13,$O13,$P13,$Q13,$R13,$N13)<8,"",$I13+$J13+$K13+$O13+$P13+$Q13+$R13+$N13) -> 71.9 | AK13: =IF(OR($AI13="",$AG13=""),"",IF(IFERROR(INDEX(Cadastro!$F$8:$F$47,MATCH($B13,Cadastro!$B$8:$B$47,0)),"")="Feminino",1.097-0.00046971*$AI13+0.00000056*$AI13^2-0.00012828*$AG13,1.112-0.00043499*$AI13+0.00000055*$AI13^2-0.00028826*$AG13)) -> 1.0783703 | AL13: =IF(OR($AK13="",$AK13=0),"",495/$AK13-450) -> 9.0260136 | AM13: =IF(OR($AL13="",$E13=""),"",$E13*$AL13/100) -> 8.5747129 | AN13: =IF(OR($AM13="",$E13=""),"",$E13-$AM13) -> 86.425287 | AO13: =IFERROR($E13/($F13/100)^2,"") -> 23.053217 | AP13: =IFERROR($G13/$F13*100,"") -> 52.216749 | AQ13: =IFERROR($W13/$F13,"") -> 0.40985222 | AR13: =IF(OR($S13="",$I13=""),"",($S13-PI()*$I13/10)^2/(4*PI())-IF(IFERROR(INDEX(Cadastro!$F$8:$F$47,MATCH($B13,Cadastro!$B$8:$B$47,0)),"")="Feminino",6.5,10)) -> 58.589102 | AS13: =IF(OR($I13="",$J13="",$O13="",$F13=""),"",-0.7182+0.1451*(($I13+$J13+$O13)*(170.18/$F13))-0.00068*(($I13+$J13+$O13)*(170.18/$F13))^2+0.0000014*(($I13+$J13+$O13)*(170.18/$F13))^3) -> 2.2437147 | AT13: =IF(OR($AE13="",$AF13="",$T13="",$AA13="",$F13=""),"",0.858*$AE13+0.601*$AF13+0.188*($T13-$I13/10)+0.161*($AA13-$R13/10)-0.131*$F13+4.5) -> 2.62428 | AU13: =IF(OR($E13="",$F13=""),"",IF($F13/$E13^(1/3)>=40.75,0.732*($F13/$E13^(1/3))-28.58,IF($F13/$E13^(1/3)>=38.25,0.463*($F13/$E13^(1/3))-17.63,0.1))) -> 3.9861124 | AV13: =IF(OR($AS13="",$AT13="",$AU13=""),"",IF(AND($AT13>=$AS13,$AT13>=$AU13),"Mesomorfo dominante",IF(AND($AU13>=$AS13,$AU13>=$AT13),"Ectomorfo dominante","Endomorfo dominante"))) -> Ectomorfo dominante
A14: 46034 | B14: Felipe Andrade Rocha | C14: Pré-temporada | D14: Comissão técnica | E14: 78 | F14: 184 | G14: 96 | H14: 190.2 | I14: 8.7 | J14: 12.2 | K14: 3.3 | L14: 6 | M14: 8.9 | N14: 13.7 | O14: 8.8 | P14: 15.6 | Q14: 12 | R14: 7.1 | S14: 34.3 | T14: 35.3 | U14: 29.9 | V14: 96.8 | W14: 85.7 | X14: 84 | Y14: 95.4 | Z14: 61.5 | AA14: 40.6 | AB14: 18.7 | AC14: 43.6 | AD14: 28.3 | AE14: 7.1 | AF14: 10.3 | AG14: =IFERROR(DATEDIF(INDEX(Cadastro!$D$8:$D$47,MATCH($B14,Cadastro!$B$8:$B$47,0)),$A14,"Y"),"") -> 22 | AH14: =IF(COUNT($I14,$K14,$J14,$N14)<4,"",$I14+$K14+$J14+$N14) -> 37.9 | AI14: =IF(COUNT($L14,$M14,$I14,$J14,$P14,$N14,$Q14)<7,"",$L14+$M14+$I14+$J14+$P14+$N14+$Q14) -> 77.1 | AJ14: =IF(COUNT($I14,$J14,$K14,$O14,$P14,$Q14,$R14,$N14)<8,"",$I14+$J14+$K14+$O14+$P14+$Q14+$R14+$N14) -> 81.4 | AK14: =IF(OR($AI14="",$AG14=""),"",IF(IFERROR(INDEX(Cadastro!$F$8:$F$47,MATCH($B14,Cadastro!$B$8:$B$47,0)),"")="Feminino",1.097-0.00046971*$AI14+0.00000056*$AI14^2-0.00012828*$AG14,1.112-0.00043499*$AI14+0.00000055*$AI14^2-0.00028826*$AG14)) -> 1.07539 | AL14: =IF(OR($AK14="",$AK14=0),"",495/$AK14-450) -> 10.298134 | AM14: =IF(OR($AL14="",$E14=""),"",$E14*$AL14/100) -> 8.0325449 | AN14: =IF(OR($AM14="",$E14=""),"",$E14-$AM14) -> 69.967455 | AO14: =IFERROR($E14/($F14/100)^2,"") -> 23.038752 | AP14: =IFERROR($G14/$F14*100,"") -> 52.173913 | AQ14: =IFERROR($W14/$F14,"") -> 0.46576087 | AR14: =IF(OR($S14="",$I14=""),"",($S14-PI()*$I14/10)^2/(4*PI())-IF(IFERROR(INDEX(Cadastro!$F$8:$F$47,MATCH($B14,Cadastro!$B$8:$B$47,0)),"")="Feminino",6.5,10)) -> 69.296067 | AS14: =IF(OR($I14="",$J14="",$O14="",$F14=""),"",-0.7182+0.1451*(($I14+$J14+$O14)*(170.18/$F14))-0.00068*(($I14+$J14+$O14)*(170.18/$F14))^2+0.0000014*(($I14+$J14+$O14)*(170.18/$F14))^3) -> 2.7835081 | AT14: =IF(OR($AE14="",$AF14="",$T14="",$AA14="",$F14=""),"",0.858*$AE14+0.601*$AF14+0.188*($T14-$I14/10)+0.161*($AA14-$R14/10)-0.131*$F14+4.5) -> 5.57323 | AU14: =IF(OR($E14="",$F14=""),"",IF($F14/$E14^(1/3)>=40.75,0.732*($F14/$E14^(1/3))-28.58,IF($F14/$E14^(1/3)>=38.25,0.463*($F14/$E14^(1/3))-17.63,0.1))) -> 2.9432295 | AV14: =IF(OR($AS14="",$AT14="",$AU14=""),"",IF(AND($AT14>=$AS14,$AT14>=$AU14),"Mesomorfo dominante",IF(AND($AU14>=$AS14,$AU14>=$AT14),"Ectomorfo dominante","Endomorfo dominante"))) -> Mesomorfo dominante
A15: 46034 | B15: Gustavo Peixoto Maia | C15: Pré-temporada | D15: Comissão técnica | E15: 91 | F15: 199 | G15: 103.9 | H15: 202.9 | I15: 9.1 | J15: 12.4 | K15: 5.2 | L15: 7.9 | M15: 8.8 | N15: 9.4 | O15: 9 | P15: 12.1 | Q15: 13.9 | R15: 9.5 | S15: 32.6 | T15: 33.5 | U15: 29.2 | V15: 99 | W15: 83.3 | X15: 83.2 | Y15: 99.8 | Z15: 56.4 | AA15: 40.5 | AB15: 18 | AC15: 42.5 | AD15: 28.7 | AE15: 7.2 | AF15: 10.2 | AG15: =IFERROR(DATEDIF(INDEX(Cadastro!$D$8:$D$47,MATCH($B15,Cadastro!$B$8:$B$47,0)),$A15,"Y"),"") -> 28 | AH15: =IF(COUNT($I15,$K15,$J15,$N15)<4,"",$I15+$K15+$J15+$N15) -> 36.1 | AI15: =IF(COUNT($L15,$M15,$I15,$J15,$P15,$N15,$Q15)<7,"",$L15+$M15+$I15+$J15+$P15+$N15+$Q15) -> 73.6 | AJ15: =IF(COUNT($I15,$J15,$K15,$O15,$P15,$Q15,$R15,$N15)<8,"",$I15+$J15+$K15+$O15+$P15+$Q15+$R15+$N15) -> 80.6 | AK15: =IF(OR($AI15="",$AG15=""),"",IF(IFERROR(INDEX(Cadastro!$F$8:$F$47,MATCH($B15,Cadastro!$B$8:$B$47,0)),"")="Feminino",1.097-0.00046971*$AI15+0.00000056*$AI15^2-0.00012828*$AG15,1.112-0.00043499*$AI15+0.00000055*$AI15^2-0.00028826*$AG15)) -> 1.0748928 | AL15: =IF(OR($AK15="",$AK15=0),"",495/$AK15-450) -> 10.511046 | AM15: =IF(OR($AL15="",$E15=""),"",$E15*$AL15/100) -> 9.5650516 | AN15: =IF(OR($AM15="",$E15=""),"",$E15-$AM15) -> 81.434948 | AO15: =IFERROR($E15/($F15/100)^2,"") -> 22.979218 | AP15: =IFERROR($G15/$F15*100,"") -> 52.211055 | AQ15: =IFERROR($W15/$F15,"") -> 0.41859296 | AR15: =IF(OR($S15="",$I15=""),"",($S15-PI()*$I15/10)^2/(4*PI())-IF(IFERROR(INDEX(Cadastro!$F$8:$F$47,MATCH($B15,Cadastro!$B$8:$B$47,0)),"")="Feminino",6.5,10)) -> 60.389142 | AS15: =IF(OR($I15="",$J15="",$O15="",$F15=""),"",-0.7182+0.1451*(($I15+$J15+$O15)*(170.18/$F15))-0.00068*(($I15+$J15+$O15)*(170.18/$F15))^2+0.0000014*(($I15+$J15+$O15)*(170.18/$F15))^3) -> 2.6286513 | AT15: =IF(OR($AE15="",$AF15="",$T15="",$AA15="",$F15=""),"",0.858*$AE15+0.601*$AF15+0.188*($T15-$I15/10)+0.161*($AA15-$R15/10)-0.131*$F15+4.5) -> 3.23327 | AU15: =IF(OR($E15="",$F15=""),"",IF($F15/$E15^(1/3)>=40.75,0.732*($F15/$E15^(1/3))-28.58,IF($F15/$E15^(1/3)>=38.25,0.463*($F15/$E15^(1/3))-17.63,0.1))) -> 3.8054816 | AV15: =IF(OR($AS15="",$AT15="",$AU15=""),"",IF(AND($AT15>=$AS15,$AT15>=$AU15),"Mesomorfo dominante",IF(AND($AU15>=$AS15,$AU15>=$AT15),"Ectomorfo dominante","Endomorfo dominante"))) -> Ectomorfo dominante
A16: 46034 | B16: Vinícius Barreto Duarte | C16: Pré-temporada | D16: Comissão técnica | E16: 84 | F16: 192 | G16: 100.2 | H16: 196.9 | I16: 11 | J16: 9.1 | K16: 3.9 | L16: 6.2 | M16: 7.2 | N16: 13.3 | O16: 6.3 | P16: 13.8 | Q16: 12.9 | R16: 6.2 | S16: 31.1 | T16: 33 | U16: 27.9 | V16: 104.8 | W16: 83 | X16: 87.1 | Y16: 101.2 | Z16: 55.4 | AA16: 40.5 | AB16: 18.2 | AC16: 44.4 | AD16: 28.1 | AE16: 7.4 | AF16: 9.6 | AG16: =IFERROR(DATEDIF(INDEX(Cadastro!$D$8:$D$47,MATCH($B16,Cadastro!$B$8:$B$47,0)),$A16,"Y"),"") -> 23 | AH16: =IF(COUNT($I16,$K16,$J16,$N16)<4,"",$I16+$K16+$J16+$N16) -> 37.3 | AI16: =IF(COUNT($L16,$M16,$I16,$J16,$P16,$N16,$Q16)<7,"",$L16+$M16+$I16+$J16+$P16+$N16+$Q16) -> 73.5 | AJ16: =IF(COUNT($I16,$J16,$K16,$O16,$P16,$Q16,$R16,$N16)<8,"",$I16+$J16+$K16+$O16+$P16+$Q16+$R16+$N16) -> 76.5 | AK16: =IF(OR($AI16="",$AG16=""),"",IF(IFERROR(INDEX(Cadastro!$F$8:$F$47,MATCH($B16,Cadastro!$B$8:$B$47,0)),"")="Feminino",1.097-0.00046971*$AI16+0.00000056*$AI16^2-0.00012828*$AG16,1.112-0.00043499*$AI16+0.00000055*$AI16^2-0.00028826*$AG16)) -> 1.0763695 | AL16: =IF(OR($AK16="",$AK16=0),"",495/$AK16-450) -> 9.8792547 | AM16: =IF(OR($AL16="",$E16=""),"",$E16*$AL16/100) -> 8.298574 | AN16: =IF(OR($AM16="",$E16=""),"",$E16-$AM16) -> 75.701426 | AO16: =IFERROR($E16/($F16/100)^2,"") -> 22.786458 | AP16: =IFERROR($G16/$F16*100,"") -> 52.1875 | AQ16: =IFERROR($W16/$F16,"") -> 0.43229167 | AR16: =IF(OR($S16="",$I16=""),"",($S16-PI()*$I16/10)^2/(4*PI())-IF(IFERROR(INDEX(Cadastro!$F$8:$F$47,MATCH($B16,Cadastro!$B$8:$B$47,0)),"")="Feminino",6.5,10)) -> 50.813458 | AS16: =IF(OR($I16="",$J16="",$O16="",$F16=""),"",-0.7182+0.1451*(($I16+$J16+$O16)*(170.18/$F16))-0.00068*(($I16+$J16+$O16)*(170.18/$F16))^2+0.0000014*(($I16+$J16+$O16)*(170.18/$F16))^3) -> 2.3227084 | AT16: =IF(OR($AE16="",$AF16="",$T16="",$AA16="",$F16=""),"",0.858*$AE16+0.601*$AF16+0.188*($T16-$I16/10)+0.161*($AA16-$R16/10)-0.131*$F16+4.5) -> 3.88468 | AU16: =IF(OR($E16="",$F16=""),"",IF($F16/$E16^(1/3)>=40.75,0.732*($F16/$E16^(1/3))-28.58,IF($F16/$E16^(1/3)>=38.25,0.463*($F16/$E16^(1/3))-17.63,0.1))) -> 3.5111944 | AV16: =IF(OR($AS16="",$AT16="",$AU16=""),"",IF(AND($AT16>=$AS16,$AT16>=$AU16),"Mesomorfo dominante",IF(AND($AU16>=$AS16,$AU16>=$AT16),"Ectomorfo dominante","Endomorfo dominante"))) -> Mesomorfo dominante
A17: 46034 | B17: André Luiz Sampaio | C17: Pré-temporada | D17: Comissão técnica | E17: 97 | F17: 201 | G17: 104.9 | H17: 206 | I17: 10.9 | J17: 12.2 | K17: 4 | L17: 5.3 | M17: 7.4 | N17: 8.5 | O17: 6.5 | P17: 16.4 | Q17: 12.1 | R17: 9.1 | S17: 33 | T17: 33.3 | U17: 28.2 | V17: 104.1 | W17: 81.8 | X17: 86.4 | Y17: 96.8 | Z17: 61 | AA17: 40.6 | AB17: 17.9 | AC17: 44.1 | AD17: 27.5 | AE17: 7.7 | AF17: 9.9 | AG17: =IFERROR(DATEDIF(INDEX(Cadastro!$D$8:$D$47,MATCH($B17,Cadastro!$B$8:$B$47,0)),$A17,"Y"),"") -> 31 | AH17: =IF(COUNT($I17,$K17,$J17,$N17)<4,"",$I17+$K17+$J17+$N17) -> 35.6 | AI17: =IF(COUNT($L17,$M17,$I17,$J17,$P17,$N17,$Q17)<7,"",$L17+$M17+$I17+$J17+$P17+$N17+$Q17) -> 72.8 | AJ17: =IF(COUNT($I17,$J17,$K17,$O17,$P17,$Q17,$R17,$N17)<8,"",$I17+$J17+$K17+$O17+$P17+$Q17+$R17+$N17) -> 79.7 | AK17: =IF(OR($AI17="",$AG17=""),"",IF(IFERROR(INDEX(Cadastro!$F$8:$F$47,MATCH($B17,Cadastro!$B$8:$B$47,0)),"")="Feminino",1.097-0.00046971*$AI17+0.00000056*$AI17^2-0.00012828*$AG17,1.112-0.00043499*$AI17+0.00000055*$AI17^2-0.00028826*$AG17)) -> 1.0743116 | AL17: =IF(OR($AK17="",$AK17=0),"",495/$AK17-450) -> 10.760183 | AM17: =IF(OR($AL17="",$E17=""),"",$E17*$AL17/100) -> 10.437377 | AN17: =IF(OR($AM17="",$E17=""),"",$E17-$AM17) -> 86.562623 | AO17: =IFERROR($E17/($F17/100)^2,"") -> 24.009307 | AP17: =IFERROR($G17/$F17*100,"") -> 52.189055 | AQ17: =IFERROR($W17/$F17,"") -> 0.40696517 | AR17: =IF(OR($S17="",$I17=""),"",($S17-PI()*$I17/10)^2/(4*PI())-IF(IFERROR(INDEX(Cadastro!$F$8:$F$47,MATCH($B17,Cadastro!$B$8:$B$47,0)),"")="Feminino",6.5,10)) -> 59.607998 | AS17: =IF(OR($I17="",$J17="",$O17="",$F17=""),"",-0.7182+0.1451*(($I17+$J17+$O17)*(170.18/$F17))-0.00068*(($I17+$J17+$O17)*(170.18/$F17))^2+0.0000014*(($I17+$J17+$O17)*(170.18/$F17))^3) -> 2.513148 | AT17: =IF(OR($AE17="",$AF17="",$T17="",$AA17="",$F17=""),"",0.858*$AE17+0.601*$AF17+0.188*($T17-$I17/10)+0.161*($AA17-$R17/10)-0.131*$F17+4.5) -> 3.17107 | AU17: =IF(OR($E17="",$F17=""),"",IF($F17/$E17^(1/3)>=40.75,0.732*($F17/$E17^(1/3))-28.58,IF($F17/$E17^(1/3)>=38.25,0.463*($F17/$E17^(1/3))-17.63,0.1))) -> 3.4421062 | AV17: =IF(OR($AS17="",$AT17="",$AU17=""),"",IF(AND($AT17>=$AS17,$AT17>=$AU17),"Mesomorfo dominante",IF(AND($AU17>=$AS17,$AU17>=$AT17),"Ectomorfo dominante","Endomorfo dominante"))) -> Ectomorfo dominante
A18: 46034 | B18: Pedro Henrique Coutinho | C18: Pré-temporada | D18: Comissão técnica | E18: 93 | F18: 204 | G18: 106.5 | H18: 209.3 | I18: 7.8 | J18: 9.7 | K18: 5.1 | L18: 7.5 | M18: 9.6 | N18: 8.1 | O18: 9.3 | P18: 13.3 | Q18: 12.2 | R18: 8.1 | S18: 31.8 | T18: 36.5 | U18: 29 | V18: 103.5 | W18: 81.2 | X18: 83.6 | Y18: 97.7 | Z18: 57.1 | AA18: 38.6 | AB18: 18.6 | AC18: 41 | AD18: 28.2 | AE18: 7.7 | AF18: 10.4 | AG18: =IFERROR(DATEDIF(INDEX(Cadastro!$D$8:$D$47,MATCH($B18,Cadastro!$B$8:$B$47,0)),$A18,"Y"),"") -> 21 | AH18: =IF(COUNT($I18,$K18,$J18,$N18)<4,"",$I18+$K18+$J18+$N18) -> 30.7 | AI18: =IF(COUNT($L18,$M18,$I18,$J18,$P18,$N18,$Q18)<7,"",$L18+$M18+$I18+$J18+$P18+$N18+$Q18) -> 68.2 | AJ18: =IF(COUNT($I18,$J18,$K18,$O18,$P18,$Q18,$R18,$N18)<8,"",$I18+$J18+$K18+$O18+$P18+$Q18+$R18+$N18) -> 73.6 | AK18: =IF(OR($AI18="",$AG18=""),"",IF(IFERROR(INDEX(Cadastro!$F$8:$F$47,MATCH($B18,Cadastro!$B$8:$B$47,0)),"")="Feminino",1.097-0.00046971*$AI18+0.00000056*$AI18^2-0.00012828*$AG18,1.112-0.00043499*$AI18+0.00000055*$AI18^2-0.00028826*$AG18)) -> 1.0788384 | AL18: =IF(OR($AK18="",$AK18=0),"",495/$AK18-450) -> 8.8268254 | AM18: =IF(OR($AL18="",$E18=""),"",$E18*$AL18/100) -> 8.2089476 | AN18: =IF(OR($AM18="",$E18=""),"",$E18-$AM18) -> 84.791052 | AO18: =IFERROR($E18/($F18/100)^2,"") -> 22.347174 | AP18: =IFERROR($G18/$F18*100,"") -> 52.205882 | AQ18: =IFERROR($W18/$F18,"") -> 0.39803922 | AR18: =IF(OR($S18="",$I18=""),"",($S18-PI()*$I18/10)^2/(4*PI())-IF(IFERROR(INDEX(Cadastro!$F$8:$F$47,MATCH($B18,Cadastro!$B$8:$B$47,0)),"")="Feminino",6.5,10)) -> 58.547759 | AS18: =IF(OR($I18="",$J18="",$O18="",$F18=""),"",-0.7182+0.1451*(($I18+$J18+$O18)*(170.18/$F18))-0.00068*(($I18+$J18+$O18)*(170.18/$F18))^2+0.0000014*(($I18+$J18+$O18)*(170.18/$F18))^3) -> 2.2015551 | AT18: =IF(OR($AE18="",$AF18="",$T18="",$AA18="",$F18=""),"",0.858*$AE18+0.601*$AF18+0.188*($T18-$I18/10)+0.161*($AA18-$R18/10)-0.131*$F18+4.5) -> 3.43255 | AU18: =IF(OR($E18="",$F18=""),"",IF($F18/$E18^(1/3)>=40.75,0.732*($F18/$E18^(1/3))-28.58,IF($F18/$E18^(1/3)>=38.25,0.463*($F18/$E18^(1/3))-17.63,0.1))) -> 4.3794735 | AV18: =IF(OR($AS18="",$AT18="",$AU18=""),"",IF(AND($AT18>=$AS18,$AT18>=$AU18),"Mesomorfo dominante",IF(AND($AU18>=$AS18,$AU18>=$AT18),"Ectomorfo dominante","Endomorfo dominante"))) -> Ectomorfo dominante
A19: 46034 | B19: Caio Fernandes Bastos | C19: Pré-temporada | D19: Comissão técnica | E19: 79 | F19: 186 | G19: 97.1 | H19: 189.2 | I19: 10.7 | J19: 12.1 | K19: 3.1 | L19: 8 | M19: 6.8 | N19: 8.8 | O19: 8.4 | P19: 13.4 | Q19: 13.7 | R19: 9.7 | S19: 32.7 | T19: 35.8 | U19: 27.5 | V19: 96.4 | W19: 82.6 | X19: 82.6 | Y19: 95.5 | Z19: 58.9 | AA19: 39.4 | AB19: 17.1 | AC19: 41.8 | AD19: 29.6 | AE19: 7.4 | AF19: 9.8 | AG19: =IFERROR(DATEDIF(INDEX(Cadastro!$D$8:$D$47,MATCH($B19,Cadastro!$B$8:$B$47,0)),$A19,"Y"),"") -> 24 | AH19: =IF(COUNT($I19,$K19,$J19,$N19)<4,"",$I19+$K19+$J19+$N19) -> 34.7 | AI19: =IF(COUNT($L19,$M19,$I19,$J19,$P19,$N19,$Q19)<7,"",$L19+$M19+$I19+$J19+$P19+$N19+$Q19) -> 73.5 | AJ19: =IF(COUNT($I19,$J19,$K19,$O19,$P19,$Q19,$R19,$N19)<8,"",$I19+$J19+$K19+$O19+$P19+$Q19+$R19+$N19) -> 79.9 | AK19: =IF(OR($AI19="",$AG19=""),"",IF(IFERROR(INDEX(Cadastro!$F$8:$F$47,MATCH($B19,Cadastro!$B$8:$B$47,0)),"")="Feminino",1.097-0.00046971*$AI19+0.00000056*$AI19^2-0.00012828*$AG19,1.112-0.00043499*$AI19+0.00000055*$AI19^2-0.00028826*$AG19)) -> 1.0760812 | AL19: =IF(OR($AK19="",$AK19=0),"",495/$AK19-450) -> 10.002447 | AM19: =IF(OR($AL19="",$E19=""),"",$E19*$AL19/100) -> 7.901933 | AN19: =IF(OR($AM19="",$E19=""),"",$E19-$AM19) -> 71.098067 | AO19: =IFERROR($E19/($F19/100)^2,"") -> 22.83501 | AP19: =IFERROR($G19/$F19*100,"") -> 52.204301 | AQ19: =IFERROR($W19/$F19,"") -> 0.44408602 | AR19: =IF(OR($S19="",$I19=""),"",($S19-PI()*$I19/10)^2/(4*PI())-IF(IFERROR(INDEX(Cadastro!$F$8:$F$47,MATCH($B19,Cadastro!$B$8:$B$47,0)),"")="Feminino",6.5,10)) -> 58.496097 | AS19: =IF(OR($I19="",$J19="",$O19="",$F19=""),"",-0.7182+0.1451*(($I19+$J19+$O19)*(170.18/$F19))-0.00068*(($I19+$J19+$O19)*(170.18/$F19))^2+0.0000014*(($I19+$J19+$O19)*(170.18/$F19))^3) -> 2.9023115 | AT19: =IF(OR($AE19="",$AF19="",$T19="",$AA19="",$F19=""),"",0.858*$AE19+0.601*$AF19+0.188*($T19-$I19/10)+0.161*($AA19-$R19/10)-0.131*$F19+4.5) -> 5.08947 | AU19: =IF(OR($E19="",$F19=""),"",IF($F19/$E19^(1/3)>=40.75,0.732*($F19/$E19^(1/3))-28.58,IF($F19/$E19^(1/3)>=38.25,0.463*($F19/$E19^(1/3))-17.63,0.1))) -> 3.1508467 | AV19: =IF(OR($AS19="",$AT19="",$AU19=""),"",IF(AND($AT19>=$AS19,$AT19>=$AU19),"Mesomorfo dominante",IF(AND($AU19>=$AS19,$AU19>=$AT19),"Ectomorfo dominante","Endomorfo dominante"))) -> Mesomorfo dominante
... A31: 46225 | B31: Caio Fernandes Bastos | C31: Meio da Temporada | D31: Comissão técnica | E31: 78.2 | F31: 186 | G31: 97.1 | H31: 190.9 | I31: 10.1 | J31: 10.3 | K31: 3.1 | L31: 6.8 | M31: 6 | N31: 7.6 | O31: 5.6 | P31: 15.2 | Q31: 10.2 | R31: 6.6 | S31: 31.7 | T31: 34.6 | U31: 28.3 | V31: 98.2 | W31: 77.5 | X31: 81.6 | Y31: 99.1 | Z31: 55.9 | AA31: 40.6 | AB31: 17.6 | AC31: 41.9 | AD31: 29.7 | AE31: 7.2 | AF31: 10.1 | AG31: =IFERROR(DATEDIF(INDEX(Cadastro!$D$8:$D$47,MATCH($B31,Cadastro!$B$8:$B$47,0)),$A31,"Y"),"") -> 24 | AH31: =IF(COUNT($I31,$K31,$J31,$N31)<4,"",$I31+$K31+$J31+$N31) -> 31.1 | AI31: =IF(COUNT($L31,$M31,$I31,$J31,$P31,$N31,$Q31)<7,"",$L31+$M31+$I31+$J31+$P31+$N31+$Q31) -> 66.2 | AJ31: =IF(COUNT($I31,$J31,$K31,$O31,$P31,$Q31,$R31,$N31)<8,"",$I31+$J31+$K31+$O31+$P31+$Q31+$R31+$N31) -> 68.7 | AK31: =IF(OR($AI31="",$AG31=""),"",IF(IFERROR(INDEX(Cadastro!$F$8:$F$47,MATCH($B31,Cadastro!$B$8:$B$47,0)),"")="Feminino",1.097-0.00046971*$AI31+0.00000056*$AI31^2-0.00012828*$AG31,1.112-0.00043499*$AI31+0.00000055*$AI31^2-0.00028826*$AG31)) -> 1.0786958 | AL31: =IF(OR($AK31="",$AK31=0),"",495/$AK31-450) -> 8.8874978 | AM31: =IF(OR($AL31="",$E31=""),"",$E31*$AL31/100) -> 6.9500233 | AN31: =IF(OR($AM31="",$E31=""),"",$E31-$AM31) -> 71.249977 | AO31: =IFERROR($E31/($F31/100)^2,"") -> 22.603769 | AP31: =IFERROR($G31/$F31*100,"") -> 52.204301 | AQ31: =IFERROR($W31/$F31,"") -> 0.41666667 | AR31: =IF(OR($S31="",$I31=""),"",($S31-PI()*$I31/10)^2/(4*PI())-IF(IFERROR(INDEX(Cadastro!$F$8:$F$47,MATCH($B31,Cadastro!$B$8:$B$47,0)),"")="Feminino",6.5,10)) -> 54.75929 | AS31: =IF(OR($I31="",$J31="",$O31="",$F31=""),"",-0.7182+0.1451*(($I31+$J31+$O31)*(170.18/$F31))-0.00068*(($I31+$J31+$O31)*(170.18/$F31))^2+0.0000014*(($I31+$J31+$O31)*(170.18/$F31))^3) -> 2.3675625 | AT31: =IF(OR($AE31="",$AF31="",$T31="",$AA31="",$F31=""),"",0.858*$AE31+0.601*$AF31+0.188*($T31-$I31/10)+0.161*($AA31-$R31/10)-0.131*$F31+4.5) -> 5.12696 | AU31: =IF(OR($E31="",$F31=""),"",IF($F31/$E31^(1/3)>=40.75,0.732*($F31/$E31^(1/3))-28.58,IF($F31/$E31^(1/3)>=38.25,0.463*($F31/$E31^(1/3))-17.63,0.1))) -> 3.2586839 | AV31: =IF(OR($AS31="",$AT31="",$AU31=""),"",IF(AND($AT31>=$AS31,$AT31>=$AU31),"Mesomorfo dominante",IF(AND($AU31>=$AS31,$AU31>=$AT31),"Ectomorfo dominante","Endomorfo dominante"))) -> Mesomorfo dominante
AG32: =IFERROR(DATEDIF(INDEX(Cadastro!$D$8:$D$47,MATCH($B32,Cadastro!$B$8:$B$47,0)),$A32,"Y"),"") | AH32: =IF(COUNT($I32,$K32,$J32,$N32)<4,"",$I32+$K32+$J32+$N32) | AI32: =IF(COUNT($L32,$M32,$I32,$J32,$P32,$N32,$Q32)<7,"",$L32+$M32+$I32+$J32+$P32+$N32+$Q32) | AJ32: =IF(COUNT($I32,$J32,$K32,$O32,$P32,$Q32,$R32,$N32)<8,"",$I32+$J32+$K32+$O32+$P32+$Q32+$R32+$N32) | AK32: =IF(OR($AI32="",$AG32=""),"",IF(IFERROR(INDEX(Cadastro!$F$8:$F$47,MATCH($B32,Cadastro!$B$8:$B$47,0)),"")="Feminino",1.097-0.00046971*$AI32+0.00000056*$AI32^2-0.00012828*$AG32,1.112-0.00043499*$AI32+0.00000055*$AI32^2-0.00028826*$AG32)) | AL32: =IF(OR($AK32="",$AK32=0),"",495/$AK32-450) | AM32: =IF(OR($AL32="",$E32=""),"",$E32*$AL32/100) | AN32: =IF(OR($AM32="",$E32=""),"",$E32-$AM32) | AO32: =IFERROR($E32/($F32/100)^2,"") | AP32: =IFERROR($G32/$F32*100,"") | AQ32: =IFERROR($W32/$F32,"") | AR32: =IF(OR($S32="",$I32=""),"",($S32-PI()*$I32/10)^2/(4*PI())-IF(IFERROR(INDEX(Cadastro!$F$8:$F$47,MATCH($B32,Cadastro!$B$8:$B$47,0)),"")="Feminino",6.5,10)) | AS32: =IF(OR($I32="",$J32="",$O32="",$F32=""),"",-0.7182+0.1451*(($I32+$J32+$O32)*(170.18/$F32))-0.00068*(($I32+$J32+$O32)*(170.18/$F32))^2+0.0000014*(($I32+$J32+$O32)*(170.18/$F32))^3) | AT32: =IF(OR($AE32="",$AF32="",$T32="",$AA32="",$F32=""),"",0.858*$AE32+0.601*$AF32+0.188*($T32-$I32/10)+0.161*($AA32-$R32/10)-0.131*$F32+4.5) | AU32: =IF(OR($E32="",$F32=""),"",IF($F32/$E32^(1/3)>=40.75,0.732*($F32/$E32^(1/3))-28.58,IF($F32/$E32^(1/3)>=38.25,0.463*($F32/$E32^(1/3))-17.63,0.1))) | AV32: =IF(OR($AS32="",$AT32="",$AU32=""),"",IF(AND($AT32>=$AS32,$AT32>=$AU32),"Mesomorfo dominante",IF(AND($AU32>=$AS32,$AU32>=$AT32),"Ectomorfo dominante","Endomorfo dominante")))
AG33: =IFERROR(DATEDIF(INDEX(Cadastro!$D$8:$D$47,MATCH($B33,Cadastro!$B$8:$B$47,0)),$A33,"Y"),"") | AH33: =IF(COUNT($I33,$K33,$J33,$N33)<4,"",$I33+$K33+$J33+$N33) | AI33: =IF(COUNT($L33,$M33,$I33,$J33,$P33,$N33,$Q33)<7,"",$L33+$M33+$I33+$J33+$P33+$N33+$Q33) | AJ33: =IF(COUNT($I33,$J33,$K33,$O33,$P33,$Q33,$R33,$N33)<8,"",$I33+$J33+$K33+$O33+$P33+$Q33+$R33+$N33) | AK33: =IF(OR($AI33="",$AG33=""),"",IF(IFERROR(INDEX(Cadastro!$F$8:$F$47,MATCH($B33,Cadastro!$B$8:$B$47,0)),"")="Feminino",1.097-0.00046971*$AI33+0.00000056*$AI33^2-0.00012828*$AG33,1.112-0.00043499*$AI33+0.00000055*$AI33^2-0.00028826*$AG33)) | AL33: =IF(OR($AK33="",$AK33=0),"",495/$AK33-450) | AM33: =IF(OR($AL33="",$E33=""),"",$E33*$AL33/100) | AN33: =IF(OR($AM33="",$E33=""),"",$E33-$AM33) | AO33: =IFERROR($E33/($F33/100)^2,"") | AP33: =IFERROR($G33/$F33*100,"") | AQ33: =IFERROR($W33/$F33,"") | AR33: =IF(OR($S33="",$I33=""),"",($S33-PI()*$I33/10)^2/(4*PI())-IF(IFERROR(INDEX(Cadastro!$F$8:$F$47,MATCH($B33,Cadastro!$B$8:$B$47,0)),"")="Feminino",6.5,10)) | AS33: =IF(OR($I33="",$J33="",$O33="",$F33=""),"",-0.7182+0.1451*(($I33+$J33+$O33)*(170.18/$F33))-0.00068*(($I33+$J33+$O33)*(170.18/$F33))^2+0.0000014*(($I33+$J33+$O33)*(170.18/$F33))^3) | AT33: =IF(OR($AE33="",$AF33="",$T33="",$AA33="",$F33=""),"",0.858*$AE33+0.601*$AF33+0.188*($T33-$I33/10)+0.161*($AA33-$R33/10)-0.131*$F33+4.5) | AU33: =IF(OR($E33="",$F33=""),"",IF($F33/$E33^(1/3)>=40.75,0.732*($F33/$E33^(1/3))-28.58,IF($F33/$E33^(1/3)>=38.25,0.463*($F33/$E33^(1/3))-17.63,0.1))) | AV33: =IF(OR($AS33="",$AT33="",$AU33=""),"",IF(AND($AT33>=$AS33,$AT33>=$AU33),"Mesomorfo dominante",IF(AND($AU33>=$AS33,$AU33>=$AT33),"Ectomorfo dominante","Endomorfo dominante")))
AG34: =IFERROR(DATEDIF(INDEX(Cadastro!$D$8:$D$47,MATCH($B34,Cadastro!$B$8:$B$47,0)),$A34,"Y"),"") | AH34: =IF(COUNT($I34,$K34,$J34,$N34)<4,"",$I34+$K34+$J34+$N34) | AI34: =IF(COUNT($L34,$M34,$I34,$J34,$P34,$N34,$Q34)<7,"",$L34+$M34+$I34+$J34+$P34+$N34+$Q34) | AJ34: =IF(COUNT($I34,$J34,$K34,$O34,$P34,$Q34,$R34,$N34)<8,"",$I34+$J34+$K34+$O34+$P34+$Q34+$R34+$N34) | AK34: =IF(OR($AI34="",$AG34=""),"",IF(IFERROR(INDEX(Cadastro!$F$8:$F$47,MATCH($B34,Cadastro!$B$8:$B$47,0)),"")="Feminino",1.097-0.00046971*$AI34+0.00000056*$AI34^2-0.00012828*$AG34,1.112-0.00043499*$AI34+0.00000055*$AI34^2-0.00028826*$AG34)) | AL34: =IF(OR($AK34="",$AK34=0),"",495/$AK34-450) | AM34: =IF(OR($AL34="",$E34=""),"",$E34*$AL34/100) | AN34: =IF(OR($AM34="",$E34=""),"",$E34-$AM34) | AO34: =IFERROR($E34/($F34/100)^2,"") | AP34: =IFERROR($G34/$F34*100,"") | AQ34: =IFERROR($W34/$F34,"") | AR34: =IF(OR($S34="",$I34=""),"",($S34-PI()*$I34/10)^2/(4*PI())-IF(IFERROR(INDEX(Cadastro!$F$8:$F$47,MATCH($B34,Cadastro!$B$8:$B$47,0)),"")="Feminino",6.5,10)) | AS34: =IF(OR($I34="",$J34="",$O34="",$F34=""),"",-0.7182+0.1451*(($I34+$J34+$O34)*(170.18/$F34))-0.00068*(($I34+$J34+$O34)*(170.18/$F34))^2+0.0000014*(($I34+$J34+$O34)*(170.18/$F34))^3) | AT34: =IF(OR($AE34="",$AF34="",$T34="",$AA34="",$F34=""),"",0.858*$AE34+0.601*$AF34+0.188*($T34-$I34/10)+0.161*($AA34-$R34/10)-0.131*$F34+4.5) | AU34: =IF(OR($E34="",$F34=""),"",IF($F34/$E34^(1/3)>=40.75,0.732*($F34/$E34^(1/3))-28.58,IF($F34/$E34^(1/3)>=38.25,0.463*($F34/$E34^(1/3))-17.63,0.1))) | AV34: =IF(OR($AS34="",$AT34="",$AU34=""),"",IF(AND($AT34>=$AS34,$AT34>=$AU34),"Mesomorfo dominante",IF(AND($AU34>=$AS34,$AU34>=$AT34),"Ectomorfo dominante","Endomorfo dominante")))
AG35: =IFERROR(DATEDIF(INDEX(Cadastro!$D$8:$D$47,MATCH($B35,Cadastro!$B$8:$B$47,0)),$A35,"Y"),"") | AH35: =IF(COUNT($I35,$K35,$J35,$N35)<4,"",$I35+$K35+$J35+$N35) | AI35: =IF(COUNT($L35,$M35,$I35,$J35,$P35,$N35,$Q35)<7,"",$L35+$M35+$I35+$J35+$P35+$N35+$Q35) | AJ35: =IF(COUNT($I35,$J35,$K35,$O35,$P35,$Q35,$R35,$N35)<8,"",$I35+$J35+$K35+$O35+$P35+$Q35+$R35+$N35) | AK35: =IF(OR($AI35="",$AG35=""),"",IF(IFERROR(INDEX(Cadastro!$F$8:$F$47,MATCH($B35,Cadastro!$B$8:$B$47,0)),"")="Feminino",1.097-0.00046971*$AI35+0.00000056*$AI35^2-0.00012828*$AG35,1.112-0.00043499*$AI35+0.00000055*$AI35^2-0.00028826*$AG35)) | AL35: =IF(OR($AK35="",$AK35=0),"",495/$AK35-450) | AM35: =IF(OR($AL35="",$E35=""),"",$E35*$AL35/100) | AN35: =IF(OR($AM35="",$E35=""),"",$E35-$AM35) | AO35: =IFERROR($E35/($F35/100)^2,"") | AP35: =IFERROR($G35/$F35*100,"") | AQ35: =IFERROR($W35/$F35,"") | AR35: =IF(OR($S35="",$I35=""),"",($S35-PI()*$I35/10)^2/(4*PI())-IF(IFERROR(INDEX(Cadastro!$F$8:$F$47,MATCH($B35,Cadastro!$B$8:$B$47,0)),"")="Feminino",6.5,10)) | AS35: =IF(OR($I35="",$J35="",$O35="",$F35=""),"",-0.7182+0.1451*(($I35+$J35+$O35)*(170.18/$F35))-0.00068*(($I35+$J35+$O35)*(170.18/$F35))^2+0.0000014*(($I35+$J35+$O35)*(170.18/$F35))^3) | AT35: =IF(OR($AE35="",$AF35="",$T35="",$AA35="",$F35=""),"",0.858*$AE35+0.601*$AF35+0.188*($T35-$I35/10)+0.161*($AA35-$R35/10)-0.131*$F35+4.5) | AU35: =IF(OR($E35="",$F35=""),"",IF($F35/$E35^(1/3)>=40.75,0.732*($F35/$E35^(1/3))-28.58,IF($F35/$E35^(1/3)>=38.25,0.463*($F35/$E35^(1/3))-17.63,0.1))) | AV35: =IF(OR($AS35="",$AT35="",$AU35=""),"",IF(AND($AT35>=$AS35,$AT35>=$AU35),"Mesomorfo dominante",IF(AND($AU35>=$AS35,$AU35>=$AT35),"Ectomorfo dominante","Endomorfo dominante")))
AG36: =IFERROR(DATEDIF(INDEX(Cadastro!$D$8:$D$47,MATCH($B36,Cadastro!$B$8:$B$47,0)),$A36,"Y"),"") | AH36: =IF(COUNT($I36,$K36,$J36,$N36)<4,"",$I36+$K36+$J36+$N36) | AI36: =IF(COUNT($L36,$M36,$I36,$J36,$P36,$N36,$Q36)<7,"",$L36+$M36+$I36+$J36+$P36+$N36+$Q36) | AJ36: =IF(COUNT($I36,$J36,$K36,$O36,$P36,$Q36,$R36,$N36)<8,"",$I36+$J36+$K36+$O36+$P36+$Q36+$R36+$N36) | AK36: =IF(OR($AI36="",$AG36=""),"",IF(IFERROR(INDEX(Cadastro!$F$8:$F$47,MATCH($B36,Cadastro!$B$8:$B$47,0)),"")="Feminino",1.097-0.00046971*$AI36+0.00000056*$AI36^2-0.00012828*$AG36,1.112-0.00043499*$AI36+0.00000055*$AI36^2-0.00028826*$AG36)) | AL36: =IF(OR($AK36="",$AK36=0),"",495/$AK36-450) | AM36: =IF(OR($AL36="",$E36=""),"",$E36*$AL36/100) | AN36: =IF(OR($AM36="",$E36=""),"",$E36-$AM36) | AO36: =IFERROR($E36/($F36/100)^2,"") | AP36: =IFERROR($G36/$F36*100,"") | AQ36: =IFERROR($W36/$F36,"") | AR36: =IF(OR($S36="",$I36=""),"",($S36-PI()*$I36/10)^2/(4*PI())-IF(IFERROR(INDEX(Cadastro!$F$8:$F$47,MATCH($B36,Cadastro!$B$8:$B$47,0)),"")="Feminino",6.5,10)) | AS36: =IF(OR($I36="",$J36="",$O36="",$F36=""),"",-0.7182+0.1451*(($I36+$J36+$O36)*(170.18/$F36))-0.00068*(($I36+$J36+$O36)*(170.18/$F36))^2+0.0000014*(($I36+$J36+$O36)*(170.18/$F36))^3) | AT36: =IF(OR($AE36="",$AF36="",$T36="",$AA36="",$F36=""),"",0.858*$AE36+0.601*$AF36+0.188*($T36-$I36/10)+0.161*($AA36-$R36/10)-0.131*$F36+4.5) | AU36: =IF(OR($E36="",$F36=""),"",IF($F36/$E36^(1/3)>=40.75,0.732*($F36/$E36^(1/3))-28.58,IF($F36/$E36^(1/3)>=38.25,0.463*($F36/$E36^(1/3))-17.63,0.1))) | AV36: =IF(OR($AS36="",$AT36="",$AU36=""),"",IF(AND($AT36>=$AS36,$AT36>=$AU36),"Mesomorfo dominante",IF(AND($AU36>=$AS36,$AU36>=$AT36),"Ectomorfo dominante","Endomorfo dominante")))
AG37: =IFERROR(DATEDIF(INDEX(Cadastro!$D$8:$D$47,MATCH($B37,Cadastro!$B$8:$B$47,0)),$A37,"Y"),"") | AH37: =IF(COUNT($I37,$K37,$J37,$N37)<4,"",$I37+$K37+$J37+$N37) | AI37: =IF(COUNT($L37,$M37,$I37,$J37,$P37,$N37,$Q37)<7,"",$L37+$M37+$I37+$J37+$P37+$N37+$Q37) | AJ37: =IF(COUNT($I37,$J37,$K37,$O37,$P37,$Q37,$R37,$N37)<8,"",$I37+$J37+$K37+$O37+$P37+$Q37+$R37+$N37) | AK37: =IF(OR($AI37="",$AG37=""),"",IF(IFERROR(INDEX(Cadastro!$F$8:$F$47,MATCH($B37,Cadastro!$B$8:$B$47,0)),"")="Feminino",1.097-0.00046971*$AI37+0.00000056*$AI37^2-0.00012828*$AG37,1.112-0.00043499*$AI37+0.00000055*$AI37^2-0.00028826*$AG37)) | AL37: =IF(OR($AK37="",$AK37=0),"",495/$AK37-450) | AM37: =IF(OR($AL37="",$E37=""),"",$E37*$AL37/100) | AN37: =IF(OR($AM37="",$E37=""),"",$E37-$AM37) | AO37: =IFERROR($E37/($F37/100)^2,"") | AP37: =IFERROR($G37/$F37*100,"") | AQ37: =IFERROR($W37/$F37,"") | AR37: =IF(OR($S37="",$I37=""),"",($S37-PI()*$I37/10)^2/(4*PI())-IF(IFERROR(INDEX(Cadastro!$F$8:$F$47,MATCH($B37,Cadastro!$B$8:$B$47,0)),"")="Feminino",6.5,10)) | AS37: =IF(OR($I37="",$J37="",$O37="",$F37=""),"",-0.7182+0.1451*(($I37+$J37+$O37)*(170.18/$F37))-0.00068*(($I37+$J37+$O37)*(170.18/$F37))^2+0.0000014*(($I37+$J37+$O37)*(170.18/$F37))^3) | AT37: =IF(OR($AE37="",$AF37="",$T37="",$AA37="",$F37=""),"",0.858*$AE37+0.601*$AF37+0.188*($T37-$I37/10)+0.161*($AA37-$R37/10)-0.131*$F37+4.5) | AU37: =IF(OR($E37="",$F37=""),"",IF($F37/$E37^(1/3)>=40.75,0.732*($F37/$E37^(1/3))-28.58,IF($F37/$E37^(1/3)>=38.25,0.463*($F37/$E37^(1/3))-17.63,0.1))) | AV37: =IF(OR($AS37="",$AT37="",$AU37=""),"",IF(AND($AT37>=$AS37,$AT37>=$AU37),"Mesomorfo dominante",IF(AND($AU37>=$AS37,$AU37>=$AT37),"Ectomorfo dominante","Endomorfo dominante")))
AG38: =IFERROR(DATEDIF(INDEX(Cadastro!$D$8:$D$47,MATCH($B38,Cadastro!$B$8:$B$47,0)),$A38,"Y"),"") | AH38: =IF(COUNT($I38,$K38,$J38,$N38)<4,"",$I38+$K38+$J38+$N38) | AI38: =IF(COUNT($L38,$M38,$I38,$J38,$P38,$N38,$Q38)<7,"",$L38+$M38+$I38+$J38+$P38+$N38+$Q38) | AJ38: =IF(COUNT($I38,$J38,$K38,$O38,$P38,$Q38,$R38,$N38)<8,"",$I38+$J38+$K38+$O38+$P38+$Q38+$R38+$N38) | AK38: =IF(OR($AI38="",$AG38=""),"",IF(IFERROR(INDEX(Cadastro!$F$8:$F$47,MATCH($B38,Cadastro!$B$8:$B$47,0)),"")="Feminino",1.097-0.00046971*$AI38+0.00000056*$AI38^2-0.00012828*$AG38,1.112-0.00043499*$AI38+0.00000055*$AI38^2-0.00028826*$AG38)) | AL38: =IF(OR($AK38="",$AK38=0),"",495/$AK38-450) | AM38: =IF(OR($AL38="",$E38=""),"",$E38*$AL38/100) | AN38: =IF(OR($AM38="",$E38=""),"",$E38-$AM38) | AO38: =IFERROR($E38/($F38/100)^2,"") | AP38: =IFERROR($G38/$F38*100,"") | AQ38: =IFERROR($W38/$F38,"") | AR38: =IF(OR($S38="",$I38=""),"",($S38-PI()*$I38/10)^2/(4*PI())-IF(IFERROR(INDEX(Cadastro!$F$8:$F$47,MATCH($B38,Cadastro!$B$8:$B$47,0)),"")="Feminino",6.5,10)) | AS38: =IF(OR($I38="",$J38="",$O38="",$F38=""),"",-0.7182+0.1451*(($I38+$J38+$O38)*(170.18/$F38))-0.00068*(($I38+$J38+$O38)*(170.18/$F38))^2+0.0000014*(($I38+$J38+$O38)*(170.18/$F38))^3) | AT38: =IF(OR($AE38="",$AF38="",$T38="",$AA38="",$F38=""),"",0.858*$AE38+0.601*$AF38+0.188*($T38-$I38/10)+0.161*($AA38-$R38/10)-0.131*$F38+4.5) | AU38: =IF(OR($E38="",$F38=""),"",IF($F38/$E38^(1/3)>=40.75,0.732*($F38/$E38^(1/3))-28.58,IF($F38/$E38^(1/3)>=38.25,0.463*($F38/$E38^(1/3))-17.63,0.1))) | AV38: =IF(OR($AS38="",$AT38="",$AU38=""),"",IF(AND($AT38>=$AS38,$AT38>=$AU38),"Mesomorfo dominante",IF(AND($AU38>=$AS38,$AU38>=$AT38),"Ectomorfo dominante","Endomorfo dominante")))
AG39: =IFERROR(DATEDIF(INDEX(Cadastro!$D$8:$D$47,MATCH($B39,Cadastro!$B$8:$B$47,0)),$A39,"Y"),"") | AH39: =IF(COUNT($I39,$K39,$J39,$N39)<4,"",$I39+$K39+$J39+$N39) | AI39: =IF(COUNT($L39,$M39,$I39,$J39,$P39,$N39,$Q39)<7,"",$L39+$M39+$I39+$J39+$P39+$N39+$Q39) | AJ39: =IF(COUNT($I39,$J39,$K39,$O39,$P39,$Q39,$R39,$N39)<8,"",$I39+$J39+$K39+$O39+$P39+$Q39+$R39+$N39) | AK39: =IF(OR($AI39="",$AG39=""),"",IF(IFERROR(INDEX(Cadastro!$F$8:$F$47,MATCH($B39,Cadastro!$B$8:$B$47,0)),"")="Feminino",1.097-0.00046971*$AI39+0.00000056*$AI39^2-0.00012828*$AG39,1.112-0.00043499*$AI39+0.00000055*$AI39^2-0.00028826*$AG39)) | AL39: =IF(OR($AK39="",$AK39=0),"",495/$AK39-450) | AM39: =IF(OR($AL39="",$E39=""),"",$E39*$AL39/100) | AN39: =IF(OR($AM39="",$E39=""),"",$E39-$AM39) | AO39: =IFERROR($E39/($F39/100)^2,"") | AP39: =IFERROR($G39/$F39*100,"") | AQ39: =IFERROR($W39/$F39,"") | AR39: =IF(OR($S39="",$I39=""),"",($S39-PI()*$I39/10)^2/(4*PI())-IF(IFERROR(INDEX(Cadastro!$F$8:$F$47,MATCH($B39,Cadastro!$B$8:$B$47,0)),"")="Feminino",6.5,10)) | AS39: =IF(OR($I39="",$J39="",$O39="",$F39=""),"",-0.7182+0.1451*(($I39+$J39+$O39)*(170.18/$F39))-0.00068*(($I39+$J39+$O39)*(170.18/$F39))^2+0.0000014*(($I39+$J39+$O39)*(170.18/$F39))^3) | AT39: =IF(OR($AE39="",$AF39="",$T39="",$AA39="",$F39=""),"",0.858*$AE39+0.601*$AF39+0.188*($T39-$I39/10)+0.161*($AA39-$R39/10)-0.131*$F39+4.5) | AU39: =IF(OR($E39="",$F39=""),"",IF($F39/$E39^(1/3)>=40.75,0.732*($F39/$E39^(1/3))-28.58,IF($F39/$E39^(1/3)>=38.25,0.463*($F39/$E39^(1/3))-17.63,0.1))) | AV39: =IF(OR($AS39="",$AT39="",$AU39=""),"",IF(AND($AT39>=$AS39,$AT39>=$AU39),"Mesomorfo dominante",IF(AND($AU39>=$AS39,$AU39>=$AT39),"Ectomorfo dominante","Endomorfo dominante")))
AG40: =IFERROR(DATEDIF(INDEX(Cadastro!$D$8:$D$47,MATCH($B40,Cadastro!$B$8:$B$47,0)),$A40,"Y"),"") | AH40: =IF(COUNT($I40,$K40,$J40,$N40)<4,"",$I40+$K40+$J40+$N40) | AI40: =IF(COUNT($L40,$M40,$I40,$J40,$P40,$N40,$Q40)<7,"",$L40+$M40+$I40+$J40+$P40+$N40+$Q40) | AJ40: =IF(COUNT($I40,$J40,$K40,$O40,$P40,$Q40,$R40,$N40)<8,"",$I40+$J40+$K40+$O40+$P40+$Q40+$R40+$N40) | AK40: =IF(OR($AI40="",$AG40=""),"",IF(IFERROR(INDEX(Cadastro!$F$8:$F$47,MATCH($B40,Cadastro!$B$8:$B$47,0)),"")="Feminino",1.097-0.00046971*$AI40+0.00000056*$AI40^2-0.00012828*$AG40,1.112-0.00043499*$AI40+0.00000055*$AI40^2-0.00028826*$AG40)) | AL40: =IF(OR($AK40="",$AK40=0),"",495/$AK40-450) | AM40: =IF(OR($AL40="",$E40=""),"",$E40*$AL40/100) | AN40: =IF(OR($AM40="",$E40=""),"",$E40-$AM40) | AO40: =IFERROR($E40/($F40/100)^2,"") | AP40: =IFERROR($G40/$F40*100,"") | AQ40: =IFERROR($W40/$F40,"") | AR40: =IF(OR($S40="",$I40=""),"",($S40-PI()*$I40/10)^2/(4*PI())-IF(IFERROR(INDEX(Cadastro!$F$8:$F$47,MATCH($B40,Cadastro!$B$8:$B$47,0)),"")="Feminino",6.5,10)) | AS40: =IF(OR($I40="",$J40="",$O40="",$F40=""),"",-0.7182+0.1451*(($I40+$J40+$O40)*(170.18/$F40))-0.00068*(($I40+$J40+$O40)*(170.18/$F40))^2+0.0000014*(($I40+$J40+$O40)*(170.18/$F40))^3) | AT40: =IF(OR($AE40="",$AF40="",$T40="",$AA40="",$F40=""),"",0.858*$AE40+0.601*$AF40+0.188*($T40-$I40/10)+0.161*($AA40-$R40/10)-0.131*$F40+4.5) | AU40: =IF(OR($E40="",$F40=""),"",IF($F40/$E40^(1/3)>=40.75,0.732*($F40/$E40^(1/3))-28.58,IF($F40/$E40^(1/3)>=38.25,0.463*($F40/$E40^(1/3))-17.63,0.1))) | AV40: =IF(OR($AS40="",$AT40="",$AU40=""),"",IF(AND($AT40>=$AS40,$AT40>=$AU40),"Mesomorfo dominante",IF(AND($AU40>=$AS40,$AU40>=$AT40),"Ectomorfo dominante","Endomorfo dominante")))
AG41: =IFERROR(DATEDIF(INDEX(Cadastro!$D$8:$D$47,MATCH($B41,Cadastro!$B$8:$B$47,0)),$A41,"Y"),"") | AH41: =IF(COUNT($I41,$K41,$J41,$N41)<4,"",$I41+$K41+$J41+$N41) | AI41: =IF(COUNT($L41,$M41,$I41,$J41,$P41,$N41,$Q41)<7,"",$L41+$M41+$I41+$J41+$P41+$N41+$Q41) | AJ41: =IF(COUNT($I41,$J41,$K41,$O41,$P41,$Q41,$R41,$N41)<8,"",$I41+$J41+$K41+$O41+$P41+$Q41+$R41+$N41) | AK41: =IF(OR($AI41="",$AG41=""),"",IF(IFERROR(INDEX(Cadastro!$F$8:$F$47,MATCH($B41,Cadastro!$B$8:$B$47,0)),"")="Feminino",1.097-0.00046971*$AI41+0.00000056*$AI41^2-0.00012828*$AG41,1.112-0.00043499*$AI41+0.00000055*$AI41^2-0.00028826*$AG41)) | AL41: =IF(OR($AK41="",$AK41=0),"",495/$AK41-450) | AM41: =IF(OR($AL41="",$E41=""),"",$E41*$AL41/100) | AN41: =IF(OR($AM41="",$E41=""),"",$E41-$AM41) | AO41: =IFERROR($E41/($F41/100)^2,"") | AP41: =IFERROR($G41/$F41*100,"") | AQ41: =IFERROR($W41/$F41,"") | AR41: =IF(OR($S41="",$I41=""),"",($S41-PI()*$I41/10)^2/(4*PI())-IF(IFERROR(INDEX(Cadastro!$F$8:$F$47,MATCH($B41,Cadastro!$B$8:$B$47,0)),"")="Feminino",6.5,10)) | AS41: =IF(OR($I41="",$J41="",$O41="",$F41=""),"",-0.7182+0.1451*(($I41+$J41+$O41)*(170.18/$F41))-0.00068*(($I41+$J41+$O41)*(170.18/$F41))^2+0.0000014*(($I41+$J41+$O41)*(170.18/$F41))^3) | AT41: =IF(OR($AE41="",$AF41="",$T41="",$AA41="",$F41=""),"",0.858*$AE41+0.601*$AF41+0.188*($T41-$I41/10)+0.161*($AA41-$R41/10)-0.131*$F41+4.5) | AU41: =IF(OR($E41="",$F41=""),"",IF($F41/$E41^(1/3)>=40.75,0.732*($F41/$E41^(1/3))-28.58,IF($F41/$E41^(1/3)>=38.25,0.463*($F41/$E41^(1/3))-17.63,0.1))) | AV41: =IF(OR($AS41="",$AT41="",$AU41=""),"",IF(AND($AT41>=$AS41,$AT41>=$AU41),"Mesomorfo dominante",IF(AND($AU41>=$AS41,$AU41>=$AT41),"Ectomorfo dominante","Endomorfo dominante")))
AG42: =IFERROR(DATEDIF(INDEX(Cadastro!$D$8:$D$47,MATCH($B42,Cadastro!$B$8:$B$47,0)),$A42,"Y"),"") | AH42: =IF(COUNT($I42,$K42,$J42,$N42)<4,"",$I42+$K42+$J42+$N42) | AI42: =IF(COUNT($L42,$M42,$I42,$J42,$P42,$N42,$Q42)<7,"",$L42+$M42+$I42+$J42+$P42+$N42+$Q42) | AJ42: =IF(COUNT($I42,$J42,$K42,$O42,$P42,$Q42,$R42,$N42)<8,"",$I42+$J42+$K42+$O42+$P42+$Q42+$R42+$N42) | AK42: =IF(OR($AI42="",$AG42=""),"",IF(IFERROR(INDEX(Cadastro!$F$8:$F$47,MATCH($B42,Cadastro!$B$8:$B$47,0)),"")="Feminino",1.097-0.00046971*$AI42+0.00000056*$AI42^2-0.00012828*$AG42,1.112-0.00043499*$AI42+0.00000055*$AI42^2-0.00028826*$AG42)) | AL42: =IF(OR($AK42="",$AK42=0),"",495/$AK42-450) | AM42: =IF(OR($AL42="",$E42=""),"",$E42*$AL42/100) | AN42: =IF(OR($AM42="",$E42=""),"",$E42-$AM42) | AO42: =IFERROR($E42/($F42/100)^2,"") | AP42: =IFERROR($G42/$F42*100,"") | AQ42: =IFERROR($W42/$F42,"") | AR42: =IF(OR($S42="",$I42=""),"",($S42-PI()*$I42/10)^2/(4*PI())-IF(IFERROR(INDEX(Cadastro!$F$8:$F$47,MATCH($B42,Cadastro!$B$8:$B$47,0)),"")="Feminino",6.5,10)) | AS42: =IF(OR($I42="",$J42="",$O42="",$F42=""),"",-0.7182+0.1451*(($I42+$J42+$O42)*(170.18/$F42))-0.00068*(($I42+$J42+$O42)*(170.18/$F42))^2+0.0000014*(($I42+$J42+$O42)*(170.18/$F42))^3) | AT42: =IF(OR($AE42="",$AF42="",$T42="",$AA42="",$F42=""),"",0.858*$AE42+0.601*$AF42+0.188*($T42-$I42/10)+0.161*($AA42-$R42/10)-0.131*$F42+4.5) | AU42: =IF(OR($E42="",$F42=""),"",IF($F42/$E42^(1/3)>=40.75,0.732*($F42/$E42^(1/3))-28.58,IF($F42/$E42^(1/3)>=38.25,0.463*($F42/$E42^(1/3))-17.63,0.1))) | AV42: =IF(OR($AS42="",$AT42="",$AU42=""),"",IF(AND($AT42>=$AS42,$AT42>=$AU42),"Mesomorfo dominante",IF(AND($AU42>=$AS42,$AU42>=$AT42),"Ectomorfo dominante","Endomorfo dominante")))
AG43: =IFERROR(DATEDIF(INDEX(Cadastro!$D$8:$D$47,MATCH($B43,Cadastro!$B$8:$B$47,0)),$A43,"Y"),"") | AH43: =IF(COUNT($I43,$K43,$J43,$N43)<4,"",$I43+$K43+$J43+$N43) | AI43: =IF(COUNT($L43,$M43,$I43,$J43,$P43,$N43,$Q43)<7,"",$L43+$M43+$I43+$J43+$P43+$N43+$Q43) | AJ43: =IF(COUNT($I43,$J43,$K43,$O43,$P43,$Q43,$R43,$N43)<8,"",$I43+$J43+$K43+$O43+$P43+$Q43+$R43+$N43) | AK43: =IF(OR($AI43="",$AG43=""),"",IF(IFERROR(INDEX(Cadastro!$F$8:$F$47,MATCH($B43,Cadastro!$B$8:$B$47,0)),"")="Feminino",1.097-0.00046971*$AI43+0.00000056*$AI43^2-0.00012828*$AG43,1.112-0.00043499*$AI43+0.00000055*$AI43^2-0.00028826*$AG43)) | AL43: =IF(OR($AK43="",$AK43=0),"",495/$AK43-450) | AM43: =IF(OR($AL43="",$E43=""),"",$E43*$AL43/100) | AN43: =IF(OR($AM43="",$E43=""),"",$E43-$AM43) | AO43: =IFERROR($E43/($F43/100)^2,"") | AP43: =IFERROR($G43/$F43*100,"") | AQ43: =IFERROR($W43/$F43,"") | AR43: =IF(OR($S43="",$I43=""),"",($S43-PI()*$I43/10)^2/(4*PI())-IF(IFERROR(INDEX(Cadastro!$F$8:$F$47,MATCH($B43,Cadastro!$B$8:$B$47,0)),"")="Feminino",6.5,10)) | AS43: =IF(OR($I43="",$J43="",$O43="",$F43=""),"",-0.7182+0.1451*(($I43+$J43+$O43)*(170.18/$F43))-0.00068*(($I43+$J43+$O43)*(170.18/$F43))^2+0.0000014*(($I43+$J43+$O43)*(170.18/$F43))^3) | AT43: =IF(OR($AE43="",$AF43="",$T43="",$AA43="",$F43=""),"",0.858*$AE43+0.601*$AF43+0.188*($T43-$I43/10)+0.161*($AA43-$R43/10)-0.131*$F43+4.5) | AU43: =IF(OR($E43="",$F43=""),"",IF($F43/$E43^(1/3)>=40.75,0.732*($F43/$E43^(1/3))-28.58,IF($F43/$E43^(1/3)>=38.25,0.463*($F43/$E43^(1/3))-17.63,0.1))) | AV43: =IF(OR($AS43="",$AT43="",$AU43=""),"",IF(AND($AT43>=$AS43,$AT43>=$AU43),"Mesomorfo dominante",IF(AND($AU43>=$AS43,$AU43>=$AT43),"Ectomorfo dominante","Endomorfo dominante")))
... AG407: =IFERROR(DATEDIF(INDEX(Cadastro!$D$8:$D$47,MATCH($B407,Cadastro!$B$8:$B$47,0)),$A407,"Y"),"") | AH407: =IF(COUNT($I407,$K407,$J407,$N407)<4,"",$I407+$K407+$J407+$N407) | AI407: =IF(COUNT($L407,$M407,$I407,$J407,$P407,$N407,$Q407)<7,"",$L407+$M407+$I407+$J407+$P407+$N407+$Q407) | AJ407: =IF(COUNT($I407,$J407,$K407,$O407,$P407,$Q407,$R407,$N407)<8,"",$I407+$J407+$K407+$O407+$P407+$Q407+$R407+$N407) | AK407: =IF(OR($AI407="",$AG407=""),"",IF(IFERROR(INDEX(Cadastro!$F$8:$F$47,MATCH($B407,Cadastro!$B$8:$B$47,0)),"")="Feminino",1.097-0.00046971*$AI407+0.00000056*$AI407^2-0.00012828*$AG407,1.112-0.00043499*$AI407+0.00000055*$AI407^2-0.00028826*$AG407)) | AL407: =IF(OR($AK407="",$AK407=0),"",495/$AK407-450) | AM407: =IF(OR($AL407="",$E407=""),"",$E407*$AL407/100) | AN407: =IF(OR($AM407="",$E407=""),"",$E407-$AM407) | AO407: =IFERROR($E407/($F407/100)^2,"") | AP407: =IFERROR($G407/$F407*100,"") | AQ407: =IFERROR($W407/$F407,"") | AR407: =IF(OR($S407="",$I407=""),"",($S407-PI()*$I407/10)^2/(4*PI())-IF(IFERROR(INDEX(Cadastro!$F$8:$F$47,MATCH($B407,Cadastro!$B$8:$B$47,0)),"")="Feminino",6.5,10)) | AS407: =IF(OR($I407="",$J407="",$O407="",$F407=""),"",-0.7182+0.1451*(($I407+$J407+$O407)*(170.18/$F407))-0.00068*(($I407+$J407+$O407)*(170.18/$F407))^2+0.0000014*(($I407+$J407+$O407)*(170.18/$F407))^3) | AT407: =IF(OR($AE407="",$AF407="",$T407="",$AA407="",$F407=""),"",0.858*$AE407+0.601*$AF407+0.188*($T407-$I407/10)+0.161*($AA407-$R407/10)-0.131*$F407+4.5) | AU407: =IF(OR($E407="",$F407=""),"",IF($F407/$E407^(1/3)>=40.75,0.732*($F407/$E407^(1/3))-28.58,IF($F407/$E407^(1/3)>=38.25,0.463*($F407/$E407^(1/3))-17.63,0.1))) | AV407: =IF(OR($AS407="",$AT407="",$AU407=""),"",IF(AND($AT407>=$AS407,$AT407>=$AU407),"Mesomorfo dominante",IF(AND($AU407>=$AS407,$AU407>=$AT407),"Ectomorfo dominante","Endomorfo dominante")))

Sheet Testes
A1: AVALIAÇÕES E TESTES FÍSICOS
A2: Bateria longitudinal. Impulsões, RSI, índice elástico e potência de pico são calculados automaticamente. Registre a melhor de 3 tentativas nos testes de salto, sprint e arremesso.
A4: RSI (Reactive Strength Index) = altura do drop jump (m) ÷ tempo de contato (s). • Índice Elástico = (CMJ − Squat Jump) ÷ Squat Jump — quanto o atleta aproveita do ciclo alongamento-encurtamento. • Potência de Pico pela equação de Sayers et al. (1999): P = 60,7 × CMJ(cm) + 45,3 × massa(kg) − 2055.
A6: IDENTIFICAÇÃO | F6: ALCANCES E IMPULSÕES (específico do voleibol) | K6: SALTOS E POTÊNCIA | T6: VELOCIDADE, AGILIDADE E OUTROS | AA6: FORÇA ISOMÉTRICA
A7: Data | B7: Atleta | C7: Momento | D7: Avaliador | E7: Massa (kg) | F7: Alcance em Pé (cm) | G7: Alcance de Ataque (cm) | H7: Alcance de Bloqueio (cm) | I7: Impulsão de Ataque (cm) | J7: Impulsão de Bloqueio (cm) | K7: Squat Jump (cm) | L7: CMJ (cm) | M7: CMJ c/ Braços (cm) | N7: Drop Jump 40 cm (cm) | O7: Tempo de Contato DJ (s) | P7: RSI (m/s) | Q7: Índice Elástico (%) | R7: Salto c/ Aproximação (cm) | S7: Potência de Pico — Sayers (W) | T7: Sprint 5 m (s) | U7: Sprint 10 m (s) | V7: T-Test (s) | W7: Sheppard Agility (s) | X7: Arremesso Medicine Ball (m) | Y7: Sentar-e-Alcançar (cm) | Z7: Yo-Yo IR1 (m) | AA7: IMTP Pico de Força (N) | AB7: Força Relativa IMTP (N/kg) | AC7: Observações
A8: 46036 | B8: Rafael Monteiro Alves | C8: Pré-temporada | D8: Preparação física | E8: 88 | F8: 253 | G8: 330 | H8: 309 | I8: =IF(OR($G8="",$F8=""),"",$G8-$F8) -> 77 | J8: =IF(OR($H8="",$F8=""),"",$H8-$F8) -> 56 | K8: 44.3 | L8: 49.1 | M8: 57 | N8: 47.5 | O8: 0.239 | P8: =IF(OR($N8="",$O8="",$O8=0),"",($N8/100)/$O8) -> 1.9874477 | Q8: =IF(OR($K8="",$L8="",$K8=0),"",($L8-$K8)/$K8) -> 0.10835214 | R8: 67.7 | S8: =IF(OR($L8="",$E8=""),"",60.7*$L8+45.3*$E8-2055) -> 4911.77 | T8: 1.1 | U8: 1.79 | V8: 9.69 | W8: 5.96 | X8: 15.4 | Y8: 24.1 | Z8: 1590 | AA8: 4086 | AB8: =IF(OR($AA8="",$E8="",$E8=0),"",$AA8/$E8) -> 46.431818 | AC8: EXEMPLO
A9: 46036 | B9: Diego Salgado Ferraz | C9: Pré-temporada | D9: Preparação física | E9: 95 | F9: 261 | G9: 339 | H9: 331 | I9: =IF(OR($G9="",$F9=""),"",$G9-$F9) -> 78 | J9: =IF(OR($H9="",$F9=""),"",$H9-$F9) -> 70 | K9: 51.9 | L9: 55.3 | M9: 62.8 | N9: 53 | O9: 0.215 | P9: =IF(OR($N9="",$O9="",$O9=0),"",($N9/100)/$O9) -> 2.4651163 | Q9: =IF(OR($K9="",$L9="",$K9=0),"",($L9-$K9)/$K9) -> 0.065510597 | R9: 71.3 | S9: =IF(OR($L9="",$E9=""),"",60.7*$L9+45.3*$E9-2055) -> 5605.21 | T9: 1.09 | U9: 1.89 | V9: 9.32 | W9: 5.93 | X9: 15.7 | Y9: 24.5 | Z9: 1229 | AA9: 3937 | AB9: =IF(OR($AA9="",$E9="",$E9=0),"",$AA9/$E9) -> 41.442105 | AC9: EXEMPLO
A10: 46036 | B10: Lucas Prado Bittencourt | C10: Pré-temporada | D10: Preparação física | E10: 89 | F10: 255 | G10: 335 | H10: 319 | I10: =IF(OR($G10="",$F10=""),"",$G10-$F10) -> 80 | J10: =IF(OR($H10="",$F10=""),"",$H10-$F10) -> 64 | K10: 46 | L10: 50 | M10: 56.3 | N10: 47.3 | O10: 0.212 | P10: =IF(OR($N10="",$O10="",$O10=0),"",($N10/100)/$O10) -> 2.2311321 | Q10: =IF(OR($K10="",$L10="",$K10=0),"",($L10-$K10)/$K10) -> 0.086956522 | R10: 67.8 | S10: =IF(OR($L10="",$E10=""),"",60.7*$L10+45.3*$E10-2055) -> 5011.7 | T10: 1.07 | U10: 1.76 | V10: 10.13 | W10: 5.54 | X10: 14.5 | Y10: 32.9 | Z10: 1919 | AA10: 3957 | AB10: =IF(OR($AA10="",$E10="",$E10=0),"",$AA10/$E10) -> 44.460674 | AC10: EXEMPLO
A11: 46036 | B11: Bruno Rezende Camargo | C11: Pré-temporada | D11: Preparação física | E11: 87 | F11: 254 | G11: 323 | H11: 315 | I11: =IF(OR($G11="",$F11=""),"",$G11-$F11) -> 69 | J11: =IF(OR($H11="",$F11=""),"",$H11-$F11) -> 61 | K11: 42.6 | L11: 46.4 | M11: 52.7 | N11: 44.7 | O11: 0.226 | P11: =IF(OR($N11="",$O11="",$O11=0),"",($N11/100)/$O11) -> 1.9778761 | Q11: =IF(OR($K11="",$L11="",$K11=0),"",($L11-$K11)/$K11) -> 0.089201878 | R11: 64.3 | S11: =IF(OR($L11="",$E11=""),"",60.7*$L11+45.3*$E11-2055) -> 4702.58 | T11: 1.08 | U11: 1.88 | V11: 9.21 | W11: 5.64 | X11: 13.2 | Y11: 23 | Z11: 1498 | AA11: 4069 | AB11: =IF(OR($AA11="",$E11="",$E11=0),"",$AA11/$E11) -> 46.770115 | AC11: EXEMPLO
A12: 46036 | B12: Thiago Nogueira Vasques | C12: Pré-temporada | D12: Preparação física | E12: 99 | F12: 264 | G12: 333 | H12: 324 | I12: =IF(OR($G12="",$F12=""),"",$G12-$F12) -> 69 | J12: =IF(OR($H12="",$F12=""),"",$H12-$F12) -> 60 | K12: 46.7 | L12: 50.3 | M12: 58.1 | N12: 47.5 | O12: 0.225 | P12: =IF(OR($N12="",$O12="",$O12=0),"",($N12/100)/$O12) -> 2.1111111 | Q12: =IF(OR($K12="",$L12="",$K12=0),"",($L12-$K12)/$K12) -> 0.077087794 | R12: 70.3 | S12: =IF(OR($L12="",$E12=""),"",60.7*$L12+45.3*$E12-2055) -> 5482.91 | T12: 1.15 | U12: 1.77 | V12: 9.34 | W12: 6.03 | X12: 15.1 | Y12: 23.5 | Z12: 1376 | AA12: 3417 | AB12: =IF(OR($AA12="",$E12="",$E12=0),"",$AA12/$E12) -> 34.515152 | AC12: EXEMPLO
A13: 46036 | B13: Matheus Caldeira Lins | C13: Pré-temporada | D13: Preparação física | E13: 95 | F13: 262 | G13: 334 | H13: 320 | I13: =IF(OR($G13="",$F13=""),"",$G13-$F13) -> 72 | J13: =IF(OR($H13="",$F13=""),"",$H13-$F13) -> 58 | K13: 42.8 | L13: 46.5 | M13: 54 | N13: 43.8 | O13: 0.24 | P13: =IF(OR($N13="",$O13="",$O13=0),"",($N13/100)/$O13) -> 1.825 | Q13: =IF(OR($K13="",$L13="",$K13=0),"",($L13-$K13)/$K13) -> 0.086448598 | R13: 63.7 | S13: =IF(OR($L13="",$E13=""),"",60.7*$L13+45.3*$E13-2055) -> 5071.05 | T13: 1.15 | U13: 1.72 | V13: 9.26 | W13: 5.94 | X13: 14.9 | Y13: 32.6 | Z13: 1323 | AA13: 3949 | AB13: =IF(OR($AA13="",$E13="",$E13=0),"",$AA13/$E13) -> 41.568421 | AC13: EXEMPLO
A14: 46036 | B14: Felipe Andrade Rocha | C14: Pré-temporada | D14: Preparação física | E14: 78 | F14: 237 | G14: 318 | H14: 292 | I14: =IF(OR($G14="",$F14=""),"",$G14-$F14) -> 81 | J14: =IF(OR($H14="",$F14=""),"",$H14-$F14) -> 55 | K14: 48.6 | L14: 53.1 | M14: 60.6 | N14: 51.7 | O14: 0.243 | P14: =IF(OR($N14="",$O14="",$O14=0),"",($N14/100)/$O14) -> 2.127572 | Q14: =IF(OR($K14="",$L14="",$K14=0),"",($L14-$K14)/$K14) -> 0.092592593 | R14: 69 | S14: =IF(OR($L14="",$E14=""),"",60.7*$L14+45.3*$E14-2055) -> 4701.57 | T14: 1.12 | U14: 1.78 | V14: 9.76 | W14: 6.12 | X14: 14.4 | Y14: 23.6 | Z14: 1253 | AA14: 2805 | AB14: =IF(OR($AA14="",$E14="",$E14=0),"",$AA14/$E14) -> 35.961538 | AC14: EXEMPLO
A15: 46036 | B15: Gustavo Peixoto Maia | C15: Pré-temporada | D15: Preparação física | E15: 91 | F15: 257 | G15: 335 | H15: 321 | I15: =IF(OR($G15="",$F15=""),"",$G15-$F15) -> 78 | J15: =IF(OR($H15="",$F15=""),"",$H15-$F15) -> 64 | K15: 47.9 | L15: 51 | M15: 57.2 | N15: 48.4 | O15: 0.235 | P15: =IF(OR($N15="",$O15="",$O15=0),"",($N15/100)/$O15) -> 2.0595745 | Q15: =IF(OR($K15="",$L15="",$K15=0),"",($L15-$K15)/$K15) -> 0.064718163 | R15: 67.5 | S15: =IF(OR($L15="",$E15=""),"",60.7*$L15+45.3*$E15-2055) -> 5163 | T15: 1.17 | U15: 1.87 | V15: 9.6 | W15: 5.9 | X15: 12.8 | Y15: 27.9 | Z15: 1365 | AA15: 3051 | AB15: =IF(OR($AA15="",$E15="",$E15=0),"",$AA15/$E15) -> 33.527473 | AC15: EXEMPLO
A16: 46036 | B16: Vinícius Barreto Duarte | C16: Pré-temporada | D16: Preparação física | E16: 84 | F16: 248 | G16: 326 | H16: 309 | I16: =IF(OR($G16="",$F16=""),"",$G16-$F16) -> 78 | J16: =IF(OR($H16="",$F16=""),"",$H16-$F16) -> 61 | K16: 44.6 | L16: 48.2 | M16: 54.2 | N16: 46.8 | O16: 0.209 | P16: =IF(OR($N16="",$O16="",$O16=0),"",($N16/100)/$O16) -> 2.2392344 | Q16: =IF(OR($K16="",$L16="",$K16=0),"",($L16-$K16)/$K16) -> 0.080717489 | R16: 66.5 | S16: =IF(OR($L16="",$E16=""),"",60.7*$L16+45.3*$E16-2055) -> 4675.94 | T16: 1.12 | U16: 1.88 | V16: 9.31 | W16: 5.85 | X16: 15.2 | Y16: 31.5 | Z16: 1634 | AA16: 3505 | AB16: =IF(OR($AA16="",$E16="",$E16=0),"",$AA16/$E16) -> 41.72619 | AC16: EXEMPLO
A17: 46036 | B17: André Luiz Sampaio | C17: Pré-temporada | D17: Preparação física | E17: 97 | F17: 259 | G17: 332 | H17: 315 | I17: =IF(OR($G17="",$F17=""),"",$G17-$F17) -> 73 | J17: =IF(OR($H17="",$F17=""),"",$H17-$F17) -> 56 | K17: 54 | L17: 57 | M17: 64.9 | N17: 55.8 | O17: 0.221 | P17: =IF(OR($N17="",$O17="",$O17=0),"",($N17/100)/$O17) -> 2.5248869 | Q17: =IF(OR($K17="",$L17="",$K17=0),"",($L17-$K17)/$K17) -> 0.055555556 | R17: 72.5 | S17: =IF(OR($L17="",$E17=""),"",60.7*$L17+45.3*$E17-2055) -> 5799 | T17: 1.13 | U17: 1.86 | V17: 9.3 | W17: 5.77 | X17: 14.5 | Y17: 26 | Z17: 1542 | AA17: 3345 | AB17: =IF(OR($AA17="",$E17="",$E17=0),"",$AA17/$E17) -> 34.484536 | AC17: EXEMPLO
A18: 46036 | B18: Pedro Henrique Coutinho | C18: Pré-temporada | D18: Preparação física | E18: 93 | F18: 263 | G18: 333 | H18: 327 | I18: =IF(OR($G18="",$F18=""),"",$G18-$F18) -> 70 | J18: =IF(OR($H18="",$F18=""),"",$H18-$F18) -> 64 | K18: 43.9 | L18: 48.3 | M18: 57.2 | N18: 46.3 | O18: 0.243 | P18: =IF(OR($N18="",$O18="",$O18=0),"",($N18/100)/$O18) -> 1.9053498 | Q18: =IF(OR($K18="",$L18="",$K18=0),"",($L18-$K18)/$K18) -> 0.10022779 | R18: 64.8 | S18: =IF(OR($L18="",$E18=""),"",60.7*$L18+45.3*$E18-2055) -> 5089.71 | T18: 1.17 | U18: 1.79 | V18: 9.37 | W18: 5.9 | X18: 15.1 | Y18: 31.8 | Z18: 1485 | AA18: 3305 | AB18: =IF(OR($AA18="",$E18="",$E18=0),"",$AA18/$E18) -> 35.537634 | AC18: EXEMPLO
A19: 46036 | B19: Caio Fernandes Bastos | C19: Pré-temporada | D19: Preparação física | E19: 79 | F19: 240 | G19: 310 | H19: 306 | I19: =IF(OR($G19="",$F19=""),"",$G19-$F19) -> 70 | J19: =IF(OR($H19="",$F19=""),"",$H19-$F19) -> 66 | K19: 46.9 | L19: 51.9 | M19: 57.9 | N19: 49.7 | O19: 0.223 | P19: =IF(OR($N19="",$O19="",$O19=0),"",($N19/100)/$O19) -> 2.2286996 | Q19: =IF(OR($K19="",$L19="",$K19=0),"",($L19-$K19)/$K19) -> 0.10660981 | R19: 68.7 | S19: =IF(OR($L19="",$E19=""),"",60.7*$L19+45.3*$E19-2055) -> 4674.03 | T19: 1.14 | U19: 1.87 | V19: 9.91 | W19: 6.08 | X19: 13.1 | Y19: 29.5 | Z19: 1937 | AA19: 3678 | AB19: =IF(OR($AA19="",$E19="",$E19=0),"",$AA19/$E19) -> 46.556962 | AC19: EXEMPLO
... A31: 46227 | B31: Caio Fernandes Bastos | C31: Meio da Temporada | D31: Preparação física | E31: 78.4 | F31: 240 | G31: 318 | H31: 310 | I31: =IF(OR($G31="",$F31=""),"",$G31-$F31) -> 78 | J31: =IF(OR($H31="",$F31=""),"",$H31-$F31) -> 70 | K31: 49.1 | L31: 53.3 | M31: 59.9 | N31: 52.1 | O31: 0.232 | P31: =IF(OR($N31="",$O31="",$O31=0),"",($N31/100)/$O31) -> 2.2456897 | Q31: =IF(OR($K31="",$L31="",$K31=0),"",($L31-$K31)/$K31) -> 0.085539715 | R31: 72.7 | S31: =IF(OR($L31="",$E31=""),"",60.7*$L31+45.3*$E31-2055) -> 4731.83 | T31: 1.07 | U31: 1.8 | V31: 9.95 | W31: 5.55 | X31: 14.3 | Y31: 23.9 | Z31: 1764 | AA31: 3538 | AB31: =IF(OR($AA31="",$E31="",$E31=0),"",$AA31/$E31) -> 45.127551 | AC31: EXEMPLO
I32: =IF(OR($G32="",$F32=""),"",$G32-$F32) | J32: =IF(OR($H32="",$F32=""),"",$H32-$F32) | P32: =IF(OR($N32="",$O32="",$O32=0),"",($N32/100)/$O32) | Q32: =IF(OR($K32="",$L32="",$K32=0),"",($L32-$K32)/$K32) | S32: =IF(OR($L32="",$E32=""),"",60.7*$L32+45.3*$E32-2055) | AB32: =IF(OR($AA32="",$E32="",$E32=0),"",$AA32/$E32)
I33: =IF(OR($G33="",$F33=""),"",$G33-$F33) | J33: =IF(OR($H33="",$F33=""),"",$H33-$F33) | P33: =IF(OR($N33="",$O33="",$O33=0),"",($N33/100)/$O33) | Q33: =IF(OR($K33="",$L33="",$K33=0),"",($L33-$K33)/$K33) | S33: =IF(OR($L33="",$E33=""),"",60.7*$L33+45.3*$E33-2055) | AB33: =IF(OR($AA33="",$E33="",$E33=0),"",$AA33/$E33)
I34: =IF(OR($G34="",$F34=""),"",$G34-$F34) | J34: =IF(OR($H34="",$F34=""),"",$H34-$F34) | P34: =IF(OR($N34="",$O34="",$O34=0),"",($N34/100)/$O34) | Q34: =IF(OR($K34="",$L34="",$K34=0),"",($L34-$K34)/$K34) | S34: =IF(OR($L34="",$E34=""),"",60.7*$L34+45.3*$E34-2055) | AB34: =IF(OR($AA34="",$E34="",$E34=0),"",$AA34/$E34)
I35: =IF(OR($G35="",$F35=""),"",$G35-$F35) | J35: =IF(OR($H35="",$F35=""),"",$H35-$F35) | P35: =IF(OR($N35="",$O35="",$O35=0),"",($N35/100)/$O35) | Q35: =IF(OR($K35="",$L35="",$K35=0),"",($L35-$K35)/$K35) | S35: =IF(OR($L35="",$E35=""),"",60.7*$L35+45.3*$E35-2055) | AB35: =IF(OR($AA35="",$E35="",$E35=0),"",$AA35/$E35)
I36: =IF(OR($G36="",$F36=""),"",$G36-$F36) | J36: =IF(OR($H36="",$F36=""),"",$H36-$F36) | P36: =IF(OR($N36="",$O36="",$O36=0),"",($N36/100)/$O36) | Q36: =IF(OR($K36="",$L36="",$K36=0),"",($L36-$K36)/$K36) | S36: =IF(OR($L36="",$E36=""),"",60.7*$L36+45.3*$E36-2055) | AB36: =IF(OR($AA36="",$E36="",$E36=0),"",$AA36/$E36)
I37: =IF(OR($G37="",$F37=""),"",$G37-$F37) | J37: =IF(OR($H37="",$F37=""),"",$H37-$F37) | P37: =IF(OR($N37="",$O37="",$O37=0),"",($N37/100)/$O37) | Q37: =IF(OR($K37="",$L37="",$K37=0),"",($L37-$K37)/$K37) | S37: =IF(OR($L37="",$E37=""),"",60.7*$L37+45.3*$E37-2055) | AB37: =IF(OR($AA37="",$E37="",$E37=0),"",$AA37/$E37)
I38: =IF(OR($G38="",$F38=""),"",$G38-$F38) | J38: =IF(OR($H38="",$F38=""),"",$H38-$F38) | P38: =IF(OR($N38="",$O38="",$O38=0),"",($N38/100)/$O38) | Q38: =IF(OR($K38="",$L38="",$K38=0),"",($L38-$K38)/$K38) | S38: =IF(OR($L38="",$E38=""),"",60.7*$L38+45.3*$E38-2055) | AB38: =IF(OR($AA38="",$E38="",$E38=0),"",$AA38/$E38)
I39: =IF(OR($G39="",$F39=""),"",$G39-$F39) | J39: =IF(OR($H39="",$F39=""),"",$H39-$F39) | P39: =IF(OR($N39="",$O39="",$O39=0),"",($N39/100)/$O39) | Q39: =IF(OR($K39="",$L39="",$K39=0),"",($L39-$K39)/$K39) | S39: =IF(OR($L39="",$E39=""),"",60.7*$L39+45.3*$E39-2055) | AB39: =IF(OR($AA39="",$E39="",$E39=0),"",$AA39/$E39)
I40: =IF(OR($G40="",$F40=""),"",$G40-$F40) | J40: =IF(OR($H40="",$F40=""),"",$H40-$F40) | P40: =IF(OR($N40="",$O40="",$O40=0),"",($N40/100)/$O40) | Q40: =IF(OR($K40="",$L40="",$K40=0),"",($L40-$K40)/$K40) | S40: =IF(OR($L40="",$E40=""),"",60.7*$L40+45.3*$E40-2055) | AB40: =IF(OR($AA40="",$E40="",$E40=0),"",$AA40/$E40)
I41: =IF(OR($G41="",$F41=""),"",$G41-$F41) | J41: =IF(OR($H41="",$F41=""),"",$H41-$F41) | P41: =IF(OR($N41="",$O41="",$O41=0),"",($N41/100)/$O41) | Q41: =IF(OR($K41="",$L41="",$K41=0),"",($L41-$K41)/$K41) | S41: =IF(OR($L41="",$E41=""),"",60.7*$L41+45.3*$E41-2055) | AB41: =IF(OR($AA41="",$E41="",$E41=0),"",$AA41/$E41)
I42: =IF(OR($G42="",$F42=""),"",$G42-$F42) | J42: =IF(OR($H42="",$F42=""),"",$H42-$F42) | P42: =IF(OR($N42="",$O42="",$O42=0),"",($N42/100)/$O42) | Q42: =IF(OR($K42="",$L42="",$K42=0),"",($L42-$K42)/$K42) | S42: =IF(OR($L42="",$E42=""),"",60.7*$L42+45.3*$E42-2055) | AB42: =IF(OR($AA42="",$E42="",$E42=0),"",$AA42/$E42)
I43: =IF(OR($G43="",$F43=""),"",$G43-$F43) | J43: =IF(OR($H43="",$F43=""),"",$H43-$F43) | P43: =IF(OR($N43="",$O43="",$O43=0),"",($N43/100)/$O43) | Q43: =IF(OR($K43="",$L43="",$K43=0),"",($L43-$K43)/$K43) | S43: =IF(OR($L43="",$E43=""),"",60.7*$L43+45.3*$E43-2055) | AB43: =IF(OR($AA43="",$E43="",$E43=0),"",$AA43/$E43)
... I407: =IF(OR($G407="",$F407=""),"",$G407-$F407) | J407: =IF(OR($H407="",$F407=""),"",$H407-$F407) | P407: =IF(OR($N407="",$O407="",$O407=0),"",($N407/100)/$O407) | Q407: =IF(OR($K407="",$L407="",$K407=0),"",($L407-$K407)/$K407) | S407: =IF(OR($L407="",$E407=""),"",60.7*$L407+45.3*$E407-2055) | AB407: =IF(OR($AA407="",$E407="",$E407=0),"",$AA407/$E407)

Sheet Perfil F-V-P
A1: PERFIL FORÇA–VELOCIDADE–POTÊNCIA (SALTO COM CARGA)
A2: Protocolo: squat jump com 0, 20, 40, 60 e 80 kg (ou % da massa corporal). A planilha calcula F0, V0, Pmax e a inclinação do perfil por regressão linear, pelo método de Samozino/Morin.
A3: PARÂMETROS DO TESTE
A4: Atleta: | C4: Rafael Monteiro Alves
A5: Massa corporal (kg): | C5: =IFERROR(INDEX(Cadastro!$P$8:$P$47,MATCH($C$4,Cadastro!$B$8:$B$47,0)),"") -> 87.8
A6: Distância de push-off hPO (m): | C6: 0.4
A7: SFvopt (N·s/m/kg):
A10: SALTOS COM CARGA PROGRESSIVA
A11: Carga Adicional (kg) | B11: Altura do Salto (cm) | C11: Massa Total (kg) | D11: Força Média (N) | E11: Força Relativa (N/kg) | F11: Velocidade Média (m/s) | G11: Potência Média (W) | H11: Potência Relativa (W/kg)
A12: 0 | B12: 48 | C12: =IFERROR($C$5+$A12,"") -> 87.8 | D12: =IFERROR($C12*9.81*(($B12/100)/$C$6+1),"") -> 1894.8996 | E12: =IFERROR($D12/$C$5,"") -> 21.582 | F12: =IFERROR(SQRT(9.81*($B12/100)/2),"") -> 1.5344054 | G12: =IFERROR($D12*$F12,"") -> 2907.5442 | H12: =IFERROR($G12/$C$5,"") -> 33.115538
A13: 20 | B13: 39 | C13: =IFERROR($C$5+$A13,"") -> 107.8 | D13: =IFERROR($C13*9.81*(($B13/100)/$C$6+1),"") -> 2088.5981 | E13: =IFERROR($D13/$C$5,"") -> 23.788133 | F13: =IFERROR(SQRT(9.81*($B13/100)/2),"") -> 1.3830944 | G13: =IFERROR($D13*$F13,"") -> 2888.7282 | H13: =IFERROR($G13/$C$5,"") -> 32.901232
A14: 40 | B14: 32 | C14: =IFERROR($C$5+$A14,"") -> 127.8 | D14: =IFERROR($C14*9.81*(($B14/100)/$C$6+1),"") -> 2256.6924 | E14: =IFERROR($D14/$C$5,"") -> 25.702647 | F14: =IFERROR(SQRT(9.81*($B14/100)/2),"") -> 1.2528368 | G14: =IFERROR($D14*$F14,"") -> 2827.2672 | H14: =IFERROR($G14/$C$5,"") -> 32.201221
A15: 60 | B15: 26 | C15: =IFERROR($C$5+$A15,"") -> 147.8 | D15: =IFERROR($C15*9.81*(($B15/100)/$C$6+1),"") -> 2392.3647 | E15: =IFERROR($D15/$C$5,"") -> 27.24789 | F15: =IFERROR(SQRT(9.81*($B15/100)/2),"") -> 1.1292918 | G15: =IFERROR($D15*$F15,"") -> 2701.6779 | H15: =IFERROR($G15/$C$5,"") -> 30.770819
A16: 80 | B16: 21 | C16: =IFERROR($C$5+$A16,"") -> 167.8 | D16: =IFERROR($C16*9.81*(($B16/100)/$C$6+1),"") -> 2510.3299 | E16: =IFERROR($D16/$C$5,"") -> 28.591457 | F16: =IFERROR(SQRT(9.81*($B16/100)/2),"") -> 1.0149138 | G16: =IFERROR($D16*$F16,"") -> 2547.7685 | H16: =IFERROR($G16/$C$5,"") -> 29.017864
A17: F0 e V0 são EXTRAPOLAÇÕES da reta força-velocidade: dependem muito da distância de push-off (C6) e da amplitude de cargas testada. Use pelo menos 5 cargas cobrindo uma faixa ampla e confira o R² (linha 27): abaixo de 0,95, refaça o teste.
A18: RESULTADOS DO PERFIL
A19: F0 — Força teórica máxima (N) | C19: =IFERROR(INTERCEPT($D$12:$D$16,$F$12:$F$16),"") -> 3731.4337
A20: F0 relativa (N/kg) | C20: =IFERROR($C$19/$C$5,"") -> 42.499245
A21: V0 — Velocidade teórica máxima (m/s) | C21: =IFERROR(-$C$19/$C$22,"") -> 3.1356675
A22: Sfv — Inclinação do perfil (N·s/m) | C22: =IFERROR(SLOPE($D$12:$D$16,$F$12:$F$16),"") -> -1189.9966
A23: Sfv relativa (N·s/m/kg) | C23: =IFERROR($C$22/$C$5,"") -> -13.553492
A24: Pmax — Potência máxima (W) | C24: =IFERROR($C$19*$C$21/4,"") -> 2925.1338
A25: Pmax relativa (W/kg) | C25: =IFERROR($C$24/$C$5,"") -> 33.315875
A26: FVimb — Desequilíbrio F-V (%) | C26: =IF($C$7="","",IFERROR(ABS($C$23)/ABS($C$7),""))
A27: R² da regressão | C27: =IFERROR(RSQ($D$12:$D$16,$F$12:$F$16),"") -> 0.99754932
A28: PERFIL: | C28: =IF($C$26="","Informe o SFvopt em C7 para classificar",IF($C$26<0.9,"Déficit de FORÇA",IF($C$26<=1.1,"Equilibrado","Déficit de VELOCIDADE"))) -> Informe o SFvopt em C7 para classificar
A29: =IF($C$26="","Sem o SFvopt não é possível estimar o desequilíbrio. Ainda assim, F0, V0 e Pmax servem para acompanhar a evolução do atleta ao longo dos blocos e para comparar atletas do mesmo elenco na tabela abaixo.",IF($C$26<0.9,"DÉFICIT DE FORÇA — priorize cargas altas: agachamento e stiff a 80–90% 1RM, LPO (power clean e clean pull) a 80–90%, 70 a 100% do volume de força na região pesada do perfil. Reduza o volume balístico.",IF($C$26<=1.1,"PERFIL EQUILIBRADO — mantenha a distribuição mista e busque elevar a Pmax como um todo: alterne blocos de força máxima (85–90% 1RM) e blocos balísticos (jump squat 30% 1RM + pliometria).","DÉFICIT DE VELOCIDADE — priorize o lado rápido do perfil: jump squat a 0–40% 1RM, saltos sem carga, pliometria reativa (drop jump) e LPO com ênfase em velocidade da barra. Mantenha a força máxima com volume mínimo."))) -> Sem o SFvopt não é possível estimar o desequilíbrio. Ainda assim, F0, V0 e Pmax servem para acompanhar a evolução do atleta ao longo dos blocos e para comparar atletas do mesmo elenco na tabela abaixo.
A34: PERFIL F-V DE TODO O ELENCO
A35: Atleta | B35: Massa (kg) | C35: F0 (N) | D35: V0 (m/s) | E35: F0 rel (N/kg) | F35: Pmax (W) | G35: Pmax rel (W/kg) | H35: Sfv rel (N·s/m/kg) | I35: SFvopt | J35: FVimb (%) | K35: Perfil | L35: Prioridade de Treino
A36: =IF(Cadastro!$B8="","",Cadastro!$B8) -> Rafael Monteiro Alves | B36: =IF($A36="","",IFERROR(Cadastro!$P8,"")) -> 87.8 | C36: 3224 | D36: 3.4 | E36: =IFERROR($C36/$B36,"") -> 36.719818 | F36: =IFERROR($C36*$D36/4,"") -> 2740.4 | G36: =IFERROR($F36/$B36,"") -> 31.211845 | H36: =IFERROR(-$E36/$D36,"") -> -10.799946 | I36: -11.48 | J36: =IF(OR($I36="",$H36=""),"",IFERROR(ABS($H36)/ABS($I36),"")) -> 0.94076188 | K36: =IF($J36="","",IF($J36<0.9,"Déficit de FORÇA",IF($J36<=1.1,"Equilibrado","Déficit de VELOCIDADE"))) -> Equilibrado | L36: =IF($K36="","",IF($K36="Déficit de FORÇA","Cargas altas: 80–90% 1RM + LPO pesado",IF($K36="Equilibrado","Misto: alternar força máxima e balístico","Balístico: 0–40% 1RM, jump squat e pliometria reativa"))) -> Misto: alternar força máxima e balístico
A37: =IF(Cadastro!$B9="","",Cadastro!$B9) -> Diego Salgado Ferraz | B37: =IF($A37="","",IFERROR(Cadastro!$P9,"")) -> 94.2 | C37: 2963 | D37: 3.65 | E37: =IFERROR($C37/$B37,"") -> 31.454352 | F37: =IFERROR($C37*$D37/4,"") -> 2703.7375 | G37: =IFERROR($F37/$B37,"") -> 28.702097 | H37: =IFERROR(-$E37/$D37,"") -> -8.6176308 | I37: -8.57 | J37: =IF(OR($I37="",$H37=""),"",IFERROR(ABS($H37)/ABS($I37),"")) -> 1.0055579 | K37: =IF($J37="","",IF($J37<0.9,"Déficit de FORÇA",IF($J37<=1.1,"Equilibrado","Déficit de VELOCIDADE"))) -> Equilibrado | L37: =IF($K37="","",IF($K37="Déficit de FORÇA","Cargas altas: 80–90% 1RM + LPO pesado",IF($K37="Equilibrado","Misto: alternar força máxima e balístico","Balístico: 0–40% 1RM, jump squat e pliometria reativa"))) -> Misto: alternar força máxima e balístico
A38: =IF(Cadastro!$B10="","",Cadastro!$B10) -> Lucas Prado Bittencourt | B38: =IF($A38="","",IFERROR(Cadastro!$P10,"")) -> 88.9 | C38: 2814 | D38: 3.54 | E38: =IFERROR($C38/$B38,"") -> 31.653543 | F38: =IFERROR($C38*$D38/4,"") -> 2490.39 | G38: =IFERROR($F38/$B38,"") -> 28.013386 | H38: =IFERROR(-$E38/$D38,"") -> -8.9416789 | I38: -10.15 | J38: =IF(OR($I38="",$H38=""),"",IFERROR(ABS($H38)/ABS($I38),"")) -> 0.88095359 | K38: =IF($J38="","",IF($J38<0.9,"Déficit de FORÇA",IF($J38<=1.1,"Equilibrado","Déficit de VELOCIDADE"))) -> Déficit de FORÇA | L38: =IF($K38="","",IF($K38="Déficit de FORÇA","Cargas altas: 80–90% 1RM + LPO pesado",IF($K38="Equilibrado","Misto: alternar força máxima e balístico","Balístico: 0–40% 1RM, jump squat e pliometria reativa"))) -> Cargas altas: 80–90% 1RM + LPO pesado
A39: =IF(Cadastro!$B11="","",Cadastro!$B11) -> Bruno Rezende Camargo | B39: =IF($A39="","",IFERROR(Cadastro!$P11,"")) -> 87.7 | C39: 3029 | D39: 4.07 | E39: =IFERROR($C39/$B39,"") -> 34.538198 | F39: =IFERROR($C39*$D39/4,"") -> 3082.0075 | G39: =IFERROR($F39/$B39,"") -> 35.142617 | H39: =IFERROR(-$E39/$D39,"") -> -8.4860438 | I39: -8.38 | J39: =IF(OR($I39="",$H39=""),"",IFERROR(ABS($H39)/ABS($I39),"")) -> 1.0126544 | K39: =IF($J39="","",IF($J39<0.9,"Déficit de FORÇA",IF($J39<=1.1,"Equilibrado","Déficit de VELOCIDADE"))) -> Equilibrado | L39: =IF($K39="","",IF($K39="Déficit de FORÇA","Cargas altas: 80–90% 1RM + LPO pesado",IF($K39="Equilibrado","Misto: alternar força máxima e balístico","Balístico: 0–40% 1RM, jump squat e pliometria reativa"))) -> Misto: alternar força máxima e balístico
A40: =IF(Cadastro!$B12="","",Cadastro!$B12) -> Thiago Nogueira Vasques | B40: =IF($A40="","",IFERROR(Cadastro!$P12,"")) -> 99.7 | C40: 3296 | D40: 3.63 | E40: =IFERROR($C40/$B40,"") -> 33.059178 | F40: =IFERROR($C40*$D40/4,"") -> 2991.12 | G40: =IFERROR($F40/$B40,"") -> 30.001204 | H40: =IFERROR(-$E40/$D40,"") -> -9.1072114 | I40: -10.43 | J40: =IF(OR($I40="",$H40=""),"",IFERROR(ABS($H40)/ABS($I40),"")) -> 0.87317463 | K40: =IF($J40="","",IF($J40<0.9,"Déficit de FORÇA",IF($J40<=1.1,"Equilibrado","Déficit de VELOCIDADE"))) -> Déficit de FORÇA | L40: =IF($K40="","",IF($K40="Déficit de FORÇA","Cargas altas: 80–90% 1RM + LPO pesado",IF($K40="Equilibrado","Misto: alternar força máxima e balístico","Balístico: 0–40% 1RM, jump squat e pliometria reativa"))) -> Cargas altas: 80–90% 1RM + LPO pesado
A41: =IF(Cadastro!$B13="","",Cadastro!$B13) -> Matheus Caldeira Lins | B41: =IF($A41="","",IFERROR(Cadastro!$P13,"")) -> 94.9 | C41: 2868 | D41: 3.52 | E41: =IFERROR($C41/$B41,"") -> 30.221286 | F41: =IFERROR($C41*$D41/4,"") -> 2523.84 | G41: =IFERROR($F41/$B41,"") -> 26.594731 | H41: =IFERROR(-$E41/$D41,"") -> -8.5855925 | I41: -9.71 | J41: =IF(OR($I41="",$H41=""),"",IFERROR(ABS($H41)/ABS($I41),"")) -> 0.88420108 | K41: =IF($J41="","",IF($J41<0.9,"Déficit de FORÇA",IF($J41<=1.1,"Equilibrado","Déficit de VELOCIDADE"))) -> Déficit de FORÇA | L41: =IF($K41="","",IF($K41="Déficit de FORÇA","Cargas altas: 80–90% 1RM + LPO pesado",IF($K41="Equilibrado","Misto: alternar força máxima e balístico","Balístico: 0–40% 1RM, jump squat e pliometria reativa"))) -> Cargas altas: 80–90% 1RM + LPO pesado
A42: =IF(Cadastro!$B14="","",Cadastro!$B14) -> Felipe Andrade Rocha | B42: =IF($A42="","",IFERROR(Cadastro!$P14,"")) -> 79 | C42: 2653 | D42: 4.01 | E42: =IFERROR($C42/$B42,"") -> 33.582278 | F42: =IFERROR($C42*$D42/4,"") -> 2659.6325 | G42: =IFERROR($F42/$B42,"") -> 33.666234 | H42: =IFERROR(-$E42/$D42,"") -> -8.374633 | I42: -8.81 | J42: =IF(OR($I42="",$H42=""),"",IFERROR(ABS($H42)/ABS($I42),"")) -> 0.95058264 | K42: =IF($J42="","",IF($J42<0.9,"Déficit de FORÇA",IF($J42<=1.1,"Equilibrado","Déficit de VELOCIDADE"))) -> Equilibrado | L42: =IF($K42="","",IF($K42="Déficit de FORÇA","Cargas altas: 80–90% 1RM + LPO pesado",IF($K42="Equilibrado","Misto: alternar força máxima e balístico","Balístico: 0–40% 1RM, jump squat e pliometria reativa"))) -> Misto: alternar força máxima e balístico
A43: =IF(Cadastro!$B15="","",Cadastro!$B15) -> Gustavo Peixoto Maia | B43: =IF($A43="","",IFERROR(Cadastro!$P15,"")) -> 90.4 | C43: 2779 | D43: 4.2 | E43: =IFERROR($C43/$B43,"") -> 30.74115 | F43: =IFERROR($C43*$D43/4,"") -> 2917.95 | G43: =IFERROR($F43/$B43,"") -> 32.278208 | H43: =IFERROR(-$E43/$D43,"") -> -7.3193215 | I43: -7.07 | J43: =IF(OR($I43="",$H43=""),"",IFERROR(ABS($H43)/ABS($I43),"")) -> 1.0352647 | K43: =IF($J43="","",IF($J43<0.9,"Déficit de FORÇA",IF($J43<=1.1,"Equilibrado","Déficit de VELOCIDADE"))) -> Equilibrado | L43: =IF($K43="","",IF($K43="Déficit de FORÇA","Cargas altas: 80–90% 1RM + LPO pesado",IF($K43="Equilibrado","Misto: alternar força máxima e balístico","Balístico: 0–40% 1RM, jump squat e pliometria reativa"))) -> Misto: alternar força máxima e balístico
A44: =IF(Cadastro!$B16="","",Cadastro!$B16) -> Vinícius Barreto Duarte | B44: =IF($A44="","",IFERROR(Cadastro!$P16,"")) -> 82.5 | C44: 2572 | D44: 3.37 | E44: =IFERROR($C44/$B44,"") -> 31.175758 | F44: =IFERROR($C44*$D44/4,"") -> 2166.91 | G44: =IFERROR($F44/$B44,"") -> 26.265576 | H44: =IFERROR(-$E44/$D44,"") -> -9.2509666 | I44: -7.47 | J44: =IF(OR($I44="",$H44=""),"",IFERROR(ABS($H44)/ABS($I44),"")) -> 1.2384159 | K44: =IF($J44="","",IF($J44<0.9,"Déficit de FORÇA",IF($J44<=1.1,"Equilibrado","Déficit de VELOCIDADE"))) -> Déficit de VELOCIDADE | L44: =IF($K44="","",IF($K44="Déficit de FORÇA","Cargas altas: 80–90% 1RM + LPO pesado",IF($K44="Equilibrado","Misto: alternar força máxima e balístico","Balístico: 0–40% 1RM, jump squat e pliometria reativa"))) -> Balístico: 0–40% 1RM, jump squat e pliometria reativa
A45: =IF(Cadastro!$B17="","",Cadastro!$B17) -> André Luiz Sampaio | B45: =IF($A45="","",IFERROR(Cadastro!$P17,"")) -> 97.5 | C45: 3380 | D45: 3.79 | E45: =IFERROR($C45/$B45,"") -> 34.666667 | F45: =IFERROR($C45*$D45/4,"") -> 3202.55 | G45: =IFERROR($F45/$B45,"") -> 32.846667 | H45: =IFERROR(-$E45/$D45,"") -> -9.1468777 | I45: -10.44 | J45: =IF(OR($I45="",$H45=""),"",IFERROR(ABS($H45)/ABS($I45),"")) -> 0.87613772 | K45: =IF($J45="","",IF($J45<0.9,"Déficit de FORÇA",IF($J45<=1.1,"Equilibrado","Déficit de VELOCIDADE"))) -> Déficit de FORÇA | L45: =IF($K45="","",IF($K45="Déficit de FORÇA","Cargas altas: 80–90% 1RM + LPO pesado",IF($K45="Equilibrado","Misto: alternar força máxima e balístico","Balístico: 0–40% 1RM, jump squat e pliometria reativa"))) -> Cargas altas: 80–90% 1RM + LPO pesado
A46: =IF(Cadastro!$B18="","",Cadastro!$B18) -> Pedro Henrique Coutinho | B46: =IF($A46="","",IFERROR(Cadastro!$P18,"")) -> 91.8 | C46: 3326 | D46: 3.43 | E46: =IFERROR($C46/$B46,"") -> 36.230937 | F46: =IFERROR($C46*$D46/4,"") -> 2852.045 | G46: =IFERROR($F46/$B46,"") -> 31.068028 | H46: =IFERROR(-$E46/$D46,"") -> -10.562955 | I46: -8.76 | J46: =IF(OR($I46="",$H46=""),"",IFERROR(ABS($H46)/ABS($I46),"")) -> 1.2058168 | K46: =IF($J46="","",IF($J46<0.9,"Déficit de FORÇA",IF($J46<=1.1,"Equilibrado","Déficit de VELOCIDADE"))) -> Déficit de VELOCIDADE | L46: =IF($K46="","",IF($K46="Déficit de FORÇA","Cargas altas: 80–90% 1RM + LPO pesado",IF($K46="Equilibrado","Misto: alternar força máxima e balístico","Balístico: 0–40% 1RM, jump squat e pliometria reativa"))) -> Balístico: 0–40% 1RM, jump squat e pliometria reativa
A47: =IF(Cadastro!$B19="","",Cadastro!$B19) -> Caio Fernandes Bastos | B47: =IF($A47="","",IFERROR(Cadastro!$P19,"")) -> 78.2 | C47: 2877 | D47: 3.15 | E47: =IFERROR($C47/$B47,"") -> 36.790281 | F47: =IFERROR($C47*$D47/4,"") -> 2265.6375 | G47: =IFERROR($F47/$B47,"") -> 28.972347 | H47: =IFERROR(-$E47/$D47,"") -> -11.679454 | I47: -9.68 | J47: =IF(OR($I47="",$H47=""),"",IFERROR(ABS($H47)/ABS($I47),"")) -> 1.2065552 | K47: =IF($J47="","",IF($J47<0.9,"Déficit de FORÇA",IF($J47<=1.1,"Equilibrado","Déficit de VELOCIDADE"))) -> Déficit de VELOCIDADE | L47: =IF($K47="","",IF($K47="Déficit de FORÇA","Cargas altas: 80–90% 1RM + LPO pesado",IF($K47="Equilibrado","Misto: alternar força máxima e balístico","Balístico: 0–40% 1RM, jump squat e pliometria reativa"))) -> Balístico: 0–40% 1RM, jump squat e pliometria reativa
A48: =IF(Cadastro!$B20="","",Cadastro!$B20) | B48: =IF($A48="","",IFERROR(Cadastro!$P20,"")) | E48: =IFERROR($C48/$B48,"") | F48: =IFERROR($C48*$D48/4,"") -> 0 | G48: =IFERROR($F48/$B48,"") | H48: =IFERROR(-$E48/$D48,"") | J48: =IF(OR($I48="",$H48=""),"",IFERROR(ABS($H48)/ABS($I48),"")) | K48: =IF($J48="","",IF($J48<0.9,"Déficit de FORÇA",IF($J48<=1.1,"Equilibrado","Déficit de VELOCIDADE"))) | L48: =IF($K48="","",IF($K48="Déficit de FORÇA","Cargas altas: 80–90% 1RM + LPO pesado",IF($K48="Equilibrado","Misto: alternar força máxima e balístico","Balístico: 0–40% 1RM, jump squat e pliometria reativa")))
A49: =IF(Cadastro!$B21="","",Cadastro!$B21) | B49: =IF($A49="","",IFERROR(Cadastro!$P21,"")) | E49: =IFERROR($C49/$B49,"") | F49: =IFERROR($C49*$D49/4,"") -> 0 | G49: =IFERROR($F49/$B49,"") | H49: =IFERROR(-$E49/$D49,"") | J49: =IF(OR($I49="",$H49=""),"",IFERROR(ABS($H49)/ABS($I49),"")) | K49: =IF($J49="","",IF($J49<0.9,"Déficit de FORÇA",IF($J49<=1.1,"Equilibrado","Déficit de VELOCIDADE"))) | L49: =IF($K49="","",IF($K49="Déficit de FORÇA","Cargas altas: 80–90% 1RM + LPO pesado",IF($K49="Equilibrado","Misto: alternar força máxima e balístico","Balístico: 0–40% 1RM, jump squat e pliometria reativa")))
A50: =IF(Cadastro!$B22="","",Cadastro!$B22) | B50: =IF($A50="","",IFERROR(Cadastro!$P22,"")) | E50: =IFERROR($C50/$B50,"") | F50: =IFERROR($C50*$D50/4,"") -> 0 | G50: =IFERROR($F50/$B50,"") | H50: =IFERROR(-$E50/$D50,"") | J50: =IF(OR($I50="",$H50=""),"",IFERROR(ABS($H50)/ABS($I50),"")) | K50: =IF($J50="","",IF($J50<0.9,"Déficit de FORÇA",IF($J50<=1.1,"Equilibrado","Déficit de VELOCIDADE"))) | L50: =IF($K50="","",IF($K50="Déficit de FORÇA","Cargas altas: 80–90% 1RM + LPO pesado",IF($K50="Equilibrado","Misto: alternar força máxima e balístico","Balístico: 0–40% 1RM, jump squat e pliometria reativa")))
A51: =IF(Cadastro!$B23="","",Cadastro!$B23) | B51: =IF($A51="","",IFERROR(Cadastro!$P23,"")) | E51: =IFERROR($C51/$B51,"") | F51: =IFERROR($C51*$D51/4,"") -> 0 | G51: =IFERROR($F51/$B51,"") | H51: =IFERROR(-$E51/$D51,"") | J51: =IF(OR($I51="",$H51=""),"",IFERROR(ABS($H51)/ABS($I51),"")) | K51: =IF($J51="","",IF($J51<0.9,"Déficit de FORÇA",IF($J51<=1.1,"Equilibrado","Déficit de VELOCIDADE"))) | L51: =IF($K51="","",IF($K51="Déficit de FORÇA","Cargas altas: 80–90% 1RM + LPO pesado",IF($K51="Equilibrado","Misto: alternar força máxima e balístico","Balístico: 0–40% 1RM, jump squat e pliometria reativa")))
A52: =IF(Cadastro!$B24="","",Cadastro!$B24) | B52: =IF($A52="","",IFERROR(Cadastro!$P24,"")) | E52: =IFERROR($C52/$B52,"") | F52: =IFERROR($C52*$D52/4,"") -> 0 | G52: =IFERROR($F52/$B52,"") | H52: =IFERROR(-$E52/$D52,"") | J52: =IF(OR($I52="",$H52=""),"",IFERROR(ABS($H52)/ABS($I52),"")) | K52: =IF($J52="","",IF($J52<0.9,"Déficit de FORÇA",IF($J52<=1.1,"Equilibrado","Déficit de VELOCIDADE"))) | L52: =IF($K52="","",IF($K52="Déficit de FORÇA","Cargas altas: 80–90% 1RM + LPO pesado",IF($K52="Equilibrado","Misto: alternar força máxima e balístico","Balístico: 0–40% 1RM, jump squat e pliometria reativa")))
A53: =IF(Cadastro!$B25="","",Cadastro!$B25) | B53: =IF($A53="","",IFERROR(Cadastro!$P25,"")) | E53: =IFERROR($C53/$B53,"") | F53: =IFERROR($C53*$D53/4,"") -> 0 | G53: =IFERROR($F53/$B53,"") | H53: =IFERROR(-$E53/$D53,"") | J53: =IF(OR($I53="",$H53=""),"",IFERROR(ABS($H53)/ABS($I53),"")) | K53: =IF($J53="","",IF($J53<0.9,"Déficit de FORÇA",IF($J53<=1.1,"Equilibrado","Déficit de VELOCIDADE"))) | L53: =IF($K53="","",IF($K53="Déficit de FORÇA","Cargas altas: 80–90% 1RM + LPO pesado",IF($K53="Equilibrado","Misto: alternar força máxima e balístico","Balístico: 0–40% 1RM, jump squat e pliometria reativa")))
A54: =IF(Cadastro!$B26="","",Cadastro!$B26) | B54: =IF($A54="","",IFERROR(Cadastro!$P26,"")) | E54: =IFERROR($C54/$B54,"") | F54: =IFERROR($C54*$D54/4,"") -> 0 | G54: =IFERROR($F54/$B54,"") | H54: =IFERROR(-$E54/$D54,"") | J54: =IF(OR($I54="",$H54=""),"",IFERROR(ABS($H54)/ABS($I54),"")) | K54: =IF($J54="","",IF($J54<0.9,"Déficit de FORÇA",IF($J54<=1.1,"Equilibrado","Déficit de VELOCIDADE"))) | L54: =IF($K54="","",IF($K54="Déficit de FORÇA","Cargas altas: 80–90% 1RM + LPO pesado",IF($K54="Equilibrado","Misto: alternar força máxima e balístico","Balístico: 0–40% 1RM, jump squat e pliometria reativa")))
A55: =IF(Cadastro!$B27="","",Cadastro!$B27) | B55: =IF($A55="","",IFERROR(Cadastro!$P27,"")) | E55: =IFERROR($C55/$B55,"") | F55: =IFERROR($C55*$D55/4,"") -> 0 | G55: =IFERROR($F55/$B55,"") | H55: =IFERROR(-$E55/$D55,"") | J55: =IF(OR($I55="",$H55=""),"",IFERROR(ABS($H55)/ABS($I55),"")) | K55: =IF($J55="","",IF($J55<0.9,"Déficit de FORÇA",IF($J55<=1.1,"Equilibrado","Déficit de VELOCIDADE"))) | L55: =IF($K55="","",IF($K55="Déficit de FORÇA","Cargas altas: 80–90% 1RM + LPO pesado",IF($K55="Equilibrado","Misto: alternar força máxima e balístico","Balístico: 0–40% 1RM, jump squat e pliometria reativa")))
A56: =IF(Cadastro!$B28="","",Cadastro!$B28) | B56: =IF($A56="","",IFERROR(Cadastro!$P28,"")) | E56: =IFERROR($C56/$B56,"") | F56: =IFERROR($C56*$D56/4,"") -> 0 | G56: =IFERROR($F56/$B56,"") | H56: =IFERROR(-$E56/$D56,"") | J56: =IF(OR($I56="",$H56=""),"",IFERROR(ABS($H56)/ABS($I56),"")) | K56: =IF($J56="","",IF($J56<0.9,"Déficit de FORÇA",IF($J56<=1.1,"Equilibrado","Déficit de VELOCIDADE"))) | L56: =IF($K56="","",IF($K56="Déficit de FORÇA","Cargas altas: 80–90% 1RM + LPO pesado",IF($K56="Equilibrado","Misto: alternar força máxima e balístico","Balístico: 0–40% 1RM, jump squat e pliometria reativa")))
A57: =IF(Cadastro!$B29="","",Cadastro!$B29) | B57: =IF($A57="","",IFERROR(Cadastro!$P29,"")) | E57: =IFERROR($C57/$B57,"") | F57: =IFERROR($C57*$D57/4,"") -> 0 | G57: =IFERROR($F57/$B57,"") | H57: =IFERROR(-$E57/$D57,"") | J57: =IF(OR($I57="",$H57=""),"",IFERROR(ABS($H57)/ABS($I57),"")) | K57: =IF($J57="","",IF($J57<0.9,"Déficit de FORÇA",IF($J57<=1.1,"Equilibrado","Déficit de VELOCIDADE"))) | L57: =IF($K57="","",IF($K57="Déficit de FORÇA","Cargas altas: 80–90% 1RM + LPO pesado",IF($K57="Equilibrado","Misto: alternar força máxima e balístico","Balístico: 0–40% 1RM, jump squat e pliometria reativa")))
A58: =IF(Cadastro!$B30="","",Cadastro!$B30) | B58: =IF($A58="","",IFERROR(Cadastro!$P30,"")) | E58: =IFERROR($C58/$B58,"") | F58: =IFERROR($C58*$D58/4,"") -> 0 | G58: =IFERROR($F58/$B58,"") | H58: =IFERROR(-$E58/$D58,"") | J58: =IF(OR($I58="",$H58=""),"",IFERROR(ABS($H58)/ABS($I58),"")) | K58: =IF($J58="","",IF($J58<0.9,"Déficit de FORÇA",IF($J58<=1.1,"Equilibrado","Déficit de VELOCIDADE"))) | L58: =IF($K58="","",IF($K58="Déficit de FORÇA","Cargas altas: 80–90% 1RM + LPO pesado",IF($K58="Equilibrado","Misto: alternar força máxima e balístico","Balístico: 0–40% 1RM, jump squat e pliometria reativa")))
A59: =IF(Cadastro!$B31="","",Cadastro!$B31) | B59: =IF($A59="","",IFERROR(Cadastro!$P31,"")) | E59: =IFERROR($C59/$B59,"") | F59: =IFERROR($C59*$D59/4,"") -> 0 | G59: =IFERROR($F59/$B59,"") | H59: =IFERROR(-$E59/$D59,"") | J59: =IF(OR($I59="",$H59=""),"",IFERROR(ABS($H59)/ABS($I59),"")) | K59: =IF($J59="","",IF($J59<0.9,"Déficit de FORÇA",IF($J59<=1.1,"Equilibrado","Déficit de VELOCIDADE"))) | L59: =IF($K59="","",IF($K59="Déficit de FORÇA","Cargas altas: 80–90% 1RM + LPO pesado",IF($K59="Equilibrado","Misto: alternar força máxima e balístico","Balístico: 0–40% 1RM, jump squat e pliometria reativa")))
... A75: =IF(Cadastro!$B47="","",Cadastro!$B47) | B75: =IF($A75="","",IFERROR(Cadastro!$P47,"")) | E75: =IFERROR($C75/$B75,"") | F75: =IFERROR($C75*$D75/4,"") -> 0 | G75: =IFERROR($F75/$B75,"") | H75: =IFERROR(-$E75/$D75,"") | J75: =IF(OR($I75="",$H75=""),"",IFERROR(ABS($H75)/ABS($I75),"")) | K75: =IF($J75="","",IF($J75<0.9,"Déficit de FORÇA",IF($J75<=1.1,"Equilibrado","Déficit de VELOCIDADE"))) | L75: =IF($K75="","",IF($K75="Déficit de FORÇA","Cargas altas: 80–90% 1RM + LPO pesado",IF($K75="Equilibrado","Misto: alternar força máxima e balístico","Balístico: 0–40% 1RM, jump squat e pliometria reativa")))
A77: LEIA ANTES DE USAR — o treino individualizado pelo desequilíbrio F-V mostrou bons resultados em alguns estudos (Jiménez-Reyes et al., 2017 e 2019) e ganhos de F0, V0 e altura de salto em meta-análises recentes, mas ensaios controlados independentes não reproduziram a superioridade sobre um programa bem feito não individualizado (Lindberg et al., 2021; Solberg et al., 2025), e há questionamento de que parte do efeito seja aprendizado da tarefa e não adaptação neuromuscular (Bobbert et al., 2024). Use o perfil como MAIS UMA informação para decidir a ênfase do bloco — não como regra única de prescrição. A base continua sendo elevar a força máxima e a Pmax.

Sheet Exercícios
A1: BIBLIOTECA DE EXERCÍCIOS
A2: Cada exercício cadastrado aqui fica disponível no menu suspenso da aba Prescrição, que puxa automaticamente categoria, fundamento e capacidade física.
A6: ID | B6: Exercício | C6: Categoria | D6: Fundamento | E6: Capacidade Física | F6: Objetivo | G6: Descrição / Execução | H6: Material | I6: Nº de Atletas | J6: Duração Sug. (min) | K6: Intensidade Sug. | L6: PSE Sug. | M6: Nível | N6: Link de Vídeo
A7: =IF($B7="","","EX-"&TEXT(ROW()-6,"000")) -> EX-001 | B7: Saque flutuante de apoio | C7: Técnico | D7: Saque | E7: Coordenação | F7: Precisão e constância do saque flutuante | G7: Séries de 10 saques por zona alvo (1, 5 e 6). Contato firme no centro da bola, sem rotação, braço freado no impacto. | H7: Bolas, cones/alvos | I7: 1 | J7: 12 | K7: Moderada | L7: 4 | M7: Iniciante
A8: =IF($B8="","","EX-"&TEXT(ROW()-6,"000")) -> EX-002 | B8: Saque viagem no fundo (jump float) | C8: Técnico | D8: Saque | E8: Coordenação | F8: Saque flutuante com salto e maior velocidade | G8: Passada de 2–3 tempos, salto vertical, contato seco. 3 blocos de 8 saques com alvo no fundo da quadra. | H8: Bolas | I8: 1 | J8: 12 | K8: Alta | L8: 5 | M8: Intermediário
A9: =IF($B9="","","EX-"&TEXT(ROW()-6,"000")) -> EX-003 | B9: Saque potente com salto | C9: Técnico | D9: Saque | E9: Força Explosiva/Potência | F9: Velocidade e agressividade no saque | G9: 4 séries de 6 saques em potência máxima, alternando zona 1 e zona 5. Pausa completa entre séries. | H9: Bolas | I9: 1 | J9: 15 | K9: Muito Alta | L9: 7 | M9: Avançado
A10: =IF($B10="","","EX-"&TEXT(ROW()-6,"000")) -> EX-004 | B10: Recepção em duplas com bola dirigida | C10: Técnico | D10: Recepção (Passe) | E10: Coordenação | F10: Plataforma estável e passe ao alvo | G10: Técnico lança bolas alternadas; atleta recebe para o alvo em zona 2/3. 3 x 15 repetições. | H10: Bolas, alvo/cesto | I10: 2 | J10: 12 | K10: Moderada | L10: 4 | M10: Iniciante
A11: =IF($B11="","","EX-"&TEXT(ROW()-6,"000")) -> EX-005 | B11: Recepção de saque em sistema de 2 passadores | C11: Técnico | D11: Recepção (Passe) | E11: Coordenação | F11: Leitura de trajetória e responsabilidade de zona | G11: Sacador real do outro lado. Passadores em L; 20 saques por rodízio, meta de 70% de passes A/B. | H11: Bolas, rede | I11: 4 | J11: 20 | K11: Alta | L11: 6 | M11: Intermediário
A12: =IF($B12="","","EX-"&TEXT(ROW()-6,"000")) -> EX-006 | B12: Manchete de deslocamento lateral (leque) | C12: Técnico | D12: Recepção (Passe) | E12: Agilidade/COD | F12: Deslocamento e recepção fora da base | G12: Bolas alternadas à direita e à esquerda; deslocamento em passo lateral e retorno à base. 4 x 30 s. | H12: Bolas | I12: 1 | J12: 10 | K12: Alta | L12: 6 | M12: Intermediário
A13: =IF($B13="","","EX-"&TEXT(ROW()-6,"000")) -> EX-007 | B13: Levantamento em suspensão contra a parede | C13: Técnico | D13: Levantamento | E13: Coordenação | F13: Consistência do toque e ação simétrica das mãos | G13: 3 x 30 toques contra a parede a 3 m, mantendo a bola sem rotação. | H13: Bola, parede | I13: 1 | J13: 8 | K13: Baixa | L13: 3 | M13: Iniciante
A14: =IF($B14="","","EX-"&TEXT(ROW()-6,"000")) -> EX-008 | B14: Levantamento em rede com alvos | C14: Técnico | D14: Levantamento | E14: Coordenação | F14: Precisão de bola alta, rápida e de fundo | G14: Levantador recebe passe do técnico e distribui para alvos em P4, P2 e Pipe. 5 x 12 levantamentos. | H14: Bolas, aros/alvos | I14: 2 | J14: 18 | K14: Moderada | L14: 5 | M14: Intermediário
A15: =IF($B15="","","EX-"&TEXT(ROW()-6,"000")) -> EX-009 | B15: Levantamento invertido (costas) | C15: Técnico | D15: Levantamento | E15: Coordenação | F15: Domínio do levantamento para trás sem sinalizar | G15: 3 x 15 levantamentos de costas para P2 com o técnico corrigindo a extensão de quadril. | H15: Bolas | I15: 2 | J15: 12 | K15: Moderada | L15: 5 | M15: Avançado
A16: =IF($B16="","","EX-"&TEXT(ROW()-6,"000")) -> EX-010 | B16: Ataque de bola alta pela ponta (P4) | C16: Técnico | D16: Ataque | E16: Força Explosiva/Potência | F16: Ritmo de aproximação e ataque em bola alta | G16: 4 x 10 ataques com levantador real. Foco na passada de 3 tempos e no braço em arco. | H16: Bolas, rede | I16: 3 | J16: 18 | K16: Alta | L16: 6 | M16: Intermediário
A17: =IF($B17="","","EX-"&TEXT(ROW()-6,"000")) -> EX-011 | B17: Ataque de primeiro tempo (P3) | C17: Técnico | D17: Ataque | E17: Velocidade | F17: Sincronia central x levantador | G17: 4 x 8 ataques de bola rápida, variando o ponto de contato ao longo da rede. | H17: Bolas, rede | I17: 3 | J17: 15 | K17: Alta | L17: 6 | M17: Avançado
A18: =IF($B18="","","EX-"&TEXT(ROW()-6,"000")) -> EX-012 | B18: Ataque de fundo (Pipe / P6) | C18: Técnico | D18: Ataque | E18: Força Explosiva/Potência | F18: Ataque a partir da linha de 3 m | G18: 3 x 10 ataques de fundo saindo da recepção. Atenção à marca dos 3 m. | H18: Bolas, rede | I18: 3 | J18: 15 | K18: Alta | L18: 6 | M18: Avançado
... A95: =IF($B95="","","EX-"&TEXT(ROW()-6,"000")) -> EX-089 | B95: Levantamento terra | C95: Físico | D95: N/A | E95: Força Máxima | F95: Força máxima de cadeia posterior | G95: Exercício de teste de 1RM; velocidade média no 1RM ≈ 0,24 m/s. | H95: Barra, anilhas | I95: 1 | J95: 25 | K95: Muito Alta | L95: 8 | M95: Avançado
A96: =IF($B96="","","EX-"&TEXT(ROW()-6,"000"))
A97: =IF($B97="","","EX-"&TEXT(ROW()-6,"000"))
A98: =IF($B98="","","EX-"&TEXT(ROW()-6,"000"))
A99: =IF($B99="","","EX-"&TEXT(ROW()-6,"000"))
A100: =IF($B100="","","EX-"&TEXT(ROW()-6,"000"))
A101: =IF($B101="","","EX-"&TEXT(ROW()-6,"000"))
A102: =IF($B102="","","EX-"&TEXT(ROW()-6,"000"))
A103: =IF($B103="","","EX-"&TEXT(ROW()-6,"000"))
A104: =IF($B104="","","EX-"&TEXT(ROW()-6,"000"))
A105: =IF($B105="","","EX-"&TEXT(ROW()-6,"000"))
A106: =IF($B106="","","EX-"&TEXT(ROW()-6,"000"))
A107: =IF($B107="","","EX-"&TEXT(ROW()-6,"000"))
... A206: =IF($B206="","","EX-"&TEXT(ROW()-6,"000"))

Sheet Programa PF
A1: PROGRAMA DE PREPARAÇÃO FÍSICA 2026/2027 — SÉRIES 1 A 8
A2: Reprodução fiel do documento original (Adulto e Sub-19, fases Básica 1.1, 1.2, 2.1 e 3.1). As colunas %1RM, Carga e Pausa são sugestões editáveis; o restante é o conteúdo do documento.
A6: Série | B6: Temporada | C6: Categoria | D6: Fase | E6: Objetivo | F6: Bloco | G6: Esquema (séries/reps) | H6: Ordem | I6: Exercício | J6: Nº de Séries | K6: Repetições | L6: %1RM Sug. | M6: Carga (kg) | N6: Observações
A7: 1 | B7: 2026/2027 | C7: Adulto | D7: Básica 1.1 | E7: Força | F7: Core | G7: 3x25 | H7: 1 | I7: Abdominal reto com braços esticados | J7: 3 | K7: 25 | N7: Do documento original
A8: 1 | B8: 2026/2027 | C8: Adulto | D8: Básica 1.1 | E8: Força | F8: Core | G8: 3x25 | H8: 2 | I8: Dorsal perdigueiro | J8: 3 | K8: 25 | N8: Do documento original
A9: 1 | B9: 2026/2027 | C9: Adulto | D9: Básica 1.1 | E9: Força | F9: Braço | G9: 8/8/6/6 | H9: 1 | I9: Armação de braço | J9: 4 | K9: 8/8/6/6 | L9: 0.75 | N9: Do documento original
A10: 1 | B10: 2026/2027 | C10: Adulto | D10: Básica 1.1 | E10: Força | F10: Braço | G10: 8/8/6/6 | H10: 2 | I10: Supino deitado com halteres | J10: 4 | K10: 8/8/6/6 | L10: 0.75 | N10: Do documento original
A11: 1 | B11: 2026/2027 | C11: Adulto | D11: Básica 1.1 | E11: Força | F11: Braço | G11: 8/8/6/6 | H11: 3 | I11: Puxada alta | J11: 4 | K11: 8/8/6/6 | L11: 0.75 | N11: Do documento original
A12: 1 | B12: 2026/2027 | C12: Adulto | D12: Básica 1.1 | E12: Força | F12: Perna | G12: 8/8/6/6 | H12: 1 | I12: Agachamento profundo | J12: 4 | K12: 8/8/6/6 | L12: 0.75 | N12: Do documento original
A13: 1 | B13: 2026/2027 | C13: Adulto | D13: Básica 1.1 | E13: Força | F13: Perna | G13: 8/8/6/6 | H13: 2 | I13: Stiff com barra | J13: 4 | K13: 8/8/6/6 | L13: 0.75 | N13: Do documento original
A14: 1 | B14: 2026/2027 | C14: Adulto | D14: Básica 1.1 | E14: Força | F14: Perna | G14: 8/8/6/6 | H14: 3 | I14: Afundo lateral sem passada | J14: 4 | K14: 8/8/6/6 | L14: 0.75 | N14: Do documento original
A15: 2 | B15: 2027 | C15: Adulto | D15: Básica 1.1 | E15: Força | F15: Core | G15: 3x25 | H15: 1 | I15: Abdominal cruzado esticado | J15: 3 | K15: 25 | N15: Do documento original
A16: 2 | B16: 2027 | C16: Adulto | D16: Básica 1.1 | E16: Força | F16: Core | G16: 3x25 | H16: 2 | I16: Dorsal reto | J16: 3 | K16: 25 | N16: Do documento original
A17: 2 | B17: 2027 | C17: Adulto | D17: Básica 1.1 | E17: Força | F17: Braço | G17: 8/8/6/6 | H17: 1 | I17: Remada unilateral na polia | J17: 4 | K17: 8/8/6/6 | L17: 0.75 | N17: Do documento original
A18: 2 | B18: 2027 | C18: Adulto | D18: Básica 1.1 | E18: Força | F18: Braço | G18: 8/8/6/6 | H18: 2 | I18: Bíceps / Tríceps | J18: 4 | K18: 8/8/6/6 | L18: 0.75 | N18: Do documento original
A19: 2 | B19: 2027 | C19: Adulto | D19: Básica 1.1 | E19: Força | F19: Braço | G19: 8/8/6/6 | H19: 3 | I19: Pullover deitado com haltere | J19: 4 | K19: 8/8/6/6 | L19: 0.75 | N19: Do documento original
A20: 2 | B20: 2027 | C20: Adulto | D20: Básica 1.1 | E20: Força | F20: Perna | G20: 8/8/6/6 | H20: 1 | I20: Afundo frontal sem passada | J20: 4 | K20: 8/8/6/6 | L20: 0.75 | N20: Do documento original
A21: 2 | B21: 2027 | C21: Adulto | D21: Básica 1.1 | E21: Força | F21: Perna | G21: 8/8/6/6 | H21: 2 | I21: Flexão de joelho unilateral | J21: 4 | K21: 8/8/6/6 | L21: 0.75 | N21: Do documento original
A22: 2 | B22: 2027 | C22: Adulto | D22: Básica 1.1 | E22: Força | F22: Perna | G22: 8/8/6/6 | H22: 3 | I22: Agachamento sumô no minitramp | J22: 4 | K22: 8/8/6/6 | L22: 0.75 | N22: Do documento original
A23: 3 | B23: 2026 | C23: Sub-19 | D23: Fase 1.2 | E23: Força 1 | F23: Braço | G23: carga alta – 8/8/6 | H23: 1 | I23: Supino sentado | J23: 3 | K23: 8/8/6 | L23: 0.8 | N23: Do documento original
A24: 3 | B24: 2026 | C24: Sub-19 | D24: Fase 1.2 | E24: Força 1 | F24: Braço | G24: carga alta – 8/8/6 | H24: 2 | I24: Remada serrote | J24: 3 | K24: 8/8/6 | L24: 0.8 | N24: Do documento original
A25: 3 | B25: 2026 | C25: Sub-19 | D25: Fase 1.2 | E25: Força 1 | F25: Braço | G25: carga alta – 8/8/6 | H25: 3 | I25: Pullover na polia | J25: 3 | K25: 8/8/6 | L25: 0.8 | N25: Do documento original
A26: 3 | B26: 2026 | C26: Sub-19 | D26: Fase 1.2 | E26: Força 1 | F26: Perna | G26: carga alta – 8/8/6 | H26: 1 | I26: Agachamento profundo | J26: 3 | K26: 8/8/6 | L26: 0.8 | N26: Do documento original
A27: 3 | B27: 2026 | C27: Sub-19 | D27: Fase 1.2 | E27: Força 1 | F27: Perna | G27: carga alta – 8/8/6 | H27: 2 | I27: Stiff | J27: 3 | K27: 8/8/6 | L27: 0.8 | N27: Do documento original
A28: 3 | B28: 2026 | C28: Sub-19 | D28: Fase 1.2 | E28: Força 1 | F28: Perna | G28: carga alta – 8/8/6 | H28: 3 | I28: Afundo lateral com tornozeleira | J28: 3 | K28: 8/8/6 | L28: 0.8 | N28: Do documento original
A29: 3 | B29: 2026 | C29: Sub-19 | D29: Fase 1.2 | E29: Força 1 | F29: Core | G29: 3x25 | H29: 1 | I29: Abdominal infra | J29: 3 | K29: 25 | N29: Do documento original
A30: 3 | B30: 2026 | C30: Sub-19 | D30: Fase 1.2 | E30: Força 1 | F30: Core | G30: 3x25 | H30: 2 | I30: Dorsal perdigueiro | J30: 3 | K30: 25 | N30: Do documento original
A31: 4 | B31: 2026 | C31: Sub-19 | D31: Fase 1.2 | E31: Força 1 | F31: Braço | G31: carga alta – 8/8/6 | H31: 1 | I31: Tríceps / Bíceps | J31: 3 | K31: 8/8/6 | L31: 0.8 | N31: Do documento original
A32: 4 | B32: 2026 | C32: Sub-19 | D32: Fase 1.2 | E32: Força 1 | F32: Braço | G32: carga alta – 8/8/6 | H32: 2 | I32: Puxada alta | J32: 3 | K32: 8/8/6 | L32: 0.8 | N32: Do documento original
A33: 4 | B33: 2026 | C33: Sub-19 | D33: Fase 1.2 | E33: Força 1 | F33: Braço | G33: carga alta – 8/8/6 | H33: 3 | I33: Cross-over | J33: 3 | K33: 8/8/6 | L33: 0.8 | N33: Do documento original
A34: 4 | B34: 2026 | C34: Sub-19 | D34: Fase 1.2 | E34: Força 1 | F34: Perna | G34: carga alta – 8/8/6 | H34: 1 | I34: Elevação de calcanhares | J34: 3 | K34: 8/8/6 | L34: 0.8 | N34: Do documento original
A35: 4 | B35: 2026 | C35: Sub-19 | D35: Fase 1.2 | E35: Força 1 | F35: Perna | G35: carga alta – 8/8/6 | H35: 2 | I35: Afundo frontal sem passada com tornozeleira | J35: 3 | K35: 8/8/6 | L35: 0.8 | N35: Do documento original
A36: 4 | B36: 2026 | C36: Sub-19 | D36: Fase 1.2 | E36: Força 1 | F36: Perna | G36: carga alta – 8/8/6 | H36: 3 | I36: Flexão de joelhos (unilateral) | J36: 3 | K36: 8/8/6 | L36: 0.8 | N36: Do documento original
A37: 4 | B37: 2026 | C37: Sub-19 | D37: Fase 1.2 | E37: Força 1 | F37: Core | G37: 3x25 | H37: 1 | I37: Abdominal reto | J37: 3 | K37: 25 | N37: Do documento original
A38: 4 | B38: 2026 | C38: Sub-19 | D38: Fase 1.2 | E38: Força 1 | F38: Core | G38: 3x25 | H38: 2 | I38: Dorsal reto | J38: 3 | K38: 25 | N38: Do documento original
A39: 5 | B39: 2026 | C39: Sub-19 | D39: Fase 2.1 | E39: Potência | F39: Braço | G39: carga alta menos – 10/8/6 | H39: 1 | I39: Supino sentado | J39: 3 | K39: 10/8/6 | L39: 0.65 | N39: Do documento original
A40: 5 | B40: 2026 | C40: Sub-19 | D40: Fase 2.1 | E40: Potência | F40: Braço | G40: carga alta menos – 10/8/6 | H40: 2 | I40: Remada unilateral na polia | J40: 3 | K40: 10/8/6 | L40: 0.65 | N40: Do documento original
A41: 5 | B41: 2026 | C41: Sub-19 | D41: Fase 2.1 | E41: Potência | F41: Braço | G41: carga alta menos – 10/8/6 | H41: 3 | I41: Pullover na polia | J41: 3 | K41: 10/8/6 | L41: 0.65 | N41: Do documento original
A42: 5 | B42: 2026 | C42: Sub-19 | D42: Fase 2.1 | E42: Potência | F42: Perna | G42: carga alta menos – 10/8/6 | H42: 1 | I42: Agachamento | J42: 3 | K42: 10/8/6 | L42: 0.65 | N42: Do documento original
A43: 5 | B43: 2026 | C43: Sub-19 | D43: Fase 2.1 | E43: Potência | F43: Perna | G43: carga alta menos – 10/8/6 | H43: 2 | I43: Stiff | J43: 3 | K43: 10/8/6 | L43: 0.65 | N43: Do documento original
A44: 5 | B44: 2026 | C44: Sub-19 | D44: Fase 2.1 | E44: Potência | F44: Perna | G44: carga alta menos – 10/8/6 | H44: 3 | I44: Salto no caixote | J44: 3 | K44: 10/8/6 | L44: 0.65 | N44: Do documento original
A45: 5 | B45: 2026 | C45: Sub-19 | D45: Fase 2.1 | E45: Potência | F45: Core | G45: 3x20 | H45: 1 | I45: Abdominal cruzado com anilha | J45: 3 | K45: 20 | N45: Do documento original
A46: 6 | B46: 2026 | C46: Sub-19 | D46: Fase 2.1 | E46: Potência | F46: Braço | G46: carga alta menos – 10/8/6 | H46: 1 | I46: Tríceps / Bíceps | J46: 3 | K46: 10/8/6 | L46: 0.65 | N46: Do documento original
A47: 6 | B47: 2026 | C47: Sub-19 | D47: Fase 2.1 | E47: Potência | F47: Braço | G47: carga alta menos – 10/8/6 | H47: 2 | I47: Puxada alta | J47: 3 | K47: 10/8/6 | L47: 0.65 | N47: Do documento original
A48: 6 | B48: 2026 | C48: Sub-19 | D48: Fase 2.1 | E48: Potência | F48: Braço | G48: carga alta menos – 10/8/6 | H48: 3 | I48: Arremesso de bola | J48: 3 | K48: 10/8/6 | L48: 0.65 | N48: Do documento original
A49: 6 | B49: 2026 | C49: Sub-19 | D49: Fase 2.1 | E49: Potência | F49: Perna | G49: carga alta menos – 10/8/6 | H49: 1 | I49: Elevação de calcanhares | J49: 3 | K49: 10/8/6 | L49: 0.65 | N49: Do documento original
A50: 6 | B50: 2026 | C50: Sub-19 | D50: Fase 2.1 | E50: Potência | F50: Perna | G50: carga alta menos – 10/8/6 | H50: 2 | I50: Salto unilateral com sobrepeso | J50: 3 | K50: 10/8/6 | L50: 0.65 | N50: Do documento original
A51: 6 | B51: 2026 | C51: Sub-19 | D51: Fase 2.1 | E51: Potência | F51: Perna | G51: carga alta menos – 10/8/6 | H51: 3 | I51: Flexão de joelhos | J51: 3 | K51: 10/8/6 | L51: 0.65 | N51: Do documento original
A52: 6 | B52: 2026 | C52: Sub-19 | D52: Fase 2.1 | E52: Potência | F52: Core | G52: 3x20 | H52: 1 | I52: Abdominal remador com anilha | J52: 3 | K52: 20 | N52: Do documento original
A53: 7 | B53: 2026 | C53: Sub-19 | D53: Fase 3.1 | E53: Força 3 | F53: Braço | G53: carga alta – 8/8/6/6 | H53: 1 | I53: Tríceps | J53: 4 | K53: 8/8/6/6 | L53: 0.85 | N53: Do documento original
A54: 7 | B54: 2026 | C54: Sub-19 | D54: Fase 3.1 | E54: Força 3 | F54: Braço | G54: carga alta – 8/8/6/6 | H54: 2 | I54: Remada unilateral na polia (perna contrária à frente) | J54: 4 | K54: 8/8/6/6 | L54: 0.85 | N54: Do documento original
A55: 7 | B55: 2026 | C55: Sub-19 | D55: Fase 3.1 | E55: Força 3 | F55: Braço | G55: carga alta – 8/8/6/6 | H55: 3 | I55: Pullover com haltere no banco | J55: 4 | K55: 8/8/6/6 | L55: 0.85 | N55: Do documento original
A56: 7 | B56: 2026 | C56: Sub-19 | D56: Fase 3.1 | E56: Força 3 | F56: Perna | G56: carga alta – 8/8/6/6 | H56: 1 | I56: Agachamento profundo | J56: 4 | K56: 8/8/6/6 | L56: 0.85 | N56: Do documento original
A57: 7 | B57: 2026 | C57: Sub-19 | D57: Fase 3.1 | E57: Força 3 | F57: Perna | G57: carga alta – 8/8/6/6 | H57: 2 | I57: Stiff | J57: 4 | K57: 8/8/6/6 | L57: 0.85 | N57: Do documento original
A58: 7 | B58: 2026 | C58: Sub-19 | D58: Fase 3.1 | E58: Força 3 | F58: Perna | G58: carga alta – 8/8/6/6 | H58: 3 | I58: Afundo lateral com sobrepeso | J58: 4 | K58: 8/8/6/6 | L58: 0.85 | N58: Do documento original
A59: 7 | B59: 2026 | C59: Sub-19 | D59: Fase 3.1 | E59: Força 3 | F59: Core | G59: 3x25 | H59: 1 | I59: Abdominal cruzado com anilha de 20 | J59: 3 | K59: 25 | N59: Do documento original
A60: 8 | B60: 2026 | C60: Sub-19 | D60: Fase 3.1 | E60: Força 3 | F60: Braço | G60: carga alta – 8/8/6/6 | H60: 1 | I60: Bíceps | J60: 4 | K60: 8/8/6/6 | L60: 0.85 | N60: Do documento original
A61: 8 | B61: 2026 | C61: Sub-19 | D61: Fase 3.1 | E61: Força 3 | F61: Braço | G61: carga alta – 8/8/6/6 | H61: 2 | I61: Puxada alta | J61: 4 | K61: 8/8/6/6 | L61: 0.85 | N61: Do documento original
A62: 8 | B62: 2026 | C62: Sub-19 | D62: Fase 3.1 | E62: Força 3 | F62: Braço | G62: carga alta – 8/8/6/6 | H62: 3 | I62: Cross-over supino | J62: 4 | K62: 8/8/6/6 | L62: 0.85 | N62: Do documento original
A63: 8 | B63: 2026 | C63: Sub-19 | D63: Fase 3.1 | E63: Força 3 | F63: Perna | G63: carga alta – 8/8/6/6 | H63: 1 | I63: Elevação de calcanhares | J63: 4 | K63: 8/8/6/6 | L63: 0.85 | N63: Do documento original
A64: 8 | B64: 2026 | C64: Sub-19 | D64: Fase 3.1 | E64: Força 3 | F64: Perna | G64: carga alta – 8/8/6/6 | H64: 2 | I64: Afundo frontal com sobrepeso (sem passada) | J64: 4 | K64: 8/8/6/6 | L64: 0.85 | N64: Do documento original
A65: 8 | B65: 2026 | C65: Sub-19 | D65: Fase 3.1 | E65: Força 3 | F65: Perna | G65: carga alta – 8/8/6/6 | H65: 3 | I65: Flexão de joelhos | J65: 4 | K65: 8/8/6/6 | L65: 0.85 | N65: Do documento original
A66: 8 | B66: 2026 | C66: Sub-19 | D66: Fase 3.1 | E66: Força 3 | F66: Core | G66: 3x25 | H66: 1 | I66: Abdominal reto canivete | J66: 3 | K66: 25 | N66: Do documento original
A68: COMO ESTE PROGRAMA SE ENCAIXA NA PERIODIZAÇÃO EM BLOCOS (aba Bloco Base)
A69: Séries 1 e 2 — Básica 1.1 (Adulto), 8/8/6/6 | H69: Bloco de ACUMULAÇÃO — semanas 1 a 4. Volume alto, intensidade moderada (70–80% 1RM). É aqui que entram a técnica de LPO com carga leve e a pliometria de baixa intensidade.
A70: Séries 3 e 4 — Fase 1.2 'Força 1', carga alta 8/8/6 | H70: Fim da ACUMULAÇÃO e início da TRANSMUTAÇÃO — semanas 4 a 6. Intensidade sobe para 80–88% 1RM no agachamento.
A71: Séries 5 e 6 — Fase 2.1 'Potência', carga alta menos 10/8/6 (já com salto no caixote e arremesso de bola) | H71: Bloco de TRANSMUTAÇÃO — semanas 6 e 7, incluindo o microciclo de CHOQUE. É o momento do jump squat com 30% 1RM, do drop jump e do power clean em intensidade alta.
A72: Séries 7 e 8 — Fase 3.1 'Força 3', carga alta 8/8/6/6 | H72: Bloco de REALIZAÇÃO — semana 8 e o mesociclo seguinte. Volume baixo, intensidade ≥ 90% 1RM, pliometria de alta qualidade e pouco volume.

Sheet Macrociclo
A1: MACROCICLO — PLANEJAMENTO DA TEMPORADA
A2: Defina o período total e divida-o em mesociclos. A Data de Início (C11) é a referência de TODA a numeração de semanas da planilha.
B4: IDENTIFICAÇÃO DO MACROCICLO
B6: Temporada / Época | C6: 2026
B7: Equipe / Clube | C7: Equipe Exemplo de Voleibol
B8: Categoria | C8: Adulto Feminino
B9: Técnico Responsável | C9: (preencher)
B10: Preparador Físico | C10: (preencher)
B11: Data de Início | C11: 46027
B12: Data de Término | C12: 46355
B13: Duração (semanas) | C13: =IFERROR(ROUNDUP(($C$12-$C$11+1)/7,0),"") -> 47
B14: Objetivo Principal | C14: Chegar ao 1º turno do estadual com alto nível técnico-tático e baixo índice de lesões
B15: Competição-Alvo | C15: Campeonato Estadual Adulto — fase final em outubro/2026
A17: DIVISÃO EM MESOCICLOS
A18: Nº | B18: Mesociclo | C18: Período | D18: Data Início | E18: Data Fim | F18: Semanas | G18: Semana Inicial | H18: Volume (%) | I18: Intensidade (%) | J18: Ênfase Física | K18: Ênfase Técnica | L18: Ênfase Tática | M18: Carga-Alvo Semanal (UA) | N18: Competições no Período | O18: Situação
A19: =IF($B19="","",ROW()-18) -> 1 | B19: Meso 1 — Base Geral | C19: Preparatório Geral | D19: 46027 | E19: 46068 | F19: =IF(OR($D19="",$E19=""),0,ROUNDUP(($E19-$D19+1)/7,0)) -> 6 | G19: =IF(OR($D19="",$C$11=""),0,INT(($D19-$C$11)/7)+1) -> 1 | H19: 0.9 | I19: 0.55 | J19: Força máxima, base aeróbia e core | K19: Fundamentos individuais e repetição técnica | L19: Reconhecimento do sistema 5x1 | M19: 2600 | N19: — | O19: Concluído
A20: =IF($B20="","",ROW()-18) -> 2 | B20: Meso 2 — Base Específica | C20: Preparatório Específico | D20: 46069 | E20: 46110 | F20: =IF(OR($D20="",$E20=""),0,ROUNDUP(($E20-$D20+1)/7,0)) -> 6 | G20: =IF(OR($D20="",$C$11=""),0,INT(($D20-$C$11)/7)+1) -> 7 | H20: 0.85 | I20: 0.7 | J20: Força-potência e pliometria introdutória | K20: Técnica sob deslocamento e sob fadiga | L20: Complexos K1 e K2 | M20: 2900 | N20: Amistosos preparatórios | O20: Concluído
A21: =IF($B21="","",ROW()-18) -> 3 | B21: Meso 3 — Pré-Competitivo | C21: Pré-Competitivo | D21: 46111 | E21: 46152 | F21: =IF(OR($D21="",$E21=""),0,ROUNDUP(($E21-$D21+1)/7,0)) -> 6 | G21: =IF(OR($D21="",$C$11=""),0,INT(($D21-$C$11)/7)+1) -> 13 | H21: 0.7 | I21: 0.85 | J21: Potência, pliometria e velocidade | K21: Técnica em situação de jogo | L21: Sistemas de defesa e coberturas | M21: 2700 | N21: Copa regional | O21: Concluído
A22: =IF($B22="","",ROW()-18) -> 4 | B22: Meso 4 — Competitivo I | C22: Competitivo I | D22: 46153 | E22: 46222 | F22: =IF(OR($D22="",$E22=""),0,ROUNDUP(($E22-$D22+1)/7,0)) -> 10 | G22: =IF(OR($D22="",$C$11=""),0,INT(($D22-$C$11)/7)+1) -> 19 | H22: 0.55 | I22: 0.9 | J22: Manutenção de força e potência | K22: Correção pontual e saque sob pressão | L22: Ajustes de scout adversário | M22: 2200 | N22: Estadual — 1º turno | O22: Em execução
A23: =IF($B23="","",ROW()-18) -> 5 | B23: Meso 5 — Competitivo II | C23: Competitivo II | D23: 46223 | E23: 46306 | F23: =IF(OR($D23="",$E23=""),0,ROUNDUP(($E23-$D23+1)/7,0)) -> 12 | G23: =IF(OR($D23="",$C$11=""),0,INT(($D23-$C$11)/7)+1) -> 29 | H23: 0.5 | I23: 0.95 | J23: Manutenção e prevenção de lesões | K23: Refinamento técnico individual | L23: Preparação por adversário | M23: 2000 | N23: Estadual — 2º turno e playoffs | O23: Planejado
A24: =IF($B24="","",ROW()-18) -> 6 | B24: Meso 6 — Transição | C24: Transição | D24: 46307 | E24: 46355 | F24: =IF(OR($D24="",$E24=""),0,ROUNDUP(($E24-$D24+1)/7,0)) -> 7 | G24: =IF(OR($D24="",$C$11=""),0,INT(($D24-$C$11)/7)+1) -> 41 | H24: 0.35 | I24: 0.4 | J24: Recuperação ativa e trabalho compensatório | K24: Atividades lúdicas e técnica livre | L24: Avaliação da temporada | M24: 900 | N24: — | O24: Planejado
A25: =IF($B25="","",ROW()-18) | F25: =IF(OR($D25="",$E25=""),0,ROUNDUP(($E25-$D25+1)/7,0)) -> 0 | G25: =IF(OR($D25="",$C$11=""),0,INT(($D25-$C$11)/7)+1) -> 0
A26: =IF($B26="","",ROW()-18) | F26: =IF(OR($D26="",$E26=""),0,ROUNDUP(($E26-$D26+1)/7,0)) -> 0 | G26: =IF(OR($D26="",$C$11=""),0,INT(($D26-$C$11)/7)+1) -> 0
A27: =IF($B27="","",ROW()-18) | F27: =IF(OR($D27="",$E27=""),0,ROUNDUP(($E27-$D27+1)/7,0)) -> 0 | G27: =IF(OR($D27="",$C$11=""),0,INT(($D27-$C$11)/7)+1) -> 0
A28: =IF($B28="","",ROW()-18) | F28: =IF(OR($D28="",$E28=""),0,ROUNDUP(($E28-$D28+1)/7,0)) -> 0 | G28: =IF(OR($D28="",$C$11=""),0,INT(($D28-$C$11)/7)+1) -> 0
A29: =IF($B29="","",ROW()-18) | F29: =IF(OR($D29="",$E29=""),0,ROUNDUP(($E29-$D29+1)/7,0)) -> 0 | G29: =IF(OR($D29="",$C$11=""),0,INT(($D29-$C$11)/7)+1) -> 0
A30: =IF($B30="","",ROW()-18) | F30: =IF(OR($D30="",$E30=""),0,ROUNDUP(($E30-$D30+1)/7,0)) -> 0 | G30: =IF(OR($D30="",$C$11=""),0,INT(($D30-$C$11)/7)+1) -> 0
B31: TOTAL / MÉDIA | F31: =SUM(F19:F30) -> 47 | H31: =IFERROR(AVERAGE(H19:H30),"") -> 0.64166667 | I31: =IFERROR(AVERAGE(I19:I30),"") -> 0.725 | M31: =IFERROR(SUMPRODUCT($F19:$F30,$M19:$M30),"") -> 101500
B32: Confira: a soma de semanas dos mesociclos deve bater com a Duração (semanas) em C13. A Carga-Alvo total é a soma de (semanas × carga-alvo semanal) de cada mesociclo.

Sheet Mesociclo
A1: MESOCICLO — DETALHAMENTO EM MICROCICLOS
A2: Escolha o mesociclo no menu suspenso: os dados do planejamento são puxados do Macrociclo automaticamente.
B4: SELEÇÃO E RESUMO DO MESOCICLO
B6: Mesociclo selecionado | C6: Meso 5 — Competitivo II
B8: Período | C8: =IFERROR(INDEX(Macrociclo!$C$19:$C$30,MATCH($C$6,Macrociclo!$B$19:$B$30,0)),"") -> Competitivo II | F8: Ênfase Física | G8: =IFERROR(INDEX(Macrociclo!$J$19:$J$30,MATCH($C$6,Macrociclo!$B$19:$B$30,0)),"") -> Manutenção e prevenção de lesões
B9: Data de Início | C9: =IFERROR(INDEX(Macrociclo!$D$19:$D$30,MATCH($C$6,Macrociclo!$B$19:$B$30,0)),"") -> 46223 | F9: Ênfase Técnica | G9: =IFERROR(INDEX(Macrociclo!$K$19:$K$30,MATCH($C$6,Macrociclo!$B$19:$B$30,0)),"") -> Refinamento técnico individual
B10: Data de Término | C10: =IFERROR(INDEX(Macrociclo!$E$19:$E$30,MATCH($C$6,Macrociclo!$B$19:$B$30,0)),"") -> 46306 | F10: Ênfase Tática | G10: =IFERROR(INDEX(Macrociclo!$L$19:$L$30,MATCH($C$6,Macrociclo!$B$19:$B$30,0)),"") -> Preparação por adversário
B11: Duração (semanas) | C11: =IFERROR(INDEX(Macrociclo!$F$19:$F$30,MATCH($C$6,Macrociclo!$B$19:$B$30,0)),"") -> 12 | F11: Competições | G11: =IFERROR(INDEX(Macrociclo!$N$19:$N$30,MATCH($C$6,Macrociclo!$B$19:$B$30,0)),"") -> Estadual — 2º turno e playoffs
B12: Semana Inicial no Macro | C12: =IFERROR(INDEX(Macrociclo!$G$19:$G$30,MATCH($C$6,Macrociclo!$B$19:$B$30,0)),"") -> 29
B13: Volume Planejado | C13: =IFERROR(INDEX(Macrociclo!$H$19:$H$30,MATCH($C$6,Macrociclo!$B$19:$B$30,0)),"") -> 0.5
B14: Intensidade Planejada | C14: =IFERROR(INDEX(Macrociclo!$I$19:$I$30,MATCH($C$6,Macrociclo!$B$19:$B$30,0)),"") -> 0.95
B15: Carga-Alvo Semanal (UA) | C15: =IFERROR(INDEX(Macrociclo!$M$19:$M$30,MATCH($C$6,Macrociclo!$B$19:$B$30,0)),"") -> 2000
A17: MICROCICLOS DO MESOCICLO — PREVISTO × REALIZADO
A18: Nº | B18: Microciclo | C18: Tipo de Microciclo | D18: Data Início | E18: Data Fim | F18: Objetivo do Microciclo | G18: Semana nº | H18: Sessões Previstas | I18: Volume Previsto (min) | J18: PSE Média Prevista | K18: Carga Prevista (UA) | L18: % Cumprido | M18: Observações
A19: =IF($B19="","",ROW()-18) -> 1 | B19: Micro 5.1 | C19: Ordinário | D19: 46244 | E19: 46250 | F19: Retomada do volume após a rodada; ênfase em side-out | G19: =IF(OR($D19="",Macrociclo!$C$11=""),0,INT(($D19-Macrociclo!$C$11)/7)+1) -> 32 | H19: 7 | I19: 530 | J19: 6 | K19: =IF(OR($I19="",$J19=""),0,$I19*$J19) -> 3180 | L19: =IF($K19=0,0,SUMIFS('Carga (PSE)'!$G$8:$G$1007,'Carga (PSE)'!$B$8:$B$1007,$G19)/MAX(1,COUNTIF(Cadastro!$BL$8:$BL$47,"Ativo"))/$K19) -> 1.2840194
A20: =IF($B20="","",ROW()-18) -> 2 | B20: Micro 5.2 | C20: Choque | D20: 46251 | E20: 46257 | F20: Pico de carga física da fase, mantendo o volume técnico | G20: =IF(OR($D20="",Macrociclo!$C$11=""),0,INT(($D20-Macrociclo!$C$11)/7)+1) -> 33 | H20: 7 | I20: 530 | J20: 7 | K20: =IF(OR($I20="",$J20=""),0,$I20*$J20) -> 3710 | L20: =IF($K20=0,0,SUMIFS('Carga (PSE)'!$G$8:$G$1007,'Carga (PSE)'!$B$8:$B$1007,$G20)/MAX(1,COUNTIF(Cadastro!$BL$8:$BL$47,"Ativo"))/$K20) -> 1.0983827
A21: =IF($B21="","",ROW()-18) -> 3 | B21: Micro 5.3 | C21: Ordinário | D21: 46258 | E21: 46264 | F21: Consolidação técnico-tática do sistema defensivo | G21: =IF(OR($D21="",Macrociclo!$C$11=""),0,INT(($D21-Macrociclo!$C$11)/7)+1) -> 34 | H21: 7 | I21: 530 | J21: 6 | K21: =IF(OR($I21="",$J21=""),0,$I21*$J21) -> 3180 | L21: =IF($K21=0,0,SUMIFS('Carga (PSE)'!$G$8:$G$1007,'Carga (PSE)'!$B$8:$B$1007,$G21)/MAX(1,COUNTIF(Cadastro!$BL$8:$BL$47,"Ativo"))/$K21) -> 1.2031161
A22: =IF($B22="","",ROW()-18) -> 4 | B22: Micro 5.4 | C22: Recuperativo | D22: 46265 | E22: 46271 | F22: Redução de volume; recuperação e preparação do jogo | G22: =IF(OR($D22="",Macrociclo!$C$11=""),0,INT(($D22-Macrociclo!$C$11)/7)+1) -> 35 | H22: 5 | I22: 380 | J22: 5 | K22: =IF(OR($I22="",$J22=""),0,$I22*$J22) -> 1900 | L22: =IF($K22=0,0,SUMIFS('Carga (PSE)'!$G$8:$G$1007,'Carga (PSE)'!$B$8:$B$1007,$G22)/MAX(1,COUNTIF(Cadastro!$BL$8:$BL$47,"Ativo"))/$K22) -> 1.0483254
A23: =IF($B23="","",ROW()-18) -> 5 | B23: Micro 5.5 | C23: Pré-Competitivo | D23: 46272 | E23: 46278 | F23: Polimento técnico e preparação por adversário | G23: =IF(OR($D23="",Macrociclo!$C$11=""),0,INT(($D23-Macrociclo!$C$11)/7)+1) -> 36 | H23: 5 | I23: 360 | J23: 5 | K23: =IF(OR($I23="",$J23=""),0,$I23*$J23) -> 1800 | L23: =IF($K23=0,0,SUMIFS('Carga (PSE)'!$G$8:$G$1007,'Carga (PSE)'!$B$8:$B$1007,$G23)/MAX(1,COUNTIF(Cadastro!$BL$8:$BL$47,"Ativo"))/$K23) -> 0
A24: =IF($B24="","",ROW()-18) | G24: =IF(OR($D24="",Macrociclo!$C$11=""),0,INT(($D24-Macrociclo!$C$11)/7)+1) -> 0 | K24: =IF(OR($I24="",$J24=""),0,$I24*$J24) -> 0 | L24: =IF($K24=0,0,SUMIFS('Carga (PSE)'!$G$8:$G$1007,'Carga (PSE)'!$B$8:$B$1007,$G24)/MAX(1,COUNTIF(Cadastro!$BL$8:$BL$47,"Ativo"))/$K24) -> 0
A25: =IF($B25="","",ROW()-18) | G25: =IF(OR($D25="",Macrociclo!$C$11=""),0,INT(($D25-Macrociclo!$C$11)/7)+1) -> 0 | K25: =IF(OR($I25="",$J25=""),0,$I25*$J25) -> 0 | L25: =IF($K25=0,0,SUMIFS('Carga (PSE)'!$G$8:$G$1007,'Carga (PSE)'!$B$8:$B$1007,$G25)/MAX(1,COUNTIF(Cadastro!$BL$8:$BL$47,"Ativo"))/$K25) -> 0
A26: =IF($B26="","",ROW()-18) | G26: =IF(OR($D26="",Macrociclo!$C$11=""),0,INT(($D26-Macrociclo!$C$11)/7)+1) -> 0 | K26: =IF(OR($I26="",$J26=""),0,$I26*$J26) -> 0 | L26: =IF($K26=0,0,SUMIFS('Carga (PSE)'!$G$8:$G$1007,'Carga (PSE)'!$B$8:$B$1007,$G26)/MAX(1,COUNTIF(Cadastro!$BL$8:$BL$47,"Ativo"))/$K26) -> 0
A27: =IF($B27="","",ROW()-18) | G27: =IF(OR($D27="",Macrociclo!$C$11=""),0,INT(($D27-Macrociclo!$C$11)/7)+1) -> 0 | K27: =IF(OR($I27="",$J27=""),0,$I27*$J27) -> 0 | L27: =IF($K27=0,0,SUMIFS('Carga (PSE)'!$G$8:$G$1007,'Carga (PSE)'!$B$8:$B$1007,$G27)/MAX(1,COUNTIF(Cadastro!$BL$8:$BL$47,"Ativo"))/$K27) -> 0
A28: =IF($B28="","",ROW()-18) | G28: =IF(OR($D28="",Macrociclo!$C$11=""),0,INT(($D28-Macrociclo!$C$11)/7)+1) -> 0 | K28: =IF(OR($I28="",$J28=""),0,$I28*$J28) -> 0 | L28: =IF($K28=0,0,SUMIFS('Carga (PSE)'!$G$8:$G$1007,'Carga (PSE)'!$B$8:$B$1007,$G28)/MAX(1,COUNTIF(Cadastro!$BL$8:$BL$47,"Ativo"))/$K28) -> 0
A29: =IF($B29="","",ROW()-18) | G29: =IF(OR($D29="",Macrociclo!$C$11=""),0,INT(($D29-Macrociclo!$C$11)/7)+1) -> 0 | K29: =IF(OR($I29="",$J29=""),0,$I29*$J29) -> 0 | L29: =IF($K29=0,0,SUMIFS('Carga (PSE)'!$G$8:$G$1007,'Carga (PSE)'!$B$8:$B$1007,$G29)/MAX(1,COUNTIF(Cadastro!$BL$8:$BL$47,"Ativo"))/$K29) -> 0
A30: =IF($B30="","",ROW()-18) | G30: =IF(OR($D30="",Macrociclo!$C$11=""),0,INT(($D30-Macrociclo!$C$11)/7)+1) -> 0 | K30: =IF(OR($I30="",$J30=""),0,$I30*$J30) -> 0 | L30: =IF($K30=0,0,SUMIFS('Carga (PSE)'!$G$8:$G$1007,'Carga (PSE)'!$B$8:$B$1007,$G30)/MAX(1,COUNTIF(Cadastro!$BL$8:$BL$47,"Ativo"))/$K30) -> 0
B32: % Cumprido = carga média por atleta ativo realizada na semana (aba Carga (PSE)) ÷ carga prevista do microciclo. Verde = 90–110% do previsto; amarelo = acima; vermelho = abaixo.

Sheet Bloco Base
A1: PERIODIZAÇÃO EM BLOCOS — 2 MESES DE PERÍODO DE BASE
A2: Acumulação → Transmutação → Realização, com microciclos de CHOQUE nas semanas 3 e 7 e descarga na semana 4. Foco em força máxima, força explosiva com movimentos de LPO, agachamento e pliometria.
A4: PARÂMETROS DO BLOCO
A5: Início do bloco (2ª feira) | C5: 46272 | F5: OBJETIVO DO BLOCO — elevar a força máxima de membros inferiores e a taxa de produção de força, criando a base sobre a qual a potência será expressa nos blocos competitivos. LÓGICA — a periodização em blocos concentra poucas capacidades por vez, em vez de desenvolver muitas ao mesmo tempo (Issurin, 2010; Stone et al., 2021). Estudos com esportes coletivos mostram vantagem dos blocos sobre a periodização tradicional em força, potência e salto (Rønnestad et al., 2018; Manchado et al., 2017). CHOQUE — as semanas 3 e 7 concentram a carga deliberadamente para induzir overreaching funcional; espera-se queda transitória do CMJ nessas semanas, com supercompensação após a descarga (Micke et al., 2026). MONITORE o CMJ e o wellness nessas semanas: queda de CMJ acima de 10% por mais de 5 dias exige reduzir a carga.
A6: Sessões de força por semana | C6: 3
A7: Sessões de quadra por semana | C7: 5
A8: Atletas no bloco | C8: 12
A10: MATRIZ SEMANA A SEMANA
A11: Semana | B11: Data Início | C11: Bloco | D11: Microciclo | E11: Ênfase Principal | F11: Sessões de Força | G11: Séries MMII/Sessão | H11: Agachamento (sér.×reps) | I11: %1RM Agach. | J11: Exercício de LPO | K11: LPO (sér.×reps) | L11: %1RM LPO | M11: Pliometria (contatos/sem) | N11: Intensidade Pliométrica | O11: Índice de Volume | P11: Índice de Intensidade | Q11: ACWR Alvo | R11: O que monitorar nesta semana
A12: 1 | B12: =IF($C$5="","",$C$5+($A12-1)*7) -> 46272 | C12: Acumulação | D12: Incorporação | E12: Adaptação anatômica + técnica de LPO | F12: 3 | G12: 13 | H12: 4 × 8 | I12: 0.65 | J12: Power clean a partir do joelho (técnica) | K12: 5 × 3 | L12: 0.55 | M12: 60 | N12: Baixa (solo, CMJ e saltos horizontais) | O12: 0.75 | P12: 0.62 | Q12: 1 | R12: Qualidade técnica do power clean e da aterrissagem. Sem busca de carga.
A13: 2 | B13: =IF($C$5="","",$C$5+($A13-1)*7) -> 46279 | C13: Acumulação | D13: Ordinário | E13: Força máxima de base | F13: 3 | G13: 15 | H13: 4 × 6 | I13: 0.75 | J13: Clean pull | K13: 4 × 4 | L13: 0.7 | M13: 90 | N13: Baixa a média (saltos sobre barreiras 40 cm) | O13: 0.88 | P13: 0.72 | Q13: 1.1 | R13: Velocidade média no agachamento a 75% ≥ 0,62 m/s. PSE das sessões de força entre 6 e 7.
A14: 3 | B14: =IF($C$5="","",$C$5+($A14-1)*7) -> 46286 | C14: Acumulação | D14: CHOQUE | E14: Pico de volume da fase de acumulação | F14: 4 | G14: 18 | H14: 5 × 5 | I14: 0.8 | J14: Power clean | K14: 5 × 3 | L14: 0.75 | M14: 120 | N14: Média (barreiras 50 cm + salto no caixote) | O14: 1 | P14: 0.78 | Q14: 1.3 | R14: SEMANA DE CHOQUE — espere queda de CMJ e piora do Hooper. Monitore diariamente e não some carga de quadra.
A15: 4 | B15: =IF($C$5="","",$C$5+($A15-1)*7) -> 46293 | C15: Descarga | D15: Recuperativo | E15: Assimilação e supercompensação | F15: 2 | G15: 8 | H15: 3 × 5 | I15: 0.7 | J15: Técnica leve (hang high pull) | K15: 3 × 3 | L15: 0.6 | M15: 45 | N15: Baixa (qualidade, volume reduzido) | O15: 0.45 | P15: 0.66 | Q15: 0.75 | R15: Retorno do CMJ ao valor da semana 1 ou acima. Se não voltar, prolongue a descarga.
A16: 5 | B16: =IF($C$5="","",$C$5+($A16-1)*7) -> 46300 | C16: Transmutação | D16: Ordinário | E16: Força máxima | F16: 3 | G16: 13 | H16: 5 × 4 | I16: 0.85 | J16: Power clean | K16: 5 × 2 | L16: 0.82 | M16: 90 | N16: Média (drop jump 40 cm) | O16: 0.75 | P16: 0.85 | Q16: 1.1 | R16: Reteste indireto do 1RM pela velocidade. Ganho esperado de 3 a 6% no agachamento.
A17: 6 | B17: =IF($C$5="","",$C$5+($A17-1)*7) -> 46307 | C17: Transmutação | D17: Ordinário | E17: Força-velocidade | F17: 3 | G17: 12 | H17: 4 × 3 | I17: 0.88 | J17: Clean pull (carga supramáxima) | K17: 4 × 3 | L17: 0.95 | M17: 110 | N17: Média a alta (drop jump 40–50 cm + unilaterais) | O17: 0.7 | P17: 0.9 | Q17: 1.15 | R17: Introduzir jump squat a 30% 1RM. Velocidade média do jump squat ≥ 1,0 m/s.
A18: 7 | B18: =IF($C$5="","",$C$5+($A18-1)*7) -> 46314 | C18: Transmutação | D18: CHOQUE | E18: Sobrecarga concentrada de potência | F18: 4 | G18: 15 | H18: 4 × 3 (cluster 2+2) | I18: 0.9 | J18: Power clean | K18: 6 × 2 | L18: 0.88 | M18: 140 | N18: Alta (drop jump 50 cm + saltos com sobrecarga) | O18: 0.85 | P18: 0.93 | Q18: 1.45 | R18: SEGUNDA SEMANA DE CHOQUE. ACWR chega a ~1,45 de propósito; reduza o volume de saltos de quadra para compensar.
A19: 8 | B19: =IF($C$5="","",$C$5+($A19-1)*7) -> 46321 | C19: Realização | D19: Polimento | E19: Expressão de potência | F19: 3 | G19: 9 | H19: 3 × 2 | I19: 0.92 | J19: Power clean | K19: 4 × 1–2 | L19: 0.9 | M19: 70 | N19: Alta qualidade, volume baixo (CMJ e DJ máximos) | O19: 0.42 | P19: 0.95 | Q19: 0.85 | R19: Reteste de CMJ, salto de ataque e 1RM. Espera-se o pico do bloco no fim desta semana.
A20: TOTAL | F20: =SUM(F12:F19) -> 25 | M20: =SUM(M12:M19) -> 725 | O20: =AVERAGE(O12:O19) -> 0.725 | P20: =AVERAGE(P12:P19) -> 0.80125
A40: SESSÕES-MODELO DA SEMANA (A, B e C) — exercícios do seu programa + LPO e pliometria
A41: Sessão | B41: Dia | C41: Ordem | D41: Exercício | E41: Objetivo | F41: Ref. VBT | G41: Observação de execução
A42: A — Força MMII + LPO | B42: Segunda | C42: 1 | D42: Mobilidade de tornozelo e quadril | E42: Aquecimento | F42: — | G42: 6 exercícios × 8 rep, antes da barra
C43: 2 | D43: Power clean a partir do joelho | E43: Força explosiva (LPO) | F43: — | G43: Interromper a série se a velocidade da barra cair visivelmente
C44: 3 | D44: Agachamento profundo | E44: Força máxima | F44: Agachamento | G44: Exercício-âncora do bloco; controlar pela velocidade média
C45: 4 | D45: Stiff com barra | E45: Força máxima (cadeia posterior) | F45: Terra | G45: Excêntrica de 3 s nas semanas 1 a 4
C46: 5 | D46: Afundo lateral sem passada | E46: Força unilateral | F46: — | G46: Do seu programa (Séries 1, 3 e 7)
C47: 6 | D47: Nórdico de isquiotibiais (excêntrico) | E47: Preventivo | F47: — | G47: 3 × 6, 2x por semana durante todo o bloco
C48: 7 | D48: Abdominal reto com braços esticados + Dorsal perdigueiro | E48: Core | F48: — | G48: 3 × 25, do seu programa (Série 1)
A49: B — Potência, pliometria e MMSS | B49: Quarta | C49: 1 | D49: Rotadores do ombro com elástico | E49: Preventivo (ativação) | F49: — | G49: 3 × 15, antes de qualquer trabalho de ombro
C50: 2 | D50: Agachamento com salto sob carga (jump squat) | E50: Potência | F50: Agachamento | G50: 30% 1RM a partir da semana 6; pausa completa
C51: 3 | D51: Salto no caixote / Drop jump | E51: Pliometria | F51: — | G51: Do seu programa (Série 5); altura conforme a matriz semanal
C52: 4 | D52: Saltos consecutivos sobre barreiras | E52: Pliometria | F52: — | G52: Contato mínimo com o solo; contar os contatos
C53: 5 | D53: Supino deitado com halteres | E53: Força MMSS | F53: Supino | G53: Do seu programa (Série 1)
C54: 6 | D54: Remada unilateral na polia | E54: Força MMSS | F54: — | G54: Do seu programa (Séries 2, 5 e 7)
C55: 7 | D55: Arremesso de bola | E55: Potência MMSS | F55: — | G55: Do seu programa (Série 6)
C56: 8 | D56: Abdominal cruzado esticado + Dorsal reto | E56: Core | F56: — | G56: 3 × 25, do seu programa (Série 2)
A57: C — Força-velocidade e unilateral | B57: Sexta | C57: 1 | D57: Mobilidade de tornozelo e quadril | E57: Aquecimento | F57: — | G57: —
C58: 2 | D58: Snatch pull / Hang high pull | E58: Força explosiva (LPO) | F58: — | G58: Puxadas sem fase de recepção: mesmo estímulo de tripla extensão, técnica mais simples
C59: 3 | D59: Agachamento sumô no minitramp | E59: Força-velocidade | F59: Agachamento | G59: Do seu programa (Série 2)
C60: 4 | D60: Elevação de calcanhares | E60: Preventivo (tornozelo) | F60: — | G60: Do seu programa (Séries 4, 6 e 8); descida lenta de 3 s
C61: 5 | D61: Afundo frontal sem passada com sobrepeso | E61: Força unilateral | F61: — | G61: Do seu programa (Séries 2, 4 e 8)
C62: 6 | D62: Salto unilateral com sobrepeso | E62: Pliometria unilateral | F62: — | G62: Do seu programa (Série 6)
C63: 7 | D63: Pullover deitado com haltere | E63: Força MMSS | F63: — | G63: Do seu programa (Série 2)
C64: 8 | D64: Sprints de 10 e 20 m com mudança de direção | E64: Velocidade | F64: — | G64: Só nas semanas sem choque
C65: 9 | D65: Abdominal remador com anilha | E65: Core | F65: — | G65: 3 × 20, do seu programa (Série 6)
A67: As sessões A, B e C já estão prescritas semana a semana na aba 'Prescrição Força', com séries, repetições, %1RM, carga calculada e velocidade-alvo para o atleta de referência.

Sheet Microciclo
A1: MICROCICLO — PLANEJAMENTO DA SEMANA
A2: Duas linhas por dia (duas sessões possíveis). As datas e os dias da semana são gerados a partir da Data de Início.
A4: IDENTIFICAÇÃO DO MICROCICLO
A5: Microciclo | B5: Micro 5.3
A6: Semana nº no Macrociclo | B6: 34
A7: Data de Início (2ª feira) | B7: 46258
A8: Tipo de Microciclo | B8: Ordinário
A9: Objetivo da Semana | B9: Consolidação técnico-tática do sistema defensivo, mantendo a carga física da fase
A11: SESSÕES DA SEMANA
A12: Dia da Semana | B12: Data | C12: Turno | D12: Tipo de Sessão | E12: Local | F12: Duração (min) | G12: PSE Prevista | H12: Carga Prevista (UA) | I12: Ênfase Técnica | J12: Ênfase Tática | K12: Ênfase Física / Prevenção | L12: Observações
A13: =IF($B13="","",CHOOSE(WEEKDAY($B13,2),"Segunda-feira","Terça-feira","Quarta-feira","Quinta-feira","Sexta-feira","Sábado","Domingo")) -> Segunda-feira | B13: =IF($B$7="","",$B$7+INT((ROW()-13)/2)) -> 46258 | C13: Manhã | D13: Físico (Força) | E13: Sala de musculação | F13: 75 | G13: 7 | H13: =IF(OR($F13="",$G13=""),0,$F13*$G13) -> 525 | I13: — | J13: — | K13: Força máxima: agachamento e terra romeno
A14: =IF($B14="","",CHOOSE(WEEKDAY($B14,2),"Segunda-feira","Terça-feira","Quarta-feira","Quinta-feira","Sexta-feira","Sábado","Domingo")) -> Segunda-feira | B14: =IF($B$7="","",$B$7+INT((ROW()-13)/2)) -> 46258 | C14: Tarde | D14: Técnico-Tático | E14: Ginásio principal | F14: 90 | G14: 6 | H14: =IF(OR($F14="",$G14=""),0,$F14*$G14) -> 540 | I14: Recepção de saque e side-out | J14: Complexo K1 | K14: Ativação e core
A15: =IF($B15="","",CHOOSE(WEEKDAY($B15,2),"Segunda-feira","Terça-feira","Quarta-feira","Quinta-feira","Sexta-feira","Sábado","Domingo")) -> Terça-feira | B15: =IF($B$7="","",$B$7+INT((ROW()-13)/2)) -> 46259 | C15: Manhã | D15: Físico (Potência) | E15: Sala de musculação | F15: 60 | G15: 7 | H15: =IF(OR($F15="",$G15=""),0,$F15*$G15) -> 420 | I15: — | J15: — | K15: Power clean e jump squat
A16: =IF($B16="","",CHOOSE(WEEKDAY($B16,2),"Segunda-feira","Terça-feira","Quarta-feira","Quinta-feira","Sexta-feira","Sábado","Domingo")) -> Terça-feira | B16: =IF($B$7="","",$B$7+INT((ROW()-13)/2)) -> 46259 | C16: Tarde | D16: Técnico-Tático | E16: Ginásio principal | F16: 90 | G16: 7 | H16: =IF(OR($F16="",$G16=""),0,$F16*$G16) -> 630 | I16: Ataque de ponta e primeiro tempo | J16: Complexo K2 | K16: Pliometria de baixo volume
A17: =IF($B17="","",CHOOSE(WEEKDAY($B17,2),"Segunda-feira","Terça-feira","Quarta-feira","Quinta-feira","Sexta-feira","Sábado","Domingo")) -> Quarta-feira | B17: =IF($B$7="","",$B$7+INT((ROW()-13)/2)) -> 46260 | C17: Tarde | D17: Coletivo/Jogo | E17: Ginásio principal | F17: 100 | G17: 8 | H17: =IF(OR($F17="",$G17=""),0,$F17*$G17) -> 800 | I17: Saque sob pressão | J17: Jogo 6x6 com pontuação diferenciada | K17: Prevenção de ombro
A18: =IF($B18="","",CHOOSE(WEEKDAY($B18,2),"Segunda-feira","Terça-feira","Quarta-feira","Quinta-feira","Sexta-feira","Sábado","Domingo")) -> Quarta-feira | B18: =IF($B$7="","",$B$7+INT((ROW()-13)/2)) -> 46260 | H18: =IF(OR($F18="",$G18=""),0,$F18*$G18) -> 0
A19: =IF($B19="","",CHOOSE(WEEKDAY($B19,2),"Segunda-feira","Terça-feira","Quarta-feira","Quinta-feira","Sexta-feira","Sábado","Domingo")) -> Quinta-feira | B19: =IF($B$7="","",$B$7+INT((ROW()-13)/2)) -> 46261 | C19: Manhã | D19: Físico (Condicionamento) | E19: Pista | F19: 50 | G19: 6 | H19: =IF(OR($F19="",$G19=""),0,$F19*$G19) -> 300 | I19: — | J19: — | K19: Intervalado 15/15
A20: =IF($B20="","",CHOOSE(WEEKDAY($B20,2),"Segunda-feira","Terça-feira","Quarta-feira","Quinta-feira","Sexta-feira","Sábado","Domingo")) -> Quinta-feira | B20: =IF($B$7="","",$B$7+INT((ROW()-13)/2)) -> 46261 | C20: Tarde | D20: Técnico-Tático | E20: Ginásio principal | F20: 90 | G20: 7 | H20: =IF(OR($F20="",$G20=""),0,$F20*$G20) -> 630 | I20: Bloqueio e defesa | J20: Sistemas de cobertura | K20: Mobilidade
A21: =IF($B21="","",CHOOSE(WEEKDAY($B21,2),"Segunda-feira","Terça-feira","Quarta-feira","Quinta-feira","Sexta-feira","Sábado","Domingo")) -> Sexta-feira | B21: =IF($B$7="","",$B$7+INT((ROW()-13)/2)) -> 46262 | C21: Tarde | D21: Coletivo/Jogo | E21: Ginásio principal | F21: 110 | G21: 8 | H21: =IF(OR($F21="",$G21=""),0,$F21*$G21) -> 880 | I21: Refinamento do side-out | J21: Preparação por adversário | K21: Ativação
A22: =IF($B22="","",CHOOSE(WEEKDAY($B22,2),"Segunda-feira","Terça-feira","Quarta-feira","Quinta-feira","Sexta-feira","Sábado","Domingo")) -> Sexta-feira | B22: =IF($B$7="","",$B$7+INT((ROW()-13)/2)) -> 46262 | H22: =IF(OR($F22="",$G22=""),0,$F22*$G22) -> 0
A23: =IF($B23="","",CHOOSE(WEEKDAY($B23,2),"Segunda-feira","Terça-feira","Quarta-feira","Quinta-feira","Sexta-feira","Sábado","Domingo")) -> Sábado | B23: =IF($B$7="","",$B$7+INT((ROW()-13)/2)) -> 46263 | C23: Manhã | D23: Recuperação/Regenerativo | E23: Piscina / sala | F23: 50 | G23: 3 | H23: =IF(OR($F23="",$G23=""),0,$F23*$G23) -> 150 | I23: Técnica livre | J23: Vídeo do adversário | K23: Liberação miofascial
A24: =IF($B24="","",CHOOSE(WEEKDAY($B24,2),"Segunda-feira","Terça-feira","Quarta-feira","Quinta-feira","Sexta-feira","Sábado","Domingo")) -> Sábado | B24: =IF($B$7="","",$B$7+INT((ROW()-13)/2)) -> 46263 | H24: =IF(OR($F24="",$G24=""),0,$F24*$G24) -> 0
A25: =IF($B25="","",CHOOSE(WEEKDAY($B25,2),"Segunda-feira","Terça-feira","Quarta-feira","Quinta-feira","Sexta-feira","Sábado","Domingo")) -> Domingo | B25: =IF($B$7="","",$B$7+INT((ROW()-13)/2)) -> 46264 | C25: Manhã | D25: Folga | E25: — | F25: 0 | G25: 0 | H25: =IF(OR($F25="",$G25=""),0,$F25*$G25) -> 0 | I25: — | J25: — | K25: Descanso completo
A26: =IF($B26="","",CHOOSE(WEEKDAY($B26,2),"Segunda-feira","Terça-feira","Quarta-feira","Quinta-feira","Sexta-feira","Sábado","Domingo")) -> Domingo | B26: =IF($B$7="","",$B$7+INT((ROW()-13)/2)) -> 46264 | H26: =IF(OR($F26="",$G26=""),0,$F26*$G26) -> 0
A27: TOTAL DA SEMANA | F27: =SUM(F13:F26) -> 715 | G27: =IFERROR(AVERAGE(G13:G26),"") -> 5.9 | H27: =SUM(H13:H26) -> 4875
A29: RESUMO DA SEMANA — PREVISTO × REALIZADO
A30: SESSÕES PLANEJADAS | C30: DURAÇÃO TOTAL (min) | E30: CARGA PREVISTA (UA) | G30: CARGA REALIZADA — MÉDIA/ATLETA (UA) | J30: % DE CUMPRIMENTO DA CARGA
A31: =COUNTA(D13:D26) -> 10 | C31: =SUM(F13:F26) -> 715 | E31: =SUM(H13:H26) -> 4875 | G31: =IFERROR(SUMIFS('Carga (PSE)'!$G$8:$G$1007,'Carga (PSE)'!$B$8:$B$1007,$B$6)/MAX(1,COUNTIF(Cadastro!$BL$8:$BL$47,"Ativo")),0) -> 3825.9091 | J31: =IFERROR(G31/H27,0) -> 0.78480186
A34: DISTRIBUIÇÃO DE CONTEÚDOS POR DIA (minutos)
A35: Dia | B35: Técnico | C35: Tático | D35: Físico | E35: Preventivo / Prevenção | F35: Recuperação | G35: Total (min) | H35: % da Semana
A36: =IF($A13="","",$A13) -> Segunda-feira | B36: 60 | C36: 30 | D36: 45 | E36: 15 | F36: 10 | G36: =SUM(B36:F36) -> 160 | H36: =IFERROR($G36/$G$43,0) -> 0.17877095
A37: =IF($A15="","",$A15) -> Terça-feira | B37: 50 | C37: 20 | D37: 70 | E37: 15 | F37: 10 | G37: =SUM(B37:F37) -> 165 | H37: =IFERROR($G37/$G$43,0) -> 0.18435754
A38: =IF($A17="","",$A17) -> Quarta-feira | B38: 60 | C38: 40 | D38: 30 | E38: 15 | F38: 10 | G38: =SUM(B38:F38) -> 155 | H38: =IFERROR($G38/$G$43,0) -> 0.17318436
A39: =IF($A19="","",$A19) -> Quinta-feira | B39: 45 | C39: 35 | D39: 60 | E39: 15 | F39: 10 | G39: =SUM(B39:F39) -> 165 | H39: =IFERROR($G39/$G$43,0) -> 0.18435754
A40: =IF($A21="","",$A21) -> Sexta-feira | B40: 70 | C40: 50 | D40: 20 | E40: 15 | F40: 15 | G40: =SUM(B40:F40) -> 170 | H40: =IFERROR($G40/$G$43,0) -> 0.18994413
A41: =IF($A23="","",$A23) -> Sábado | B41: 30 | C41: 20 | D41: 0 | E41: 10 | F41: 20 | G41: =SUM(B41:F41) -> 80 | H41: =IFERROR($G41/$G$43,0) -> 0.089385475
A42: =IF($A25="","",$A25) -> Domingo | B42: 0 | C42: 0 | D42: 0 | E42: 0 | F42: 0 | G42: =SUM(B42:F42) -> 0 | H42: =IFERROR($G42/$G$43,0) -> 0
A43: TOTAL | B43: =SUM(B36:B42) -> 315 | C43: =SUM(C36:C42) -> 195 | D43: =SUM(D36:D42) -> 225 | E43: =SUM(E36:E42) -> 85 | F43: =SUM(F36:F42) -> 75 | G43: =SUM(G36:G42) -> 895 | H43: =IFERROR(SUM(H36:H42),0) -> 1

Sheet Prescrição
A1: PRESCRIÇÃO DO TREINO
A2: Uma linha por exercício prescrito. Escolha o exercício no menu (vem da aba Exercícios) e defina o destinatário: 'Equipe (todos)' ou o nome de um atleta — é assim que o treino chega à Área do Atleta.
A3: RESUMO DA SESSÃO SELECIONADA
A4: Data: | B4: 46265 | E4: EXERCÍCIOS PRESCRITOS | G4: DURAÇÃO TOTAL (min) | I4: CARGA PREVISTA (UA) | K4: PSE MÉDIA PREVISTA | M4: MIN. TÉCNICO | O4: MIN. TÁTICO | Q4: MIN. FÍSICO | S4: MIN. PREVENTIVO
E5: =COUNTIFS($A$8:$A$507,$B$4) -> 12 | G5: =SUMIFS($O$8:$O$507,$A$8:$A$507,$B$4) -> 198 | I5: =SUMIFS($R$8:$R$507,$A$8:$A$507,$B$4) -> 1182 | K5: =IFERROR(AVERAGEIFS($P$8:$P$507,$A$8:$A$507,$B$4),0) -> 5.5 | M5: =SUMIFS($O$8:$O$507,$A$8:$A$507,$B$4,$H$8:$H$507,"Técnico") -> 65 | O5: =SUMIFS($O$8:$O$507,$A$8:$A$507,$B$4,$H$8:$H$507,"Tático") -> 25 | Q5: =SUMIFS($O$8:$O$507,$A$8:$A$507,$B$4,$H$8:$H$507,"Físico") -> 63 | S5: =SUMIFS($O$8:$O$507,$A$8:$A$507,$B$4,$H$8:$H$507,"Preventivo/Compensatório") -> 30
A6: Digite a data em B4 para ver o resumo das sessões daquele dia. Séries × Repetições geram o Volume; Duração × PSE Prevista geram a Carga Prevista em UA (unidades arbitrárias).
A7: Data | B7: Semana | C7: Sessão | D7: Turno | E7: Destinatário | F7: Bloco | G7: Exercício | H7: Categoria | I7: Fundamento | J7: Capacidade Física | K7: Séries | L7: Repetições / Tempo | M7: Carga / Intensidade | N7: Pausa (s) | O7: Duração (min) | P7: PSE Prev. | Q7: Volume | R7: Carga Prev. (UA) | S7: Progressão / Critério | T7: Observações | U7: Índ.
A8: 46265 | B8: =IF($A8="",0,INT(($A8-Macrociclo!$C$11)/7)+1) -> 35 | C8: S1 — Força | D8: Manhã | E8: Equipe (todos) | F8: Aquecimento | G8: Mobilidade de tornozelo e quadril | H8: =IFERROR(INDEX(Exercícios!$C$7:$C$206,MATCH($G8,Exercícios!$B$7:$B$206,0)),"") -> Preventivo/Compensatório | I8: =IFERROR(INDEX(Exercícios!$D$7:$D$206,MATCH($G8,Exercícios!$B$7:$B$206,0)),"") -> N/A | J8: =IFERROR(INDEX(Exercícios!$E$7:$E$206,MATCH($G8,Exercícios!$B$7:$B$206,0)),"") -> Mobilidade/Flexibilidade | K8: 1 | L8: 8 por exercício | M8: Peso corporal | N8: 30 | O8: 10 | P8: 2 | Q8: =IFERROR($K8*$L8,"") | R8: =IF(OR($O8="",$P8=""),0,$O8*$P8) -> 20 | S8: Amplitude completa | T8: EXEMPLO | U8: =IF($A8="",0,IF(AND(OR($E8=Atleta!$C$4,$E8="Equipe (todos)"),$A8>=Atleta!$C$5),MAX($U$7:U7)+1,0)) -> 1
A9: 46265 | B9: =IF($A9="",0,INT(($A9-Macrociclo!$C$11)/7)+1) -> 35 | C9: S1 — Força | D9: Manhã | E9: Equipe (todos) | F9: Ativação / Prevenção | G9: Rotadores do ombro com elástico | H9: =IFERROR(INDEX(Exercícios!$C$7:$C$206,MATCH($G9,Exercícios!$B$7:$B$206,0)),"") -> Preventivo/Compensatório | I9: =IFERROR(INDEX(Exercícios!$D$7:$D$206,MATCH($G9,Exercícios!$B$7:$B$206,0)),"") -> N/A | J9: =IFERROR(INDEX(Exercícios!$E$7:$E$206,MATCH($G9,Exercícios!$B$7:$B$206,0)),"") -> Core/Estabilidade | K9: 3 | L9: 15 | M9: Elástico vermelho | N9: 45 | O9: 10 | P9: 3 | Q9: =IFERROR($K9*$L9,"") -> 45 | R9: =IF(OR($O9="",$P9=""),0,$O9*$P9) -> 30 | S9: Progredir a resistência a cada 2 semanas | T9: EXEMPLO | U9: =IF($A9="",0,IF(AND(OR($E9=Atleta!$C$4,$E9="Equipe (todos)"),$A9>=Atleta!$C$5),MAX($U$7:U8)+1,0)) -> 2
A10: 46265 | B10: =IF($A10="",0,INT(($A10-Macrociclo!$C$11)/7)+1) -> 35 | C10: S1 — Força | D10: Manhã | E10: Equipe (todos) | F10: Parte Principal | G10: Agachamento profundo | H10: =IFERROR(INDEX(Exercícios!$C$7:$C$206,MATCH($G10,Exercícios!$B$7:$B$206,0)),"") -> Físico | I10: =IFERROR(INDEX(Exercícios!$D$7:$D$206,MATCH($G10,Exercícios!$B$7:$B$206,0)),"") -> N/A | J10: =IFERROR(INDEX(Exercícios!$E$7:$E$206,MATCH($G10,Exercícios!$B$7:$B$206,0)),"") -> Força Máxima | K10: 4 | L10: 6 | M10: 75% de 1RM | N10: 180 | O10: 25 | P10: 8 | Q10: =IFERROR($K10*$L10,"") -> 24 | R10: =IF(OR($O10="",$P10=""),0,$O10*$P10) -> 200 | S10: +2,5% se completar todas as séries | T10: EXEMPLO | U10: =IF($A10="",0,IF(AND(OR($E10=Atleta!$C$4,$E10="Equipe (todos)"),$A10>=Atleta!$C$5),MAX($U$7:U9)+1,0)) -> 3
A11: 46265 | B11: =IF($A11="",0,INT(($A11-Macrociclo!$C$11)/7)+1) -> 35 | C11: S1 — Força | D11: Manhã | E11: Equipe (todos) | F11: Parte Principal | G11: Stiff com barra | H11: =IFERROR(INDEX(Exercícios!$C$7:$C$206,MATCH($G11,Exercícios!$B$7:$B$206,0)),"") -> Físico | I11: =IFERROR(INDEX(Exercícios!$D$7:$D$206,MATCH($G11,Exercícios!$B$7:$B$206,0)),"") -> N/A | J11: =IFERROR(INDEX(Exercícios!$E$7:$E$206,MATCH($G11,Exercícios!$B$7:$B$206,0)),"") -> Força Máxima | K11: 4 | L11: 8 | M11: 65% de 1RM | N11: 120 | O11: 18 | P11: 7 | Q11: =IFERROR($K11*$L11,"") -> 32 | R11: =IF(OR($O11="",$P11=""),0,$O11*$P11) -> 126 | S11: Excêntrica de 3 s | T11: EXEMPLO | U11: =IF($A11="",0,IF(AND(OR($E11=Atleta!$C$4,$E11="Equipe (todos)"),$A11>=Atleta!$C$5),MAX($U$7:U10)+1,0)) -> 4
A12: 46265 | B12: =IF($A12="",0,INT(($A12-Macrociclo!$C$11)/7)+1) -> 35 | C12: S1 — Força | D12: Manhã | E12: Equipe (todos) | F12: Parte Principal | G12: Power clean a partir do joelho | H12: =IFERROR(INDEX(Exercícios!$C$7:$C$206,MATCH($G12,Exercícios!$B$7:$B$206,0)),"") -> Físico | I12: =IFERROR(INDEX(Exercícios!$D$7:$D$206,MATCH($G12,Exercícios!$B$7:$B$206,0)),"") -> N/A | J12: =IFERROR(INDEX(Exercícios!$E$7:$E$206,MATCH($G12,Exercícios!$B$7:$B$206,0)),"") -> Força Explosiva/Potência | K12: 4 | L12: 4 | M12: 70% de 1RM | N12: 180 | O12: 20 | P12: 8 | Q12: =IFERROR($K12*$L12,"") -> 16 | R12: =IF(OR($O12="",$P12=""),0,$O12*$P12) -> 160 | S12: Parar a série se a barra desacelerar | T12: EXEMPLO | U12: =IF($A12="",0,IF(AND(OR($E12=Atleta!$C$4,$E12="Equipe (todos)"),$A12>=Atleta!$C$5),MAX($U$7:U11)+1,0)) -> 5
A13: 46265 | B13: =IF($A13="",0,INT(($A13-Macrociclo!$C$11)/7)+1) -> 35 | C13: S1 — Força | D13: Manhã | E13: Equipe (todos) | F13: Complementar | G13: Nórdico de isquiotibiais (excêntrico) | H13: =IFERROR(INDEX(Exercícios!$C$7:$C$206,MATCH($G13,Exercícios!$B$7:$B$206,0)),"") -> Preventivo/Compensatório | I13: =IFERROR(INDEX(Exercícios!$D$7:$D$206,MATCH($G13,Exercícios!$B$7:$B$206,0)),"") -> N/A | J13: =IFERROR(INDEX(Exercícios!$E$7:$E$206,MATCH($G13,Exercícios!$B$7:$B$206,0)),"") -> Força Máxima | K13: 3 | L13: 6 | M13: Peso corporal | N13: 90 | O13: 10 | P13: 6 | Q13: =IFERROR($K13*$L13,"") -> 18 | R13: =IF(OR($O13="",$P13=""),0,$O13*$P13) -> 60 | S13: 2x por semana no bloco | T13: EXEMPLO | U13: =IF($A13="",0,IF(AND(OR($E13=Atleta!$C$4,$E13="Equipe (todos)"),$A13>=Atleta!$C$5),MAX($U$7:U12)+1,0)) -> 6
A14: 46265 | B14: =IF($A14="",0,INT(($A14-Macrociclo!$C$11)/7)+1) -> 35 | C14: S1 — Força | D14: Manhã | E14: Equipe (todos) | F14: Volta à Calma | G14: Alongamento e liberação miofascial | H14: =IFERROR(INDEX(Exercícios!$C$7:$C$206,MATCH($G14,Exercícios!$B$7:$B$206,0)),"") -> Recuperação | I14: =IFERROR(INDEX(Exercícios!$D$7:$D$206,MATCH($G14,Exercícios!$B$7:$B$206,0)),"") -> N/A | J14: =IFERROR(INDEX(Exercícios!$E$7:$E$206,MATCH($G14,Exercícios!$B$7:$B$206,0)),"") -> Mobilidade/Flexibilidade | K14: 1 | L14: 30 s por grupamento | M14: Rolo | N14: 0 | O14: 15 | P14: 2 | Q14: =IFERROR($K14*$L14,"") | R14: =IF(OR($O14="",$P14=""),0,$O14*$P14) -> 30 | S14: — | T14: EXEMPLO | U14: =IF($A14="",0,IF(AND(OR($E14=Atleta!$C$4,$E14="Equipe (todos)"),$A14>=Atleta!$C$5),MAX($U$7:U13)+1,0)) -> 7
A15: 46265 | B15: =IF($A15="",0,INT(($A15-Macrociclo!$C$11)/7)+1) -> 35 | C15: S2 — Técnico-Tático | D15: Tarde | E15: Equipe (todos) | F15: Aquecimento | G15: Recepção em duplas com bola dirigida | H15: =IFERROR(INDEX(Exercícios!$C$7:$C$206,MATCH($G15,Exercícios!$B$7:$B$206,0)),"") -> Técnico | I15: =IFERROR(INDEX(Exercícios!$D$7:$D$206,MATCH($G15,Exercícios!$B$7:$B$206,0)),"") -> Recepção (Passe) | J15: =IFERROR(INDEX(Exercícios!$E$7:$E$206,MATCH($G15,Exercícios!$B$7:$B$206,0)),"") -> Coordenação | K15: 3 | L15: 15 | M15: Bola | N15: 30 | O15: 12 | P15: 4 | Q15: =IFERROR($K15*$L15,"") -> 45 | R15: =IF(OR($O15="",$P15=""),0,$O15*$P15) -> 48 | S15: Meta de 80% ao alvo | T15: EXEMPLO | U15: =IF($A15="",0,IF(AND(OR($E15=Atleta!$C$4,$E15="Equipe (todos)"),$A15>=Atleta!$C$5),MAX($U$7:U14)+1,0)) -> 8
A16: 46265 | B16: =IF($A16="",0,INT(($A16-Macrociclo!$C$11)/7)+1) -> 35 | C16: S2 — Técnico-Tático | D16: Tarde | E16: Equipe (todos) | F16: Parte Principal | G16: Recepção de saque em sistema de 2 passadores | H16: =IFERROR(INDEX(Exercícios!$C$7:$C$206,MATCH($G16,Exercícios!$B$7:$B$206,0)),"") -> Técnico | I16: =IFERROR(INDEX(Exercícios!$D$7:$D$206,MATCH($G16,Exercícios!$B$7:$B$206,0)),"") -> Recepção (Passe) | J16: =IFERROR(INDEX(Exercícios!$E$7:$E$206,MATCH($G16,Exercícios!$B$7:$B$206,0)),"") -> Coordenação | K16: 4 | L16: 20 | M16: Saque real | N16: 60 | O16: 20 | P16: 6 | Q16: =IFERROR($K16*$L16,"") -> 80 | R16: =IF(OR($O16="",$P16=""),0,$O16*$P16) -> 120 | S16: Meta de 70% de passes A/B | T16: EXEMPLO | U16: =IF($A16="",0,IF(AND(OR($E16=Atleta!$C$4,$E16="Equipe (todos)"),$A16>=Atleta!$C$5),MAX($U$7:U15)+1,0)) -> 9
A17: 46265 | B17: =IF($A17="",0,INT(($A17-Macrociclo!$C$11)/7)+1) -> 35 | C17: S2 — Técnico-Tático | D17: Tarde | E17: Equipe (todos) | F17: Parte Principal | G17: Ataque de bola alta pela ponta (P4) | H17: =IFERROR(INDEX(Exercícios!$C$7:$C$206,MATCH($G17,Exercícios!$B$7:$B$206,0)),"") -> Técnico | I17: =IFERROR(INDEX(Exercícios!$D$7:$D$206,MATCH($G17,Exercícios!$B$7:$B$206,0)),"") -> Ataque | J17: =IFERROR(INDEX(Exercícios!$E$7:$E$206,MATCH($G17,Exercícios!$B$7:$B$206,0)),"") -> Força Explosiva/Potência | K17: 4 | L17: 10 | M17: Bola alta | N17: 60 | O17: 18 | P17: 6 | Q17: =IFERROR($K17*$L17,"") -> 40 | R17: =IF(OR($O17="",$P17=""),0,$O17*$P17) -> 108 | S17: 5 séries na semana seguinte | T17: EXEMPLO | U17: =IF($A17="",0,IF(AND(OR($E17=Atleta!$C$4,$E17="Equipe (todos)"),$A17>=Atleta!$C$5),MAX($U$7:U16)+1,0)) -> 10
A18: 46265 | B18: =IF($A18="",0,INT(($A18-Macrociclo!$C$11)/7)+1) -> 35 | C18: S2 — Técnico-Tático | D18: Tarde | E18: Equipe (todos) | F18: Parte Principal | G18: Complexo I (K1) — recepção, levantamento e ataque | H18: =IFERROR(INDEX(Exercícios!$C$7:$C$206,MATCH($G18,Exercícios!$B$7:$B$206,0)),"") -> Tático | I18: =IFERROR(INDEX(Exercícios!$D$7:$D$206,MATCH($G18,Exercícios!$B$7:$B$206,0)),"") -> Jogo/Coletivo | J18: =IFERROR(INDEX(Exercícios!$E$7:$E$206,MATCH($G18,Exercícios!$B$7:$B$206,0)),"") -> N/A | K18: 1 | L18: 20 tentativas | M18: Jogo | N18: 90 | O18: 25 | P18: 7 | Q18: =IFERROR($K18*$L18,"") | R18: =IF(OR($O18="",$P18=""),0,$O18*$P18) -> 175 | S18: Meta de 60% de side-out | T18: EXEMPLO | U18: =IF($A18="",0,IF(AND(OR($E18=Atleta!$C$4,$E18="Equipe (todos)"),$A18>=Atleta!$C$5),MAX($U$7:U17)+1,0)) -> 11
A19: 46265 | B19: =IF($A19="",0,INT(($A19-Macrociclo!$C$11)/7)+1) -> 35 | C19: S2 — Técnico-Tático | D19: Tarde | E19: Lucas Prado Bittencourt | F19: Complementar | G19: Saque potente com salto | H19: =IFERROR(INDEX(Exercícios!$C$7:$C$206,MATCH($G19,Exercícios!$B$7:$B$206,0)),"") -> Técnico | I19: =IFERROR(INDEX(Exercícios!$D$7:$D$206,MATCH($G19,Exercícios!$B$7:$B$206,0)),"") -> Saque | J19: =IFERROR(INDEX(Exercícios!$E$7:$E$206,MATCH($G19,Exercícios!$B$7:$B$206,0)),"") -> Força Explosiva/Potência | K19: 4 | L19: 6 | M19: Máxima | N19: 90 | O19: 15 | P19: 7 | Q19: =IFERROR($K19*$L19,"") -> 24 | R19: =IF(OR($O19="",$P19=""),0,$O19*$P19) -> 105 | S19: Registrar acertos por série | T19: EXEMPLO — treino individual | U19: =IF($A19="",0,IF(AND(OR($E19=Atleta!$C$4,$E19="Equipe (todos)"),$A19>=Atleta!$C$5),MAX($U$7:U18)+1,0)) -> 0
A20: 46267 | B20: =IF($A20="",0,INT(($A20-Macrociclo!$C$11)/7)+1) -> 35 | C20: S3 — Potência | D20: Manhã | E20: Equipe (todos) | F20: Parte Principal | G20: Agachamento com salto sob carga (jump squat) | H20: =IFERROR(INDEX(Exercícios!$C$7:$C$206,MATCH($G20,Exercícios!$B$7:$B$206,0)),"") -> Físico | I20: =IFERROR(INDEX(Exercícios!$D$7:$D$206,MATCH($G20,Exercícios!$B$7:$B$206,0)),"") -> N/A | J20: =IFERROR(INDEX(Exercícios!$E$7:$E$206,MATCH($G20,Exercícios!$B$7:$B$206,0)),"") -> Força Explosiva/Potência | K20: 5 | L20: 4 | M20: 30% de 1RM | N20: 120 | O20: 18 | P20: 7 | Q20: =IFERROR($K20*$L20,"") -> 20 | R20: =IF(OR($O20="",$P20=""),0,$O20*$P20) -> 126 | S20: Velocidade acima de 1,0 m/s | T20: EXEMPLO | U20: =IF($A20="",0,IF(AND(OR($E20=Atleta!$C$4,$E20="Equipe (todos)"),$A20>=Atleta!$C$5),MAX($U$7:U19)+1,0)) -> 12
A21: 46267 | B21: =IF($A21="",0,INT(($A21-Macrociclo!$C$11)/7)+1) -> 35 | C21: S3 — Potência | D21: Manhã | E21: Equipe (todos) | F21: Parte Principal | G21: Salto em profundidade (drop jump) | H21: =IFERROR(INDEX(Exercícios!$C$7:$C$206,MATCH($G21,Exercícios!$B$7:$B$206,0)),"") -> Físico | I21: =IFERROR(INDEX(Exercícios!$D$7:$D$206,MATCH($G21,Exercícios!$B$7:$B$206,0)),"") -> N/A | J21: =IFERROR(INDEX(Exercícios!$E$7:$E$206,MATCH($G21,Exercícios!$B$7:$B$206,0)),"") -> Pliometria | K21: 5 | L21: 5 | M21: Caixa de 40 cm | N21: 120 | O21: 15 | P21: 7 | Q21: =IFERROR($K21*$L21,"") -> 25 | R21: =IF(OR($O21="",$P21=""),0,$O21*$P21) -> 105 | S21: Progredir só com boa aterrissagem | T21: EXEMPLO | U21: =IF($A21="",0,IF(AND(OR($E21=Atleta!$C$4,$E21="Equipe (todos)"),$A21>=Atleta!$C$5),MAX($U$7:U20)+1,0)) -> 13
A22: 46267 | B22: =IF($A22="",0,INT(($A22-Macrociclo!$C$11)/7)+1) -> 35 | C22: S4 — Coletivo | D22: Tarde | E22: Equipe (todos) | F22: Parte Principal | G22: Complexo II (K2) — bloqueio, defesa e contra-ataque | H22: =IFERROR(INDEX(Exercícios!$C$7:$C$206,MATCH($G22,Exercícios!$B$7:$B$206,0)),"") -> Tático | I22: =IFERROR(INDEX(Exercícios!$D$7:$D$206,MATCH($G22,Exercícios!$B$7:$B$206,0)),"") -> Jogo/Coletivo | J22: =IFERROR(INDEX(Exercícios!$E$7:$E$206,MATCH($G22,Exercícios!$B$7:$B$206,0)),"") -> N/A | K22: 1 | L22: 20 séries | M22: Jogo | N22: 60 | O22: 25 | P22: 7 | Q22: =IFERROR($K22*$L22,"") | R22: =IF(OR($O22="",$P22=""),0,$O22*$P22) -> 175 | S22: Avaliar eficiência do contra-ataque | T22: EXEMPLO | U22: =IF($A22="",0,IF(AND(OR($E22=Atleta!$C$4,$E22="Equipe (todos)"),$A22>=Atleta!$C$5),MAX($U$7:U21)+1,0)) -> 14
A23: 46267 | B23: =IF($A23="",0,INT(($A23-Macrociclo!$C$11)/7)+1) -> 35 | C23: S4 — Coletivo | D23: Tarde | E23: Equipe (todos) | F23: Parte Principal | G23: Jogo 6x6 com pontuação diferenciada | H23: =IFERROR(INDEX(Exercícios!$C$7:$C$206,MATCH($G23,Exercícios!$B$7:$B$206,0)),"") -> Tático | I23: =IFERROR(INDEX(Exercícios!$D$7:$D$206,MATCH($G23,Exercícios!$B$7:$B$206,0)),"") -> Jogo/Coletivo | J23: =IFERROR(INDEX(Exercícios!$E$7:$E$206,MATCH($G23,Exercícios!$B$7:$B$206,0)),"") -> N/A | K23: 3 | L23: sets a 15 | M23: Jogo | N23: 120 | O23: 30 | P23: 8 | Q23: =IFERROR($K23*$L23,"") | R23: =IF(OR($O23="",$P23=""),0,$O23*$P23) -> 240 | S23: — | T23: EXEMPLO | U23: =IF($A23="",0,IF(AND(OR($E23=Atleta!$C$4,$E23="Equipe (todos)"),$A23>=Atleta!$C$5),MAX($U$7:U22)+1,0)) -> 15
B24: =IF($A24="",0,INT(($A24-Macrociclo!$C$11)/7)+1) -> 0 | H24: =IFERROR(INDEX(Exercícios!$C$7:$C$206,MATCH($G24,Exercícios!$B$7:$B$206,0)),"") | I24: =IFERROR(INDEX(Exercícios!$D$7:$D$206,MATCH($G24,Exercícios!$B$7:$B$206,0)),"") | J24: =IFERROR(INDEX(Exercícios!$E$7:$E$206,MATCH($G24,Exercícios!$B$7:$B$206,0)),"") | Q24: =IFERROR($K24*$L24,"") -> 0 | R24: =IF(OR($O24="",$P24=""),0,$O24*$P24) -> 0 | U24: =IF($A24="",0,IF(AND(OR($E24=Atleta!$C$4,$E24="Equipe (todos)"),$A24>=Atleta!$C$5),MAX($U$7:U23)+1,0)) -> 0
B25: =IF($A25="",0,INT(($A25-Macrociclo!$C$11)/7)+1) -> 0 | H25: =IFERROR(INDEX(Exercícios!$C$7:$C$206,MATCH($G25,Exercícios!$B$7:$B$206,0)),"") | I25: =IFERROR(INDEX(Exercícios!$D$7:$D$206,MATCH($G25,Exercícios!$B$7:$B$206,0)),"") | J25: =IFERROR(INDEX(Exercícios!$E$7:$E$206,MATCH($G25,Exercícios!$B$7:$B$206,0)),"") | Q25: =IFERROR($K25*$L25,"") -> 0 | R25: =IF(OR($O25="",$P25=""),0,$O25*$P25) -> 0 | U25: =IF($A25="",0,IF(AND(OR($E25=Atleta!$C$4,$E25="Equipe (todos)"),$A25>=Atleta!$C$5),MAX($U$7:U24)+1,0)) -> 0
B26: =IF($A26="",0,INT(($A26-Macrociclo!$C$11)/7)+1) -> 0 | H26: =IFERROR(INDEX(Exercícios!$C$7:$C$206,MATCH($G26,Exercícios!$B$7:$B$206,0)),"") | I26: =IFERROR(INDEX(Exercícios!$D$7:$D$206,MATCH($G26,Exercícios!$B$7:$B$206,0)),"") | J26: =IFERROR(INDEX(Exercícios!$E$7:$E$206,MATCH($G26,Exercícios!$B$7:$B$206,0)),"") | Q26: =IFERROR($K26*$L26,"") -> 0 | R26: =IF(OR($O26="",$P26=""),0,$O26*$P26) -> 0 | U26: =IF($A26="",0,IF(AND(OR($E26=Atleta!$C$4,$E26="Equipe (todos)"),$A26>=Atleta!$C$5),MAX($U$7:U25)+1,0)) -> 0
B27: =IF($A27="",0,INT(($A27-Macrociclo!$C$11)/7)+1) -> 0 | H27: =IFERROR(INDEX(Exercícios!$C$7:$C$206,MATCH($G27,Exercícios!$B$7:$B$206,0)),"") | I27: =IFERROR(INDEX(Exercícios!$D$7:$D$206,MATCH($G27,Exercícios!$B$7:$B$206,0)),"") | J27: =IFERROR(INDEX(Exercícios!$E$7:$E$206,MATCH($G27,Exercícios!$B$7:$B$206,0)),"") | Q27: =IFERROR($K27*$L27,"") -> 0 | R27: =IF(OR($O27="",$P27=""),0,$O27*$P27) -> 0 | U27: =IF($A27="",0,IF(AND(OR($E27=Atleta!$C$4,$E27="Equipe (todos)"),$A27>=Atleta!$C$5),MAX($U$7:U26)+1,0)) -> 0
B28: =IF($A28="",0,INT(($A28-Macrociclo!$C$11)/7)+1) -> 0 | H28: =IFERROR(INDEX(Exercícios!$C$7:$C$206,MATCH($G28,Exercícios!$B$7:$B$206,0)),"") | I28: =IFERROR(INDEX(Exercícios!$D$7:$D$206,MATCH($G28,Exercícios!$B$7:$B$206,0)),"") | J28: =IFERROR(INDEX(Exercícios!$E$7:$E$206,MATCH($G28,Exercícios!$B$7:$B$206,0)),"") | Q28: =IFERROR($K28*$L28,"") -> 0 | R28: =IF(OR($O28="",$P28=""),0,$O28*$P28) -> 0 | U28: =IF($A28="",0,IF(AND(OR($E28=Atleta!$C$4,$E28="Equipe (todos)"),$A28>=Atleta!$C$5),MAX($U$7:U27)+1,0)) -> 0
B29: =IF($A29="",0,INT(($A29-Macrociclo!$C$11)/7)+1) -> 0 | H29: =IFERROR(INDEX(Exercícios!$C$7:$C$206,MATCH($G29,Exercícios!$B$7:$B$206,0)),"") | I29: =IFERROR(INDEX(Exercícios!$D$7:$D$206,MATCH($G29,Exercícios!$B$7:$B$206,0)),"") | J29: =IFERROR(INDEX(Exercícios!$E$7:$E$206,MATCH($G29,Exercícios!$B$7:$B$206,0)),"") | Q29: =IFERROR($K29*$L29,"") -> 0 | R29: =IF(OR($O29="",$P29=""),0,$O29*$P29) -> 0 | U29: =IF($A29="",0,IF(AND(OR($E29=Atleta!$C$4,$E29="Equipe (todos)"),$A29>=Atleta!$C$5),MAX($U$7:U28)+1,0)) -> 0
B30: =IF($A30="",0,INT(($A30-Macrociclo!$C$11)/7)+1) -> 0 | H30: =IFERROR(INDEX(Exercícios!$C$7:$C$206,MATCH($G30,Exercícios!$B$7:$B$206,0)),"") | I30: =IFERROR(INDEX(Exercícios!$D$7:$D$206,MATCH($G30,Exercícios!$B$7:$B$206,0)),"") | J30: =IFERROR(INDEX(Exercícios!$E$7:$E$206,MATCH($G30,Exercícios!$B$7:$B$206,0)),"") | Q30: =IFERROR($K30*$L30,"") -> 0 | R30: =IF(OR($O30="",$P30=""),0,$O30*$P30) -> 0 | U30: =IF($A30="",0,IF(AND(OR($E30=Atleta!$C$4,$E30="Equipe (todos)"),$A30>=Atleta!$C$5),MAX($U$7:U29)+1,0)) -> 0
B31: =IF($A31="",0,INT(($A31-Macrociclo!$C$11)/7)+1) -> 0 | H31: =IFERROR(INDEX(Exercícios!$C$7:$C$206,MATCH($G31,Exercícios!$B$7:$B$206,0)),"") | I31: =IFERROR(INDEX(Exercícios!$D$7:$D$206,MATCH($G31,Exercícios!$B$7:$B$206,0)),"") | J31: =IFERROR(INDEX(Exercícios!$E$7:$E$206,MATCH($G31,Exercícios!$B$7:$B$206,0)),"") | Q31: =IFERROR($K31*$L31,"") -> 0 | R31: =IF(OR($O31="",$P31=""),0,$O31*$P31) -> 0 | U31: =IF($A31="",0,IF(AND(OR($E31=Atleta!$C$4,$E31="Equipe (todos)"),$A31>=Atleta!$C$5),MAX($U$7:U30)+1,0)) -> 0
B32: =IF($A32="",0,INT(($A32-Macrociclo!$C$11)/7)+1) -> 0 | H32: =IFERROR(INDEX(Exercícios!$C$7:$C$206,MATCH($G32,Exercícios!$B$7:$B$206,0)),"") | I32: =IFERROR(INDEX(Exercícios!$D$7:$D$206,MATCH($G32,Exercícios!$B$7:$B$206,0)),"") | J32: =IFERROR(INDEX(Exercícios!$E$7:$E$206,MATCH($G32,Exercícios!$B$7:$B$206,0)),"") | Q32: =IFERROR($K32*$L32,"") -> 0 | R32: =IF(OR($O32="",$P32=""),0,$O32*$P32) -> 0 | U32: =IF($A32="",0,IF(AND(OR($E32=Atleta!$C$4,$E32="Equipe (todos)"),$A32>=Atleta!$C$5),MAX($U$7:U31)+1,0)) -> 0
B33: =IF($A33="",0,INT(($A33-Macrociclo!$C$11)/7)+1) -> 0 | H33: =IFERROR(INDEX(Exercícios!$C$7:$C$206,MATCH($G33,Exercícios!$B$7:$B$206,0)),"") | I33: =IFERROR(INDEX(Exercícios!$D$7:$D$206,MATCH($G33,Exercícios!$B$7:$B$206,0)),"") | J33: =IFERROR(INDEX(Exercícios!$E$7:$E$206,MATCH($G33,Exercícios!$B$7:$B$206,0)),"") | Q33: =IFERROR($K33*$L33,"") -> 0 | R33: =IF(OR($O33="",$P33=""),0,$O33*$P33) -> 0 | U33: =IF($A33="",0,IF(AND(OR($E33=Atleta!$C$4,$E33="Equipe (todos)"),$A33>=Atleta!$C$5),MAX($U$7:U32)+1,0)) -> 0
B34: =IF($A34="",0,INT(($A34-Macrociclo!$C$11)/7)+1) -> 0 | H34: =IFERROR(INDEX(Exercícios!$C$7:$C$206,MATCH($G34,Exercícios!$B$7:$B$206,0)),"") | I34: =IFERROR(INDEX(Exercícios!$D$7:$D$206,MATCH($G34,Exercícios!$B$7:$B$206,0)),"") | J34: =IFERROR(INDEX(Exercícios!$E$7:$E$206,MATCH($G34,Exercícios!$B$7:$B$206,0)),"") | Q34: =IFERROR($K34*$L34,"") -> 0 | R34: =IF(OR($O34="",$P34=""),0,$O34*$P34) -> 0 | U34: =IF($A34="",0,IF(AND(OR($E34=Atleta!$C$4,$E34="Equipe (todos)"),$A34>=Atleta!$C$5),MAX($U$7:U33)+1,0)) -> 0
B35: =IF($A35="",0,INT(($A35-Macrociclo!$C$11)/7)+1) -> 0 | H35: =IFERROR(INDEX(Exercícios!$C$7:$C$206,MATCH($G35,Exercícios!$B$7:$B$206,0)),"") | I35: =IFERROR(INDEX(Exercícios!$D$7:$D$206,MATCH($G35,Exercícios!$B$7:$B$206,0)),"") | J35: =IFERROR(INDEX(Exercícios!$E$7:$E$206,MATCH($G35,Exercícios!$B$7:$B$206,0)),"") | Q35: =IFERROR($K35*$L35,"") -> 0 | R35: =IF(OR($O35="",$P35=""),0,$O35*$P35) -> 0 | U35: =IF($A35="",0,IF(AND(OR($E35=Atleta!$C$4,$E35="Equipe (todos)"),$A35>=Atleta!$C$5),MAX($U$7:U34)+1,0)) -> 0
... B507: =IF($A507="",0,INT(($A507-Macrociclo!$C$11)/7)+1) -> 0 | H507: =IFERROR(INDEX(Exercícios!$C$7:$C$206,MATCH($G507,Exercícios!$B$7:$B$206,0)),"") | I507: =IFERROR(INDEX(Exercícios!$D$7:$D$206,MATCH($G507,Exercícios!$B$7:$B$206,0)),"") | J507: =IFERROR(INDEX(Exercícios!$E$7:$E$206,MATCH($G507,Exercícios!$B$7:$B$206,0)),"") | Q507: =IFERROR($K507*$L507,"") -> 0 | R507: =IF(OR($O507="",$P507=""),0,$O507*$P507) -> 0 | U507: =IF($A507="",0,IF(AND(OR($E507=Atleta!$C$4,$E507="Equipe (todos)"),$A507>=Atleta!$C$5),MAX($U$7:U506)+1,0)) -> 0

Sheet Prescrição Força
A1: PRESCRIÇÃO E CONTROLE DO TREINO DE FORÇA E POTÊNCIA
A2: As 8 semanas do bloco de base já vêm prescritas. A carga em kg sai de %1RM × 1RM atual do atleta de referência; a velocidade-alvo sai da tabela carga-velocidade (editável) à direita.
A3: PARÂMETROS E RESUMO DA SEMANA
A4: Atleta de referência: | C4: Rafael Monteiro Alves | H4: EXERCÍCIOS NA SEMANA | K4: SÉRIES TOTAIS | N4: REPETIÇÕES TOTAIS | Q4: TONELAGEM DA SEMANA (kg) | T4: INTENSIDADE MÉDIA RELATIVA | W4: CONTATOS PLIOMÉTRICOS
A5: Semana do bloco (1 a 8): | C5: 1 | H5: =COUNTIFS($B$8:$B$407,$C$5) -> 23 | K5: =SUMIFS($J$8:$J$407,$B$8:$B$407,$C$5) -> 78 | N5: =SUMIFS($X$8:$X$407,$B$8:$B$407,$C$5) -> 722 | Q5: =SUMIFS($Y$8:$Y$407,$B$8:$B$407,$C$5) -> 11641 | T5: =IFERROR(SUMPRODUCT(($B$8:$B$407=$C$5)*$X$8:$X$407*$L$8:$L$407)/SUMPRODUCT(($B$8:$B$407=$C$5)*$X$8:$X$407*($L$8:$L$407<>"")),0) -> 0.6100823 | W5: =SUMIFS($X$8:$X$407,$B$8:$B$407,$C$5,$H$8:$H$407,"Pliometria") -> 60
A6: Preencha em amarelo o que foi EXECUTADO (carga usada, velocidade obtida, perda de velocidade, RIR e PSE). A tonelagem usa a carga usada quando informada e, na falta dela, a carga calculada. | AD6: TABELA CARGA-VELOCIDADE (editável)
A7: Data | B7: Semana do Bloco | C7: Bloco | D7: Sessão | E7: Destinatário | F7: Ordem | G7: Exercício | H7: Objetivo | I7: Ref. VBT | J7: Séries | K7: Reps | L7: %1RM | M7: 1RM Atual (kg) | N7: Carga Calculada (kg) | O7: Carga Usada (kg) | P7: Velocidade Alvo (m/s) | Q7: Velocidade Obtida (m/s) | R7: Perda de Vel. Limite (%) | S7: Perda de Vel. Obtida (%) | T7: Situação VBT | U7: RIR | V7: PSE | W7: Pausa (s) | X7: Reps Totais | Y7: Tonelagem (kg) | Z7: Zona de Intensidade | AA7: Observações | AB7: Ref. 1RM | AD7: %1RM | AE7: Agachamento — MPV (m/s) | AF7: Supino — MPV (m/s) | AG7: Terra — MV (m/s)
A8: 46272 | B8: =IF($A8="",0,INT(($A8-'Bloco Base'!$C$5)/7)+1) -> 1 | C8: Acumulação | D8: A | E8: Equipe (todos) | F8: 1 | G8: Mobilidade de tornozelo e quadril | H8: Aquecimento | I8: — | J8: 1 | K8: 8 | M8: =IF($AB8="","",IFERROR(INDEX('Força 1RM'!$Q$8:$Y$47,MATCH(IF($E8="Equipe (todos)",$C$4,$E8),'Força 1RM'!$P$8:$P$47,0),MATCH($AB8,'Força 1RM'!$Q$7:$Y$7,0)),"")) | N8: =IFERROR(IF(OR($L8="",$M8="",$M8=0),0,ROUND($L8*$M8*2,0)/2),0) -> 0 | P8: =IFERROR(IF(OR($L8="",$I8="—",$I8=""),"",IF($I8="Agachamento",INDEX($AE$8:$AE$20,MATCH($L8,$AD$8:$AD$20,1)),IF($I8="Supino",INDEX($AF$8:$AF$20,MATCH($L8,$AD$8:$AD$20,1)),IF($I8="Terra",INDEX($AG$8:$AG$20,MATCH($L8,$AD$8:$AD$20,1)),"")))),"") | T8: =IF(OR($R8="",$S8=""),"",IF($S8>$R8,"Acima do limite","Dentro do limite")) | W8: 0 | X8: =IFERROR(IF(OR($J8="",$K8=""),0,$J8*$K8),0) -> 8 | Y8: =IFERROR(IF($X8=0,0,$X8*IF($O8="",$N8,$O8)),0) -> 0 | Z8: =IF($L8="","",IF($L8<0.5,"Balística / Velocidade (<50%)",IF($L8<0.7,"Velocidade-Força (50–69%)",IF($L8<0.8,"Força-Velocidade (70–79%)",IF($L8<0.9,"Força Máxima (80–89%)","Força Máxima Alta (≥90%)"))))) | AD8: 0.4 | AE8: 1.09 | AF8: 0.94 | AG8: 1.05
A9: 46272 | B9: =IF($A9="",0,INT(($A9-'Bloco Base'!$C$5)/7)+1) -> 1 | C9: Acumulação | D9: A | E9: Equipe (todos) | F9: 2 | G9: Power clean a partir do joelho | H9: Força-Velocidade | I9: — | J9: 5 | K9: 3 | L9: 0.55 | M9: =IF($AB9="","",IFERROR(INDEX('Força 1RM'!$Q$8:$Y$47,MATCH(IF($E9="Equipe (todos)",$C$4,$E9),'Força 1RM'!$P$8:$P$47,0),MATCH($AB9,'Força 1RM'!$Q$7:$Y$7,0)),"")) -> 92.5 | N9: =IFERROR(IF(OR($L9="",$M9="",$M9=0),0,ROUND($L9*$M9*2,0)/2),0) -> 51 | P9: =IFERROR(IF(OR($L9="",$I9="—",$I9=""),"",IF($I9="Agachamento",INDEX($AE$8:$AE$20,MATCH($L9,$AD$8:$AD$20,1)),IF($I9="Supino",INDEX($AF$8:$AF$20,MATCH($L9,$AD$8:$AD$20,1)),IF($I9="Terra",INDEX($AG$8:$AG$20,MATCH($L9,$AD$8:$AD$20,1)),"")))),"") | R9: 0.1 | T9: =IF(OR($R9="",$S9=""),"",IF($S9>$R9,"Acima do limite","Dentro do limite")) | W9: 180 | X9: =IFERROR(IF(OR($J9="",$K9=""),0,$J9*$K9),0) -> 15 | Y9: =IFERROR(IF($X9=0,0,$X9*IF($O9="",$N9,$O9)),0) -> 765 | Z9: =IF($L9="","",IF($L9<0.5,"Balística / Velocidade (<50%)",IF($L9<0.7,"Velocidade-Força (50–69%)",IF($L9<0.8,"Força-Velocidade (70–79%)",IF($L9<0.9,"Força Máxima (80–89%)","Força Máxima Alta (≥90%)"))))) -> Velocidade-Força (50–69%) | AB9: Power clean | AD9: 0.45 | AE9: 1.02 | AF9: 0.86 | AG9: 0.98
